uart_receiver/uart_receiver/hdl/uart_receiver.v
module uart_receiver (
  input wire uart_rx,             // UART 資料輸入
  input wire baud_rate_signal,    // Baud rate 驅動訊號
  input wire rst_n,               // 復位訊號（低有效）
  output reg [8:1] data,          // 接收的 8 位資料
  output reg valid_data           // 資料是否有效的標誌
);

  reg state, next_state;          // 狀態與下一狀態
  localparam IDLE = 1'b0;
  localparam RECEIVE = 1'b1;

  reg [3:0] bit_counter, next_bit_counter; // 位元計數器和下一值
  reg [8:1] next_data;                     // 資料暫存
  reg next_valid_data;                     // 有效標誌暫存器

  // 狀態切換邏輯（時序邏輯）
  always @(posedge baud_rate_signal or negedge rst_n) begin
    if (!rst_n) begin
      state <= IDLE;
      data <= 8'b00000000;
      valid_data <= 1'b0;
      bit_counter <= 8;
    end else begin
      state <= next_state;
      data <= next_data;
      valid_data <= next_valid_data;
      bit_counter <= next_bit_counter;
    end
  end

  // 組合邏輯：計算下一狀態和輸出
  always @(*) begin
    // 預設值
    next_state = state;
    next_data = data;
    next_bit_counter = bit_counter;
    next_valid_data = 1'b0;  // 預設為無效

    case (state)
      IDLE: begin
        if (uart_rx == 1'b0) begin
          next_state = RECEIVE;
          next_bit_counter = 8;
        end
      end

      RECEIVE: begin
        if (bit_counter == 0) begin
          if (uart_rx == 1'b1) begin
            next_valid_data = 1'b1; // 資料有效
          end
          next_state = IDLE; // 回到空閒狀態
        end else begin
          next_data[bit_counter] = uart_rx; // 接收資料位
          next_bit_counter = bit_counter - 1;
        end
      end

      default: begin
        next_state = IDLE;
      end
    endcase
  end

endmodule

uart_RandT/hdl/uart_transmitter.v
module uart_transmitter (
  input wire [7:0] data,            // 輸入的 8-bit 資料
  input wire baud_rate_signal,      // 波特率訊號
  input wire start,                 // 傳輸開始訊號
  input wire rst_n,                 // 復位訊號（低有效）
  input wire clk,                   // 時鐘訊號
  output reg uart_tx                // UART 資料輸出
);

  reg [10:0] packed_data;           // 打包的 10-bit 資料（起始位、數據位、停止位）
  reg state, next_state;            // 狀態與下一狀態
  reg [3:0] bit_counter, next_bit_counter; // 位元計數器和下一值
  reg next_uart_tx;                 // 下一時鐘週期的輸出狀態
  localparam IDLE = 1'b0;
  localparam TRANSMIT = 1'b1;

  // 狀態切換與資料更新邏輯（時序邏輯）
  always @(posedge clk or negedge rst_n) begin
    if (!rst_n) begin
      state <= IDLE;
      bit_counter <= 4'd10;
      uart_tx <= 1'b1;              // 默認為高電平
      packed_data <= 11'b0;         // 默認為空
    end else begin
      state <= next_state;
      bit_counter <= next_bit_counter;
      uart_tx <= next_uart_tx;
      if (start && state == IDLE) begin
        packed_data <= {1'b0, data, 1'b1}; // 起始位（0）+ 資料 + 停止位（1）
      end
    end
  end

  // 組合邏輯：計算下一狀態與輸出
  always @(*) begin
    // 預設值
    next_state = state;
    next_bit_counter = bit_counter;
    next_uart_tx = uart_tx;

    case (state)
      IDLE: begin
        next_uart_tx = 1'b1;        // 默認為高電平
        if (start) begin
          next_state = TRANSMIT;
          next_bit_counter = 4'd10;
        end
      end

      TRANSMIT: begin
        if (baud_rate_signal) begin
          if (bit_counter == 0) begin
            next_state = IDLE;      // 傳輸完成，回到空閒狀態
            next_uart_tx = 1'b1;    // 停止位為高電平
          end else begin
            next_bit_counter = bit_counter - 1;
            next_uart_tx = packed_data[bit_counter - 1]; // 輸出當前位元
          end
        end
      end

      default: begin
        next_state = IDLE;
      end
    endcase
  end

endmodule

uart_receiver/baud_rate/hdl/baud_rate_generator.v
module baud_rate_generator (
  input wire clk,
  input wire rst_n,
  output reg baud_rate_signal,
  output reg [13:0] counter
);

  parameter BAUD_RATE_NUMBER = 10416;
  reg baud_rate_next; // 組合邏輯輸出暫存

  // 時序邏輯：只負責時鐘驅動的數值更新
  always @(posedge clk or negedge rst_n) begin
    if (!rst_n) begin
      counter <= BAUD_RATE_NUMBER - 1;
      baud_rate_signal <= 1'b0;
    end else begin
      counter <= (counter == 0) ? BAUD_RATE_NUMBER - 1 : counter - 1;
      baud_rate_signal <= baud_rate_next; // 從組合邏輯取得下一狀態
    end
  end

  // 組合邏輯：計算 baud_rate_signal 的下一狀態
  always @(*) begin
    if (counter == 1) begin
      baud_rate_next = 1'b0;
    end else if (counter == 0) begin
      baud_rate_next = 1'b1;
    end else begin
      baud_rate_next = 1'b0;
    end
  end

endmodule

uart_RandT/xsim/uart_RandT_tb.v
// set the timescale for the simulation
 `timescale 1ns/1ps 
module testbench;  // module of testbench
//  parameter defined
parameter CYCLE = 10; // use CYCLE to describe the clock period
parameter BAUD_RATE_NUMBER = 20;

// localparam
localparam N = 256; 


// input signal use reg
reg clk;
reg rst_n;
reg start;
reg [7:0] data;

// output signal use wire
wire baud_rate_signal;
wire uart_tx;
wire [8:1] result;
wire valid_data;

// interger 
integer j, error;
///// instantiate  module /////
// instantiate the module you finished in following format //
// module_name #(.parameter1(5),.parameter2(3)) unit_name (.port1(...), .port2(...), ...); //
baud_rate_generator baud_rate_generator(
  .clk(clk),
  .rst_n(rst_n),
  .baud_rate_signal(baud_rate_signal)
);

uart_transmitter uart_transmitter(
  .data(data),
  .baud_rate_signal(baud_rate_signal),
  .start(start),
  .rst_n(rst_n),
  .clk(clk),
  .uart_tx(uart_tx)
);

uart_receiver uart_receiver(
  .uart_rx(uart_tx),
  .baud_rate_signal(baud_rate_signal),
  .rst_n(rst_n),
  .data(result),
  .valid_data(valid_data)
);
//  dump the waveform of the simulation for fsdb//
/*initial begin
 $fsdbDumpfile("testbench.fsdb"); 
 $fsdbDumpvars;              
end*/

// dump the waveform of the simulation for vcd//
initial begin
  $dumpfile("testbench.vcd");
  $dumpvars("+mda");
end

// there you can read data from the file,and store in the register.
reg [15:0] golden [0:N];
initial begin
  $readmemb("golden.dat",golden);
end


// generate clk 
always #(CYCLE/2) clk = ~clk; 

// System block set only clock,reset signal and the timeout finish. 
initial begin
  clk = 1;
  rst_n = 1;
  start = 0;
  // system reset
  #(CYCLE) rst_n = 0;
  #(CYCLE) rst_n = 1;
  #(CYCLE*2) start = 1;
end

// output result checking block, control when to sample and verify the result.
integer fp_w;
reg [7:0] correct_data;
integer debug = 0;
/*
initial begin 
  for (j = 0; j < N; j = j + 1) begin
    @(posedge clk);
    data = golden[j][15:8];
    correct_data = golden[j][7:0];
    #(CYCLE * BAUD_RATE_NUMBER * 11);
  end
end
*/

initial begin
// error count
  error = 0;
// Use the same control technique to control when to sample output result.
  wait(rst_n==0);
  wait(rst_n==1);
// adder output for two cycle from input to output
  // you can also write the result to a text file
  fp_w = $fopen("answer.txt");
  for (j = 0; j < N; j = j + 1) begin
    @(posedge clk);
    data = golden[j][15:8];
    correct_data = golden[j][7:0];
    #(CYCLE * BAUD_RATE_NUMBER * 11);
    debug = ~debug;
    if(result !== correct_data) begin
        error = error + 1;
        $display("************* Pattern No.%d is wrong at %t ************", j,$time);
        $display("signal_in = %b, correct data is %b,", data, correct_data);
        $display("but your result is %b !!", result);
      end
      $fdisplay(fp_w, "%b  %b_%b_%b", data, correct_data, result, valid_data);
    //#(CYCLE * BAUD_RATE_NUMBER);
  end

  $fclose(fp_w);

  if(error == 0) begin
    $display("Congratulations!! The functionality of your receiver is correct!!");
  end
  else begin
    $display("error !!");
  end 
  #(CYCLE) $finish; 

end

endmodule

uart_RandT/xsim/testbench.vcd
$date
   Wed Jan 15 02:40:44 2025
$end
$version
  2022.1
$end
$timescale
  1ps
$end
$scope module testbench $end
$var reg 1 ! clk $end
$var reg 1 " rst_n $end
$var reg 1 # start $end
$var reg 8 $ data [7:0] $end
$var wire 1 % baud_rate_signal $end
$var wire 1 & uart_tx $end
$var wire 8 ' result [7:0] $end
$var wire 1 ( valid_data $end
$var integer 32 ) j [31:0] $end
$var integer 32 * error [31:0] $end
$var integer 32 + fp_w [31:0] $end
$var reg 8 , correct_data [7:0] $end
$var integer 32 - debug [31:0] $end
$scope module baud_rate_generator $end
$var wire 1 . clk $end
$var wire 1 / rst_n $end
$var reg 1 0 baud_rate_signal $end
$var reg 14 1 counter [13:0] $end
$var reg 1 2 baud_rate_next $end
$upscope $end
$scope module uart_transmitter $end
$var wire 8 3 data [7:0] $end
$var wire 1 % baud_rate_signal $end
$var wire 1 4 start $end
$var wire 1 5 rst_n $end
$var wire 1 6 clk $end
$var reg 1 7 uart_tx $end
$var reg 11 8 packed_data [10:0] $end
$var reg 1 9 state $end
$var reg 1 : next_state $end
$var reg 4 ; bit_counter [3:0] $end
$var reg 4 < next_bit_counter [3:0] $end
$var reg 1 = next_uart_tx $end
$upscope $end
$scope module uart_receiver $end
$var wire 1 & uart_rx $end
$var wire 1 % baud_rate_signal $end
$var wire 1 > rst_n $end
$var reg 8 ? data [7:0] $end
$var reg 1 @ valid_data $end
$var reg 1 A state $end
$var reg 1 B next_state $end
$var reg 4 C bit_counter [3:0] $end
$var reg 4 D next_bit_counter [3:0] $end
$var reg 8 E next_data [7:0] $end
$var reg 1 F next_valid_data $end
$upscope $end
$upscope $end
$enddefinitions $end
#0
$dumpvars
1!
1"
0#
bx $
x%
x&
bx '
x(
bx )
b0 *
bx +
bx ,
b0 -
1.
1/
x0
bx 1
x2
bx 3
04
15
16
x7
bx 8
09
0:
bx ;
bx <
1=
1>
bx ?
x@
xA
xB
bx C
bx D
bx E
xF
$end
#5000
0!
0.
06
#10000
1!
0"
0%
1&
b0 '
0(
1.
0/
00
b10011 1
02
05
16
17
b0 8
09
b1010 ;
b1010 <
0>
b0 ?
0@
0A
0B
b1000 C
b1000 D
b0 E
0F
#15000
0!
0.
06
#20000
1!
1"
b0 )
b10 +
1.
1/
00
b10010 1
15
16
17
09
b1010 ;
1>
#25000
0!
0.
06
#30000
1!
b0 $
b0 ,
1.
00
b10001 1
b0 3
16
17
09
b1010 ;
#35000
0!
0.
06
#40000
1!
1#
1.
00
b10000 1
14
16
17
b1 8
19
1:
b1010 ;
b1010 <
#45000
0!
0.
06
#50000
1!
1.
00
b1111 1
16
17
19
b1010 ;
#55000
0!
0.
06
#60000
1!
1.
00
b1110 1
16
17
19
b1010 ;
#65000
0!
0.
06
#70000
1!
1.
00
b1101 1
16
17
19
b1010 ;
#75000
0!
0.
06
#80000
1!
1.
00
b1100 1
16
17
19
b1010 ;
#85000
0!
0.
06
#90000
1!
1.
00
b1011 1
16
17
19
b1010 ;
#95000
0!
0.
06
#100000
1!
1.
00
b1010 1
16
17
19
b1010 ;
#105000
0!
0.
06
#110000
1!
1.
00
b1001 1
16
17
19
b1010 ;
#115000
0!
0.
06
#120000
1!
1.
00
b1000 1
16
17
19
b1010 ;
#125000
0!
0.
06
#130000
1!
1.
00
b111 1
16
17
19
b1010 ;
#135000
0!
0.
06
#140000
1!
1.
00
b110 1
16
17
19
b1010 ;
#145000
0!
0.
06
#150000
1!
1.
00
b101 1
16
17
19
b1010 ;
#155000
0!
0.
06
#160000
1!
1.
00
b100 1
16
17
19
b1010 ;
#165000
0!
0.
06
#170000
1!
1.
00
b11 1
16
17
19
b1010 ;
#175000
0!
0.
06
#180000
1!
1.
00
b10 1
16
17
19
b1010 ;
#185000
0!
0.
06
#190000
1!
1.
00
b1 1
16
17
19
b1010 ;
#195000
0!
0.
06
#200000
1!
1.
00
b0 1
12
16
17
19
b1010 ;
#205000
0!
0.
06
#210000
1!
1%
1.
10
b10011 1
02
16
17
19
b1010 ;
b1001 <
0=
b0 ?
0@
0A
b1000 C
#215000
0!
0.
06
#220000
1!
0%
0&
1.
00
b10010 1
16
07
19
b1001 ;
b1001 <
1B
b1000 D
b0 E
#225000
0!
0.
06
#230000
1!
1.
00
b10001 1
16
07
19
b1001 ;
#235000
0!
0.
06
#240000
1!
1.
00
b10000 1
16
07
19
b1001 ;
#245000
0!
0.
06
#250000
1!
1.
00
b1111 1
16
07
19
b1001 ;
#255000
0!
0.
06
#260000
1!
1.
00
b1110 1
16
07
19
b1001 ;
#265000
0!
0.
06
#270000
1!
1.
00
b1101 1
16
07
19
b1001 ;
#275000
0!
0.
06
#280000
1!
1.
00
b1100 1
16
07
19
b1001 ;
#285000
0!
0.
06
#290000
1!
1.
00
b1011 1
16
07
19
b1001 ;
#295000
0!
0.
06
#300000
1!
1.
00
b1010 1
16
07
19
b1001 ;
#305000
0!
0.
06
#310000
1!
1.
00
b1001 1
16
07
19
b1001 ;
#315000
0!
0.
06
#320000
1!
1.
00
b1000 1
16
07
19
b1001 ;
#325000
0!
0.
06
#330000
1!
1.
00
b111 1
16
07
19
b1001 ;
#335000
0!
0.
06
#340000
1!
1.
00
b110 1
16
07
19
b1001 ;
#345000
0!
0.
06
#350000
1!
1.
00
b101 1
16
07
19
b1001 ;
#355000
0!
0.
06
#360000
1!
1.
00
b100 1
16
07
19
b1001 ;
#365000
0!
0.
06
#370000
1!
1.
00
b11 1
16
07
19
b1001 ;
#375000
0!
0.
06
#380000
1!
1.
00
b10 1
16
07
19
b1001 ;
#385000
0!
0.
06
#390000
1!
1.
00
b1 1
16
07
19
b1001 ;
#395000
0!
0.
06
#400000
1!
1.
00
b0 1
12
16
07
19
b1001 ;
#405000
0!
0.
06
#410000
1!
1%
1.
10
b10011 1
02
16
07
19
b1001 ;
b1000 <
b0 ?
0@
1A
b1000 C
b111 D
b0 E
#415000
0!
0.
06
#420000
1!
0%
1.
00
b10010 1
16
07
19
b1000 ;
b1000 <
#425000
0!
0.
06
#430000
1!
1.
00
b10001 1
16
07
19
b1000 ;
#435000
0!
0.
06
#440000
1!
1.
00
b10000 1
16
07
19
b1000 ;
#445000
0!
0.
06
#450000
1!
1.
00
b1111 1
16
07
19
b1000 ;
#455000
0!
0.
06
#460000
1!
1.
00
b1110 1
16
07
19
b1000 ;
#465000
0!
0.
06
#470000
1!
1.
00
b1101 1
16
07
19
b1000 ;
#475000
0!
0.
06
#480000
1!
1.
00
b1100 1
16
07
19
b1000 ;
#485000
0!
0.
06
#490000
1!
1.
00
b1011 1
16
07
19
b1000 ;
#495000
0!
0.
06
#500000
1!
1.
00
b1010 1
16
07
19
b1000 ;
#505000
0!
0.
06
#510000
1!
1.
00
b1001 1
16
07
19
b1000 ;
#515000
0!
0.
06
#520000
1!
1.
00
b1000 1
16
07
19
b1000 ;
#525000
0!
0.
06
#530000
1!
1.
00
b111 1
16
07
19
b1000 ;
#535000
0!
0.
06
#540000
1!
1.
00
b110 1
16
07
19
b1000 ;
#545000
0!
0.
06
#550000
1!
1.
00
b101 1
16
07
19
b1000 ;
#555000
0!
0.
06
#560000
1!
1.
00
b100 1
16
07
19
b1000 ;
#565000
0!
0.
06
#570000
1!
1.
00
b11 1
16
07
19
b1000 ;
#575000
0!
0.
06
#580000
1!
1.
00
b10 1
16
07
19
b1000 ;
#585000
0!
0.
06
#590000
1!
1.
00
b1 1
16
07
19
b1000 ;
#595000
0!
0.
06
#600000
1!
1.
00
b0 1
12
16
07
19
b1000 ;
#605000
0!
0.
06
#610000
1!
1%
1.
10
b10011 1
02
16
07
19
b1000 ;
b111 <
b0 ?
0@
1A
b111 C
b110 D
b0 E
#615000
0!
0.
06
#620000
1!
0%
1.
00
b10010 1
16
07
19
b111 ;
b111 <
#625000
0!
0.
06
#630000
1!
1.
00
b10001 1
16
07
19
b111 ;
#635000
0!
0.
06
#640000
1!
1.
00
b10000 1
16
07
19
b111 ;
#645000
0!
0.
06
#650000
1!
1.
00
b1111 1
16
07
19
b111 ;
#655000
0!
0.
06
#660000
1!
1.
00
b1110 1
16
07
19
b111 ;
#665000
0!
0.
06
#670000
1!
1.
00
b1101 1
16
07
19
b111 ;
#675000
0!
0.
06
#680000
1!
1.
00
b1100 1
16
07
19
b111 ;
#685000
0!
0.
06
#690000
1!
1.
00
b1011 1
16
07
19
b111 ;
#695000
0!
0.
06
#700000
1!
1.
00
b1010 1
16
07
19
b111 ;
#705000
0!
0.
06
#710000
1!
1.
00
b1001 1
16
07
19
b111 ;
#715000
0!
0.
06
#720000
1!
1.
00
b1000 1
16
07
19
b111 ;
#725000
0!
0.
06
#730000
1!
1.
00
b111 1
16
07
19
b111 ;
#735000
0!
0.
06
#740000
1!
1.
00
b110 1
16
07
19
b111 ;
#745000
0!
0.
06
#750000
1!
1.
00
b101 1
16
07
19
b111 ;
#755000
0!
0.
06
#760000
1!
1.
00
b100 1
16
07
19
b111 ;
#765000
0!
0.
06
#770000
1!
1.
00
b11 1
16
07
19
b111 ;
#775000
0!
0.
06
#780000
1!
1.
00
b10 1
16
07
19
b111 ;
#785000
0!
0.
06
#790000
1!
1.
00
b1 1
16
07
19
b111 ;
#795000
0!
0.
06
#800000
1!
1.
00
b0 1
12
16
07
19
b111 ;
#805000
0!
0.
06
#810000
1!
1%
1.
10
b10011 1
02
16
07
19
b111 ;
b110 <
b0 ?
0@
1A
b110 C
b101 D
b0 E
#815000
0!
0.
06
#820000
1!
0%
1.
00
b10010 1
16
07
19
b110 ;
b110 <
#825000
0!
0.
06
#830000
1!
1.
00
b10001 1
16
07
19
b110 ;
#835000
0!
0.
06
#840000
1!
1.
00
b10000 1
16
07
19
b110 ;
#845000
0!
0.
06
#850000
1!
1.
00
b1111 1
16
07
19
b110 ;
#855000
0!
0.
06
#860000
1!
1.
00
b1110 1
16
07
19
b110 ;
#865000
0!
0.
06
#870000
1!
1.
00
b1101 1
16
07
19
b110 ;
#875000
0!
0.
06
#880000
1!
1.
00
b1100 1
16
07
19
b110 ;
#885000
0!
0.
06
#890000
1!
1.
00
b1011 1
16
07
19
b110 ;
#895000
0!
0.
06
#900000
1!
1.
00
b1010 1
16
07
19
b110 ;
#905000
0!
0.
06
#910000
1!
1.
00
b1001 1
16
07
19
b110 ;
#915000
0!
0.
06
#920000
1!
1.
00
b1000 1
16
07
19
b110 ;
#925000
0!
0.
06
#930000
1!
1.
00
b111 1
16
07
19
b110 ;
#935000
0!
0.
06
#940000
1!
1.
00
b110 1
16
07
19
b110 ;
#945000
0!
0.
06
#950000
1!
1.
00
b101 1
16
07
19
b110 ;
#955000
0!
0.
06
#960000
1!
1.
00
b100 1
16
07
19
b110 ;
#965000
0!
0.
06
#970000
1!
1.
00
b11 1
16
07
19
b110 ;
#975000
0!
0.
06
#980000
1!
1.
00
b10 1
16
07
19
b110 ;
#985000
0!
0.
06
#990000
1!
1.
00
b1 1
16
07
19
b110 ;
#995000
0!
0.
06
#1000000
1!
1.
00
b0 1
12
16
07
19
b110 ;
#1005000
0!
0.
06
#1010000
1!
1%
1.
10
b10011 1
02
16
07
19
b110 ;
b101 <
b0 ?
0@
1A
b101 C
b100 D
b0 E
#1015000
0!
0.
06
#1020000
1!
0%
1.
00
b10010 1
16
07
19
b101 ;
b101 <
#1025000
0!
0.
06
#1030000
1!
1.
00
b10001 1
16
07
19
b101 ;
#1035000
0!
0.
06
#1040000
1!
1.
00
b10000 1
16
07
19
b101 ;
#1045000
0!
0.
06
#1050000
1!
1.
00
b1111 1
16
07
19
b101 ;
#1055000
0!
0.
06
#1060000
1!
1.
00
b1110 1
16
07
19
b101 ;
#1065000
0!
0.
06
#1070000
1!
1.
00
b1101 1
16
07
19
b101 ;
#1075000
0!
0.
06
#1080000
1!
1.
00
b1100 1
16
07
19
b101 ;
#1085000
0!
0.
06
#1090000
1!
1.
00
b1011 1
16
07
19
b101 ;
#1095000
0!
0.
06
#1100000
1!
1.
00
b1010 1
16
07
19
b101 ;
#1105000
0!
0.
06
#1110000
1!
1.
00
b1001 1
16
07
19
b101 ;
#1115000
0!
0.
06
#1120000
1!
1.
00
b1000 1
16
07
19
b101 ;
#1125000
0!
0.
06
#1130000
1!
1.
00
b111 1
16
07
19
b101 ;
#1135000
0!
0.
06
#1140000
1!
1.
00
b110 1
16
07
19
b101 ;
#1145000
0!
0.
06
#1150000
1!
1.
00
b101 1
16
07
19
b101 ;
#1155000
0!
0.
06
#1160000
1!
1.
00
b100 1
16
07
19
b101 ;
#1165000
0!
0.
06
#1170000
1!
1.
00
b11 1
16
07
19
b101 ;
#1175000
0!
0.
06
#1180000
1!
1.
00
b10 1
16
07
19
b101 ;
#1185000
0!
0.
06
#1190000
1!
1.
00
b1 1
16
07
19
b101 ;
#1195000
0!
0.
06
#1200000
1!
1.
00
b0 1
12
16
07
19
b101 ;
#1205000
0!
0.
06
#1210000
1!
1%
1.
10
b10011 1
02
16
07
19
b101 ;
b100 <
b0 ?
0@
1A
b100 C
b11 D
b0 E
#1215000
0!
0.
06
#1220000
1!
0%
1.
00
b10010 1
16
07
19
b100 ;
b100 <
#1225000
0!
0.
06
#1230000
1!
1.
00
b10001 1
16
07
19
b100 ;
#1235000
0!
0.
06
#1240000
1!
1.
00
b10000 1
16
07
19
b100 ;
#1245000
0!
0.
06
#1250000
1!
1.
00
b1111 1
16
07
19
b100 ;
#1255000
0!
0.
06
#1260000
1!
1.
00
b1110 1
16
07
19
b100 ;
#1265000
0!
0.
06
#1270000
1!
1.
00
b1101 1
16
07
19
b100 ;
#1275000
0!
0.
06
#1280000
1!
1.
00
b1100 1
16
07
19
b100 ;
#1285000
0!
0.
06
#1290000
1!
1.
00
b1011 1
16
07
19
b100 ;
#1295000
0!
0.
06
#1300000
1!
1.
00
b1010 1
16
07
19
b100 ;
#1305000
0!
0.
06
#1310000
1!
1.
00
b1001 1
16
07
19
b100 ;
#1315000
0!
0.
06
#1320000
1!
1.
00
b1000 1
16
07
19
b100 ;
#1325000
0!
0.
06
#1330000
1!
1.
00
b111 1
16
07
19
b100 ;
#1335000
0!
0.
06
#1340000
1!
1.
00
b110 1
16
07
19
b100 ;
#1345000
0!
0.
06
#1350000
1!
1.
00
b101 1
16
07
19
b100 ;
#1355000
0!
0.
06
#1360000
1!
1.
00
b100 1
16
07
19
b100 ;
#1365000
0!
0.
06
#1370000
1!
1.
00
b11 1
16
07
19
b100 ;
#1375000
0!
0.
06
#1380000
1!
1.
00
b10 1
16
07
19
b100 ;
#1385000
0!
0.
06
#1390000
1!
1.
00
b1 1
16
07
19
b100 ;
#1395000
0!
0.
06
#1400000
1!
1.
00
b0 1
12
16
07
19
b100 ;
#1405000
0!
0.
06
#1410000
1!
1%
1.
10
b10011 1
02
16
07
19
b100 ;
b11 <
b0 ?
0@
1A
b11 C
b10 D
b0 E
#1415000
0!
0.
06
#1420000
1!
0%
1.
00
b10010 1
16
07
19
b11 ;
b11 <
#1425000
0!
0.
06
#1430000
1!
1.
00
b10001 1
16
07
19
b11 ;
#1435000
0!
0.
06
#1440000
1!
1.
00
b10000 1
16
07
19
b11 ;
#1445000
0!
0.
06
#1450000
1!
1.
00
b1111 1
16
07
19
b11 ;
#1455000
0!
0.
06
#1460000
1!
1.
00
b1110 1
16
07
19
b11 ;
#1465000
0!
0.
06
#1470000
1!
1.
00
b1101 1
16
07
19
b11 ;
#1475000
0!
0.
06
#1480000
1!
1.
00
b1100 1
16
07
19
b11 ;
#1485000
0!
0.
06
#1490000
1!
1.
00
b1011 1
16
07
19
b11 ;
#1495000
0!
0.
06
#1500000
1!
1.
00
b1010 1
16
07
19
b11 ;
#1505000
0!
0.
06
#1510000
1!
1.
00
b1001 1
16
07
19
b11 ;
#1515000
0!
0.
06
#1520000
1!
1.
00
b1000 1
16
07
19
b11 ;
#1525000
0!
0.
06
#1530000
1!
1.
00
b111 1
16
07
19
b11 ;
#1535000
0!
0.
06
#1540000
1!
1.
00
b110 1
16
07
19
b11 ;
#1545000
0!
0.
06
#1550000
1!
1.
00
b101 1
16
07
19
b11 ;
#1555000
0!
0.
06
#1560000
1!
1.
00
b100 1
16
07
19
b11 ;
#1565000
0!
0.
06
#1570000
1!
1.
00
b11 1
16
07
19
b11 ;
#1575000
0!
0.
06
#1580000
1!
1.
00
b10 1
16
07
19
b11 ;
#1585000
0!
0.
06
#1590000
1!
1.
00
b1 1
16
07
19
b11 ;
#1595000
0!
0.
06
#1600000
1!
1.
00
b0 1
12
16
07
19
b11 ;
#1605000
0!
0.
06
#1610000
1!
1%
1.
10
b10011 1
02
16
07
19
b11 ;
b10 <
b0 ?
0@
1A
b10 C
b1 D
b0 E
#1615000
0!
0.
06
#1620000
1!
0%
1.
00
b10010 1
16
07
19
b10 ;
b10 <
#1625000
0!
0.
06
#1630000
1!
1.
00
b10001 1
16
07
19
b10 ;
#1635000
0!
0.
06
#1640000
1!
1.
00
b10000 1
16
07
19
b10 ;
#1645000
0!
0.
06
#1650000
1!
1.
00
b1111 1
16
07
19
b10 ;
#1655000
0!
0.
06
#1660000
1!
1.
00
b1110 1
16
07
19
b10 ;
#1665000
0!
0.
06
#1670000
1!
1.
00
b1101 1
16
07
19
b10 ;
#1675000
0!
0.
06
#1680000
1!
1.
00
b1100 1
16
07
19
b10 ;
#1685000
0!
0.
06
#1690000
1!
1.
00
b1011 1
16
07
19
b10 ;
#1695000
0!
0.
06
#1700000
1!
1.
00
b1010 1
16
07
19
b10 ;
#1705000
0!
0.
06
#1710000
1!
1.
00
b1001 1
16
07
19
b10 ;
#1715000
0!
0.
06
#1720000
1!
1.
00
b1000 1
16
07
19
b10 ;
#1725000
0!
0.
06
#1730000
1!
1.
00
b111 1
16
07
19
b10 ;
#1735000
0!
0.
06
#1740000
1!
1.
00
b110 1
16
07
19
b10 ;
#1745000
0!
0.
06
#1750000
1!
1.
00
b101 1
16
07
19
b10 ;
#1755000
0!
0.
06
#1760000
1!
1.
00
b100 1
16
07
19
b10 ;
#1765000
0!
0.
06
#1770000
1!
1.
00
b11 1
16
07
19
b10 ;
#1775000
0!
0.
06
#1780000
1!
1.
00
b10 1
16
07
19
b10 ;
#1785000
0!
0.
06
#1790000
1!
1.
00
b1 1
16
07
19
b10 ;
#1795000
0!
0.
06
#1800000
1!
1.
00
b0 1
12
16
07
19
b10 ;
#1805000
0!
0.
06
#1810000
1!
1%
1.
10
b10011 1
02
16
07
19
b10 ;
b1 <
b0 ?
0@
1A
b1 C
b0 D
b0 E
#1815000
0!
0.
06
#1820000
1!
0%
1.
00
b10010 1
16
07
19
b1 ;
b1 <
0=
#1825000
0!
0.
06
#1830000
1!
1.
00
b10001 1
16
07
19
b1 ;
#1835000
0!
0.
06
#1840000
1!
1.
00
b10000 1
16
07
19
b1 ;
#1845000
0!
0.
06
#1850000
1!
1.
00
b1111 1
16
07
19
b1 ;
#1855000
0!
0.
06
#1860000
1!
1.
00
b1110 1
16
07
19
b1 ;
#1865000
0!
0.
06
#1870000
1!
1.
00
b1101 1
16
07
19
b1 ;
#1875000
0!
0.
06
#1880000
1!
1.
00
b1100 1
16
07
19
b1 ;
#1885000
0!
0.
06
#1890000
1!
1.
00
b1011 1
16
07
19
b1 ;
#1895000
0!
0.
06
#1900000
1!
1.
00
b1010 1
16
07
19
b1 ;
#1905000
0!
0.
06
#1910000
1!
1.
00
b1001 1
16
07
19
b1 ;
#1915000
0!
0.
06
#1920000
1!
1.
00
b1000 1
16
07
19
b1 ;
#1925000
0!
0.
06
#1930000
1!
1.
00
b111 1
16
07
19
b1 ;
#1935000
0!
0.
06
#1940000
1!
1.
00
b110 1
16
07
19
b1 ;
#1945000
0!
0.
06
#1950000
1!
1.
00
b101 1
16
07
19
b1 ;
#1955000
0!
0.
06
#1960000
1!
1.
00
b100 1
16
07
19
b1 ;
#1965000
0!
0.
06
#1970000
1!
1.
00
b11 1
16
07
19
b1 ;
#1975000
0!
0.
06
#1980000
1!
1.
00
b10 1
16
07
19
b1 ;
#1985000
0!
0.
06
#1990000
1!
1.
00
b1 1
16
07
19
b1 ;
#1995000
0!
0.
06
#2000000
1!
1.
00
b0 1
12
16
07
19
b1 ;
#2005000
0!
0.
06
#2010000
1!
1%
1.
10
b10011 1
02
16
07
19
b1 ;
b0 <
1=
b0 ?
0@
1A
0B
b0 C
b0 D
b0 E
#2015000
0!
0.
06
#2020000
1!
0%
1&
1.
00
b10010 1
16
17
19
1:
b0 ;
b0 <
0B
b0 D
b0 E
1F
#2025000
0!
0.
06
#2030000
1!
1.
00
b10001 1
16
17
19
b0 ;
#2035000
0!
0.
06
#2040000
1!
1.
00
b10000 1
16
17
19
b0 ;
#2045000
0!
0.
06
#2050000
1!
1.
00
b1111 1
16
17
19
b0 ;
#2055000
0!
0.
06
#2060000
1!
1.
00
b1110 1
16
17
19
b0 ;
#2065000
0!
0.
06
#2070000
1!
1.
00
b1101 1
16
17
19
b0 ;
#2075000
0!
0.
06
#2080000
1!
1.
00
b1100 1
16
17
19
b0 ;
#2085000
0!
0.
06
#2090000
1!
1.
00
b1011 1
16
17
19
b0 ;
#2095000
0!
0.
06
#2100000
1!
1.
00
b1010 1
16
17
19
b0 ;
#2105000
0!
0.
06
#2110000
1!
1.
00
b1001 1
16
17
19
b0 ;
#2115000
0!
0.
06
#2120000
1!
1.
00
b1000 1
16
17
19
b0 ;
#2125000
0!
0.
06
#2130000
1!
1.
00
b111 1
16
17
19
b0 ;
#2135000
0!
0.
06
#2140000
1!
1.
00
b110 1
16
17
19
b0 ;
#2145000
0!
0.
06
#2150000
1!
1.
00
b101 1
16
17
19
b0 ;
#2155000
0!
0.
06
#2160000
1!
1.
00
b100 1
16
17
19
b0 ;
#2165000
0!
0.
06
#2170000
1!
1.
00
b11 1
16
17
19
b0 ;
#2175000
0!
0.
06
#2180000
1!
1.
00
b10 1
16
17
19
b0 ;
#2185000
0!
0.
06
#2190000
1!
1.
00
b1 1
16
17
19
b0 ;
#2195000
0!
0.
06
#2200000
1!
1.
00
b0 1
12
16
17
19
b0 ;
#2205000
0!
0.
06
#2210000
1!
1%
1(
1.
10
b10011 1
02
16
17
19
0:
b0 ;
b0 <
b0 ?
1@
0A
b0 C
b0 D
b0 E
0F
#2215000
0!
0.
06
#2220000
1!
0%
1.
00
b10010 1
16
17
09
1:
b0 ;
b1010 <
#2225000
0!
0.
06
