uart_receiver/uart_receiver/hdl/uart_receiver.v
module uart_receiver (
  input wire uart_rx,             // UART 資料輸入
  input wire baud_rate_signal,    // Baud rate 驅動訊號
  input wire rst_n,               // 復位訊號（低有效）
  output reg [8:1] data,          // 接收的 8 位資料
  output reg valid_data           // 資料是否有效的標誌
);

  reg state, next_state;          // 狀態與下一狀態
  localparam IDLE = 1'b0;
  localparam RECEIVE = 1'b1;

  reg [3:0] bit_counter, next_bit_counter; // 位元計數器和下一值
  reg [8:1] next_data;                     // 資料暫存
  reg next_valid_data;                     // 有效標誌暫存器

  // 狀態切換邏輯（時序邏輯）
  always @(posedge baud_rate_signal or negedge rst_n) begin
    if (!rst_n) begin
      state <= IDLE;
      data <= 8'b00000000;
      valid_data <= 1'b0;
      bit_counter <= 8;
    end else begin
      state <= next_state;
      data <= next_data;
      valid_data <= next_valid_data;
      bit_counter <= next_bit_counter;
    end
  end

  // 組合邏輯：計算下一狀態和輸出
  always @(*) begin
    // 預設值
    next_state = state;
    next_data = data;
    next_bit_counter = bit_counter;
    next_valid_data = 1'b0;  // 預設為無效

    case (state)
      IDLE: begin
        if (uart_rx == 1'b0) begin
          next_state = RECEIVE;
          next_bit_counter = 8;
        end
      end

      RECEIVE: begin
        if (bit_counter == 0) begin
          if (uart_rx == 1'b1) begin
            next_valid_data = 1'b1; // 資料有效
          end
          next_state = IDLE; // 回到空閒狀態
        end else begin
          next_data[bit_counter] = uart_rx; // 接收資料位
          next_bit_counter = bit_counter - 1;
        end
      end

      default: begin
        next_state = IDLE;
      end
    endcase
  end

endmodule

uart_receiver/uart_receiver/hdl/baud_rate_generator.v
module baud_rate_generator (
  input wire clk,
  input wire rst_n,
  output reg baud_rate_signal
);

  parameter BAUD_RATE_NUMBER = 20;
  reg [13:0] counter;
  reg baud_rate_next; // 組合邏輯輸出暫存

  // 時序邏輯：只負責時鐘驅動的數值更新
  always @(posedge clk or negedge rst_n) begin
    if (!rst_n) begin
      counter <= BAUD_RATE_NUMBER - 1;
      baud_rate_signal <= 1'b0;
    end else begin
      counter <= (counter == 0) ? BAUD_RATE_NUMBER - 1 : counter - 1;
      baud_rate_signal <= baud_rate_next; // 從組合邏輯取得下一狀態
    end
  end

  // 組合邏輯：計算 baud_rate_signal 的下一狀態
  always @(*) begin
    if (counter == 1) begin
      baud_rate_next = 1'b0;
    end else if (counter == 0) begin
      baud_rate_next = 1'b1;
    end else begin
      baud_rate_next = 1'b0;
    end
  end

endmodule

uart_receiver/uart_receiver/xsim/uart_receiver-tb.v
// set the timescale for the simulation
 `timescale 1ns/1ps 
module testbench;  // module of testbench
//  parameter defined
parameter CYCLE = 10; // use CYCLE to describe the clock period
parameter BAUD_RATE_NUMBER = 20;

// localparam
localparam N = 256; 


// input signal use reg
reg clk;
reg rst_n;
reg uart_rx;

// output signal use wire
wire baud_rate_signal;
wire [8:1] data;
wire valid_data;


// interger 
integer j, error;
///// instantiate  module /////
// instantiate the module you finished in following format //
// module_name #(.parameter1(5),.parameter2(3)) unit_name (.port1(...), .port2(...), ...); //
baud_rate_generator baud_rate_generator(
  .clk(clk),
  .rst_n(rst_n),
  .baud_rate_signal(baud_rate_signal)
);

uart_receiver uart_receiver(
  .uart_rx(uart_rx),
  .baud_rate_signal(baud_rate_signal),
  .rst_n(rst_n),
  .data(data),
  .valid_data(valid_data)
);
//  dump the waveform of the simulation for fsdb//
/*initial begin
 $fsdbDumpfile("testbench.fsdb"); 
 $fsdbDumpvars;              
end*/

// dump the waveform of the simulation for vcd//
initial begin
  $dumpfile("testbench.vcd");
  $dumpvars("+mda");
end

// there you can read data from the file,and store in the register.
reg [18:0] golden [0:N];
initial begin
  $readmemb("golden.dat",golden);
end


// generate clk 
always #(CYCLE/2) clk = ~clk; 

// System block set only clock,reset signal and the timeout finish. 
initial begin
  clk = 1;
  rst_n = 1;
  // system reset
  #(CYCLE) rst_n = 0;
  #(CYCLE) rst_n = 1;
end

integer k;
task send_uartrx (input reg [9:0] pattern_in);
  begin
    for(k = 9; k >= 0; k = k - 1) begin
      @(posedge baud_rate_signal);
      uart_rx = pattern_in[k];
    end
  end
endtask

// output result checking block, control when to sample and verify the result.
integer fp_w;
reg [9:0] signal_in;
reg [7:0] correct_data;
reg correct_valid;

initial begin
// error count
  error = 0;
// Use the same control technique to control when to sample output result.
  wait(rst_n==0);
  wait(rst_n==1);
// adder output for two cycle from input to output
  // you can also write the result to a text file
  fp_w = $fopen("answer.txt");
  for (j = 0; j < N; j = j + 1) begin
    @(posedge clk);
    signal_in = golden[j][18:9];
    correct_data = golden[j][8:1];
    correct_valid = golden[j][0];
    send_uartrx(signal_in);
    #(CYCLE*21)
    if({data, valid_data} !== {correct_data, correct_valid}) begin
        error = error + 1;
        $display("************* Pattern No.%d is wrong at %t ************", j,$time);
        $display("uart_rx = %b, correct data and correct valid_data is %b and %b,", signal_in, correct_data, correct_valid);
        $display("but your data and valid_data are %b and %b !!", data, valid_data);
      end
      $fdisplay(fp_w, "%b_%b_%b_%b_%b", signal_in, data, valid_data, correct_data, correct_valid);
  end

  $fclose(fp_w);

  if(error == 0) begin
    $display("Congratulations!! The functionality of your receiver is correct!!");
  end
  else begin
    $display("error !!");
  end 
  #(CYCLE) $finish; 

end

endmodule

uart_receiver/uart_receiver/xsim/testbench.vcd
$date
   Wed Jan 15 02:25:15 2025
$end
$version
  2022.1
$end
$timescale
  1ps
$end
$scope module testbench $end
$var reg 1 ! clk $end
$var reg 1 " rst_n $end
$var reg 1 # uart_rx $end
$var wire 1 $ baud_rate_signal $end
$var wire 8 % data [7:0] $end
$var wire 1 & valid_data $end
$var integer 32 ' j [31:0] $end
$var integer 32 ( error [31:0] $end
$var integer 32 ) k [31:0] $end
$var integer 32 * fp_w [31:0] $end
$var reg 10 + signal_in [9:0] $end
$var reg 8 , correct_data [7:0] $end
$var reg 1 - correct_valid $end
$scope module baud_rate_generator $end
$var wire 1 . clk $end
$var wire 1 / rst_n $end
$var reg 1 0 baud_rate_signal $end
$var reg 14 1 counter [13:0] $end
$var reg 1 2 baud_rate_next $end
$upscope $end
$scope module uart_receiver $end
$var wire 1 3 uart_rx $end
$var wire 1 $ baud_rate_signal $end
$var wire 1 4 rst_n $end
$var reg 8 5 data [7:0] $end
$var reg 1 6 valid_data $end
$var reg 1 7 state $end
$var reg 1 8 next_state $end
$var reg 4 9 bit_counter [3:0] $end
$var reg 4 : next_bit_counter [3:0] $end
$var reg 8 ; next_data [7:0] $end
$var reg 1 < next_valid_data $end
$upscope $end
$scope task send_uartrx $end
$var reg 10 = pattern_in [9:0] $end
$upscope $end
$upscope $end
$enddefinitions $end
#0
$dumpvars
1!
1"
x#
x$
bx %
x&
bx '
b0 (
bx )
bx *
bx +
bx ,
x-
1.
1/
x0
bx 1
x2
x3
14
bx 5
x6
x7
x8
bx 9
bx :
bx ;
x<
bx =
$end
#5000
0!
0.
#10000
1!
0"
0$
b0 %
0&
1.
0/
00
b10011 1
02
04
b0 5
06
07
08
b1000 9
b1000 :
b0 ;
0<
#15000
0!
0.
#20000
1!
1"
b0 '
b10 *
1.
1/
00
b10010 1
14
#25000
0!
0.
#30000
1!
b1001 )
b1 +
b0 ,
1-
1.
00
b10001 1
b1 =
#35000
0!
0.
#40000
1!
1.
00
b10000 1
#45000
0!
0.
#50000
1!
1.
00
b1111 1
#55000
0!
0.
#60000
1!
1.
00
b1110 1
#65000
0!
0.
#70000
1!
1.
00
b1101 1
#75000
0!
0.
#80000
1!
1.
00
b1100 1
#85000
0!
0.
#90000
1!
1.
00
b1011 1
#95000
0!
0.
#100000
1!
1.
00
b1010 1
#105000
0!
0.
#110000
1!
1.
00
b1001 1
#115000
0!
0.
#120000
1!
1.
00
b1000 1
#125000
0!
0.
#130000
1!
1.
00
b111 1
#135000
0!
0.
#140000
1!
1.
00
b110 1
#145000
0!
0.
#150000
1!
1.
00
b101 1
#155000
0!
0.
#160000
1!
1.
00
b100 1
#165000
0!
0.
#170000
1!
1.
00
b11 1
#175000
0!
0.
#180000
1!
1.
00
b10 1
#185000
0!
0.
#190000
1!
1.
00
b1 1
#195000
0!
0.
#200000
1!
1.
00
b0 1
12
#205000
0!
0.
#210000
1!
0#
1$
b1000 )
1.
10
b10011 1
02
03
b0 5
06
07
18
b1000 9
b1000 :
b0 ;
#215000
0!
0.
#220000
1!
0$
1.
00
b10010 1
#225000
0!
0.
#230000
1!
1.
00
b10001 1
#235000
0!
0.
#240000
1!
1.
00
b10000 1
#245000
0!
0.
#250000
1!
1.
00
b1111 1
#255000
0!
0.
#260000
1!
1.
00
b1110 1
#265000
0!
0.
#270000
1!
1.
00
b1101 1
#275000
0!
0.
#280000
1!
1.
00
b1100 1
#285000
0!
0.
#290000
1!
1.
00
b1011 1
#295000
0!
0.
#300000
1!
1.
00
b1010 1
#305000
0!
0.
#310000
1!
1.
00
b1001 1
#315000
0!
0.
#320000
1!
1.
00
b1000 1
#325000
0!
0.
#330000
1!
1.
00
b111 1
#335000
0!
0.
#340000
1!
1.
00
b110 1
#345000
0!
0.
#350000
1!
1.
00
b101 1
#355000
0!
0.
#360000
1!
1.
00
b100 1
#365000
0!
0.
#370000
1!
1.
00
b11 1
#375000
0!
0.
#380000
1!
1.
00
b10 1
#385000
0!
0.
#390000
1!
1.
00
b1 1
#395000
0!
0.
#400000
1!
1.
00
b0 1
12
#405000
0!
0.
#410000
1!
1$
b111 )
1.
10
b10011 1
02
b0 5
06
17
b1000 9
b111 :
b0 ;
#415000
0!
0.
#420000
1!
0$
1.
00
b10010 1
#425000
0!
0.
#430000
1!
1.
00
b10001 1
#435000
0!
0.
#440000
1!
1.
00
b10000 1
#445000
0!
0.
#450000
1!
1.
00
b1111 1
#455000
0!
0.
#460000
1!
1.
00
b1110 1
#465000
0!
0.
#470000
1!
1.
00
b1101 1
#475000
0!
0.
#480000
1!
1.
00
b1100 1
#485000
0!
0.
#490000
1!
1.
00
b1011 1
#495000
0!
0.
#500000
1!
1.
00
b1010 1
#505000
0!
0.
#510000
1!
1.
00
b1001 1
#515000
0!
0.
#520000
1!
1.
00
b1000 1
#525000
0!
0.
#530000
1!
1.
00
b111 1
#535000
0!
0.
#540000
1!
1.
00
b110 1
#545000
0!
0.
#550000
1!
1.
00
b101 1
#555000
0!
0.
#560000
1!
1.
00
b100 1
#565000
0!
0.
#570000
1!
1.
00
b11 1
#575000
0!
0.
#580000
1!
1.
00
b10 1
#585000
0!
0.
#590000
1!
1.
00
b1 1
#595000
0!
0.
#600000
1!
1.
00
b0 1
12
#605000
0!
0.
#610000
1!
1$
b110 )
1.
10
b10011 1
02
b0 5
06
17
b111 9
b110 :
b0 ;
#615000
0!
0.
#620000
1!
0$
1.
00
b10010 1
#625000
0!
0.
#630000
1!
1.
00
b10001 1
#635000
0!
0.
#640000
1!
1.
00
b10000 1
#645000
0!
0.
#650000
1!
1.
00
b1111 1
#655000
0!
0.
#660000
1!
1.
00
b1110 1
#665000
0!
0.
#670000
1!
1.
00
b1101 1
#675000
0!
0.
#680000
1!
1.
00
b1100 1
#685000
0!
0.
#690000
1!
1.
00
b1011 1
#695000
0!
0.
#700000
1!
1.
00
b1010 1
#705000
0!
0.
#710000
1!
1.
00
b1001 1
#715000
0!
0.
#720000
1!
1.
00
b1000 1
#725000
0!
0.
#730000
1!
1.
00
b111 1
#735000
0!
0.
#740000
1!
1.
00
b110 1
#745000
0!
0.
#750000
1!
1.
00
b101 1
#755000
0!
0.
#760000
1!
1.
00
b100 1
#765000
0!
0.
#770000
1!
1.
00
b11 1
#775000
0!
0.
#780000
1!
1.
00
b10 1
#785000
0!
0.
#790000
1!
1.
00
b1 1
#795000
0!
0.
#800000
1!
1.
00
b0 1
12
#805000
0!
0.
#810000
1!
1$
b101 )
1.
10
b10011 1
02
b0 5
06
17
b110 9
b101 :
b0 ;
#815000
0!
0.
#820000
1!
0$
1.
00
b10010 1
#825000
0!
0.
#830000
1!
1.
00
b10001 1
#835000
0!
0.
#840000
1!
1.
00
b10000 1
#845000
0!
0.
#850000
1!
1.
00
b1111 1
#855000
0!
0.
#860000
1!
1.
00
b1110 1
#865000
0!
0.
#870000
1!
1.
00
b1101 1
#875000
0!
0.
#880000
1!
1.
00
b1100 1
#885000
0!
0.
#890000
1!
1.
00
b1011 1
#895000
0!
0.
#900000
1!
1.
00
b1010 1
#905000
0!
0.
#910000
1!
1.
00
b1001 1
#915000
0!
0.
#920000
1!
1.
00
b1000 1
#925000
0!
0.
#930000
1!
1.
00
b111 1
#935000
0!
0.
#940000
1!
1.
00
b110 1
#945000
0!
0.
#950000
1!
1.
00
b101 1
#955000
0!
0.
#960000
1!
1.
00
b100 1
#965000
0!
0.
#970000
1!
1.
00
b11 1
#975000
0!
0.
#980000
1!
1.
00
b10 1
#985000
0!
0.
#990000
1!
1.
00
b1 1
#995000
0!
0.
#1000000
1!
1.
00
b0 1
12
#1005000
0!
0.
#1010000
1!
1$
b100 )
1.
10
b10011 1
02
b0 5
06
17
b101 9
b100 :
b0 ;
#1015000
0!
0.
#1020000
1!
0$
1.
00
b10010 1
#1025000
0!
0.
#1030000
1!
1.
00
b10001 1
#1035000
0!
0.
#1040000
1!
1.
00
b10000 1
#1045000
0!
0.
#1050000
1!
1.
00
b1111 1
#1055000
0!
0.
#1060000
1!
1.
00
b1110 1
#1065000
0!
0.
#1070000
1!
1.
00
b1101 1
#1075000
0!
0.
#1080000
1!
1.
00
b1100 1
#1085000
0!
0.
#1090000
1!
1.
00
b1011 1
#1095000
0!
0.
#1100000
1!
1.
00
b1010 1
#1105000
0!
0.
#1110000
1!
1.
00
b1001 1
#1115000
0!
0.
#1120000
1!
1.
00
b1000 1
#1125000
0!
0.
#1130000
1!
1.
00
b111 1
#1135000
0!
0.
#1140000
1!
1.
00
b110 1
#1145000
0!
0.
#1150000
1!
1.
00
b101 1
#1155000
0!
0.
#1160000
1!
1.
00
b100 1
#1165000
0!
0.
#1170000
1!
1.
00
b11 1
#1175000
0!
0.
#1180000
1!
1.
00
b10 1
#1185000
0!
0.
#1190000
1!
1.
00
b1 1
#1195000
0!
0.
#1200000
1!
1.
00
b0 1
12
#1205000
0!
0.
#1210000
1!
1$
b11 )
1.
10
b10011 1
02
b0 5
06
17
b100 9
b11 :
b0 ;
#1215000
0!
0.
#1220000
1!
0$
1.
00
b10010 1
#1225000
0!
0.
#1230000
1!
1.
00
b10001 1
#1235000
0!
0.
#1240000
1!
1.
00
b10000 1
#1245000
0!
0.
#1250000
1!
1.
00
b1111 1
#1255000
0!
0.
#1260000
1!
1.
00
b1110 1
#1265000
0!
0.
#1270000
1!
1.
00
b1101 1
#1275000
0!
0.
#1280000
1!
1.
00
b1100 1
#1285000
0!
0.
#1290000
1!
1.
00
b1011 1
#1295000
0!
0.
#1300000
1!
1.
00
b1010 1
#1305000
0!
0.
#1310000
1!
1.
00
b1001 1
#1315000
0!
0.
#1320000
1!
1.
00
b1000 1
#1325000
0!
0.
#1330000
1!
1.
00
b111 1
#1335000
0!
0.
#1340000
1!
1.
00
b110 1
#1345000
0!
0.
#1350000
1!
1.
00
b101 1
#1355000
0!
0.
#1360000
1!
1.
00
b100 1
#1365000
0!
0.
#1370000
1!
1.
00
b11 1
#1375000
0!
0.
#1380000
1!
1.
00
b10 1
#1385000
0!
0.
#1390000
1!
1.
00
b1 1
#1395000
0!
0.
#1400000
1!
1.
00
b0 1
12
#1405000
0!
0.
#1410000
1!
1$
b10 )
1.
10
b10011 1
02
b0 5
06
17
b11 9
b10 :
b0 ;
#1415000
0!
0.
#1420000
1!
0$
1.
00
b10010 1
#1425000
0!
0.
#1430000
1!
1.
00
b10001 1
#1435000
0!
0.
#1440000
1!
1.
00
b10000 1
#1445000
0!
0.
#1450000
1!
1.
00
b1111 1
#1455000
0!
0.
#1460000
1!
1.
00
b1110 1
#1465000
0!
0.
#1470000
1!
1.
00
b1101 1
#1475000
0!
0.
#1480000
1!
1.
00
b1100 1
#1485000
0!
0.
#1490000
1!
1.
00
b1011 1
#1495000
0!
0.
#1500000
1!
1.
00
b1010 1
#1505000
0!
0.
#1510000
1!
1.
00
b1001 1
#1515000
0!
0.
#1520000
1!
1.
00
b1000 1
#1525000
0!
0.
#1530000
1!
1.
00
b111 1
#1535000
0!
0.
#1540000
1!
1.
00
b110 1
#1545000
0!
0.
#1550000
1!
1.
00
b101 1
#1555000
0!
0.
#1560000
1!
1.
00
b100 1
#1565000
0!
0.
#1570000
1!
1.
00
b11 1
#1575000
0!
0.
#1580000
1!
1.
00
b10 1
#1585000
0!
0.
#1590000
1!
1.
00
b1 1
#1595000
0!
0.
#1600000
1!
1.
00
b0 1
12
#1605000
0!
0.
#1610000
1!
1$
b1 )
1.
10
b10011 1
02
b0 5
06
17
b10 9
b1 :
b0 ;
#1615000
0!
0.
#1620000
1!
0$
1.
00
b10010 1
#1625000
0!
0.
#1630000
1!
1.
00
b10001 1
#1635000
0!
0.
#1640000
1!
1.
00
b10000 1
#1645000
0!
0.
#1650000
1!
1.
00
b1111 1
#1655000
0!
0.
#1660000
1!
1.
00
b1110 1
#1665000
0!
0.
#1670000
1!
1.
00
b1101 1
#1675000
0!
0.
#1680000
1!
1.
00
b1100 1
#1685000
0!
0.
#1690000
1!
1.
00
b1011 1
#1695000
0!
0.
#1700000
1!
1.
00
b1010 1
#1705000
0!
0.
#1710000
1!
1.
00
b1001 1
#1715000
0!
0.
#1720000
1!
1.
00
b1000 1
#1725000
0!
0.
#1730000
1!
1.
00
b111 1
#1735000
0!
0.
#1740000
1!
1.
00
b110 1
#1745000
0!
0.
#1750000
1!
1.
00
b101 1
#1755000
0!
0.
#1760000
1!
1.
00
b100 1
#1765000
0!
0.
#1770000
1!
1.
00
b11 1
#1775000
0!
0.
#1780000
1!
1.
00
b10 1
#1785000
0!
0.
#1790000
1!
1.
00
b1 1
#1795000
0!
0.
#1800000
1!
1.
00
b0 1
12
#1805000
0!
0.
#1810000
1!
1$
b0 )
1.
10
b10011 1
02
b0 5
06
17
b1 9
b0 :
b0 ;
#1815000
0!
0.
#1820000
1!
0$
1.
00
b10010 1
#1825000
0!
0.
#1830000
1!
1.
00
b10001 1
#1835000
0!
0.
#1840000
1!
1.
00
b10000 1
#1845000
0!
0.
#1850000
1!
1.
00
b1111 1
#1855000
0!
0.
#1860000
1!
1.
00
b1110 1
#1865000
0!
0.
#1870000
1!
1.
00
b1101 1
#1875000
0!
0.
#1880000
1!
1.
00
b1100 1
#1885000
0!
0.
#1890000
1!
1.
00
b1011 1
#1895000
0!
0.
#1900000
1!
1.
00
b1010 1
#1905000
0!
0.
#1910000
1!
1.
00
b1001 1
#1915000
0!
0.
#1920000
1!
1.
00
b1000 1
#1925000
0!
0.
#1930000
1!
1.
00
b111 1
#1935000
0!
0.
#1940000
1!
1.
00
b110 1
#1945000
0!
0.
#1950000
1!
1.
00
b101 1
#1955000
0!
0.
#1960000
1!
1.
00
b100 1
#1965000
0!
0.
#1970000
1!
1.
00
b11 1
#1975000
0!
0.
#1980000
1!
1.
00
b10 1
#1985000
0!
0.
#1990000
1!
1.
00
b1 1
#1995000
0!
0.
#2000000
1!
1.
00
b0 1
12
#2005000
0!
0.
#2010000
1!
1#
1$
b11111111111111111111111111111111 )
1.
10
b10011 1
02
13
b0 5
06
17
08
b0 9
b0 :
b0 ;
1<
#2015000
0!
0.
#2020000
1!
0$
1.
00
b10010 1
#2025000
0!
0.
#2030000
1!
1.
00
b10001 1
#2035000
0!
0.
#2040000
1!
1.
00
b10000 1
#2045000
0!
0.
#2050000
1!
1.
00
b1111 1
#2055000
0!
0.
#2060000
1!
1.
00
b1110 1
#2065000
0!
0.
#2070000
1!
1.
00
b1101 1
#2075000
0!
0.
#2080000
1!
1.
00
b1100 1
#2085000
0!
0.
#2090000
1!
1.
00
b1011 1
#2095000
0!
0.
#2100000
1!
1.
00
b1010 1
#2105000
0!
0.
#2110000
1!
1.
00
b1001 1
#2115000
0!
0.
#2120000
1!
1.
00
b1000 1
#2125000
0!
0.
#2130000
1!
1.
00
b111 1
#2135000
0!
0.
#2140000
1!
1.
00
b110 1
#2145000
0!
0.
#2150000
1!
1.
00
b101 1
#2155000
0!
0.
#2160000
1!
1.
00
b100 1
#2165000
0!
0.
#2170000
1!
1.
00
b11 1
#2175000
0!
0.
#2180000
1!
1.
00
b10 1
#2185000
0!
0.
#2190000
1!
1.
00
b1 1
#2195000
0!
0.
#2200000
1!
1.
00
b0 1
12
#2205000
0!
0.
#2210000
1!
1$
1&
1.
10
b10011 1
02
b0 5
16
07
b0 9
b0 :
b0 ;
0<
#2215000
0!
0.
#2220000
1!
0$
b1 '
b1001 )
b11 +
b1 ,
1.
00
b10010 1
b11 =
#2225000
0!
0.
#2230000
1!
1.
00
b10001 1
#2235000
0!
0.
#2240000
1!
1.
00
b10000 1
#2245000
0!
0.
#2250000
1!
1.
00
b1111 1
#2255000
0!
0.
#2260000
1!
1.
00
b1110 1
#2265000
0!
0.
#2270000
1!
1.
00
b1101 1
#2275000
0!
0.
#2280000
1!
1.
00
b1100 1
#2285000
0!
0.
#2290000
1!
1.
00
b1011 1
#2295000
0!
0.
#2300000
1!
1.
00
b1010 1
#2305000
0!
0.
#2310000
1!
1.
00
b1001 1
#2315000
0!
0.
#2320000
1!
1.
00
b1000 1
#2325000
0!
0.
#2330000
1!
1.
00
b111 1
#2335000
0!
0.
#2340000
1!
1.
00
b110 1
#2345000
0!
0.
#2350000
1!
1.
00
b101 1
#2355000
0!
0.
#2360000
1!
1.
00
b100 1
#2365000
0!
0.
#2370000
1!
1.
00
b11 1
#2375000
0!
0.
#2380000
1!
1.
00
b10 1
#2385000
0!
0.
#2390000
1!
1.
00
b1 1
#2395000
0!
0.
#2400000
1!
1.
00
b0 1
12
#2405000
0!
0.
#2410000
1!
0#
1$
0&
b1000 )
1.
10
b10011 1
02
03
b0 5
06
07
18
b0 9
b1000 :
b0 ;
#2415000
0!
0.
#2420000
1!
0$
1.
00
b10010 1
#2425000
0!
0.
#2430000
1!
1.
00
b10001 1
#2435000
0!
0.
#2440000
1!
1.
00
b10000 1
#2445000
0!
0.
#2450000
1!
1.
00
b1111 1
#2455000
0!
0.
#2460000
1!
1.
00
b1110 1
#2465000
0!
0.
#2470000
1!
1.
00
b1101 1
#2475000
0!
0.
#2480000
1!
1.
00
b1100 1
#2485000
0!
0.
#2490000
1!
1.
00
b1011 1
#2495000
0!
0.
#2500000
1!
1.
00
b1010 1
#2505000
0!
0.
#2510000
1!
1.
00
b1001 1
#2515000
0!
0.
#2520000
1!
1.
00
b1000 1
#2525000
0!
0.
#2530000
1!
1.
00
b111 1
#2535000
0!
0.
#2540000
1!
1.
00
b110 1
#2545000
0!
0.
#2550000
1!
1.
00
b101 1
#2555000
0!
0.
#2560000
1!
1.
00
b100 1
#2565000
0!
0.
#2570000
1!
1.
00
b11 1
#2575000
0!
0.
#2580000
1!
1.
00
b10 1
#2585000
0!
0.
#2590000
1!
1.
00
b1 1
#2595000
0!
0.
#2600000
1!
1.
00
b0 1
12
#2605000
0!
0.
#2610000
1!
1$
b111 )
1.
10
b10011 1
02
b0 5
06
17
b1000 9
b111 :
b0 ;
#2615000
0!
0.
#2620000
1!
0$
1.
00
b10010 1
#2625000
0!
0.
#2630000
1!
1.
00
b10001 1
#2635000
0!
0.
#2640000
1!
1.
00
b10000 1
#2645000
0!
0.
#2650000
1!
1.
00
b1111 1
#2655000
0!
0.
#2660000
1!
1.
00
b1110 1
#2665000
0!
0.
#2670000
1!
1.
00
b1101 1
#2675000
0!
0.
#2680000
1!
1.
00
b1100 1
#2685000
0!
0.
#2690000
1!
1.
00
b1011 1
#2695000
0!
0.
#2700000
1!
1.
00
b1010 1
#2705000
0!
0.
#2710000
1!
1.
00
b1001 1
#2715000
0!
0.
#2720000
1!
1.
00
b1000 1
#2725000
0!
0.
#2730000
1!
1.
00
b111 1
#2735000
0!
0.
#2740000
1!
1.
00
b110 1
#2745000
0!
0.
#2750000
1!
1.
00
b101 1
#2755000
0!
0.
#2760000
1!
1.
00
b100 1
#2765000
0!
0.
#2770000
1!
1.
00
b11 1
#2775000
0!
0.
#2780000
1!
1.
00
b10 1
#2785000
0!
0.
#2790000
1!
1.
00
b1 1
#2795000
0!
0.
#2800000
1!
1.
00
b0 1
12
#2805000
0!
0.
#2810000
1!
1$
b110 )
1.
10
b10011 1
02
b0 5
06
17
b111 9
b110 :
b0 ;
#2815000
0!
0.
#2820000
1!
0$
1.
00
b10010 1
#2825000
0!
0.
#2830000
1!
1.
00
b10001 1
#2835000
0!
0.
#2840000
1!
1.
00
b10000 1
#2845000
0!
0.
#2850000
1!
1.
00
b1111 1
#2855000
0!
0.
#2860000
1!
1.
00
b1110 1
#2865000
0!
0.
#2870000
1!
1.
00
b1101 1
#2875000
0!
0.
#2880000
1!
1.
00
b1100 1
#2885000
0!
0.
#2890000
1!
1.
00
b1011 1
#2895000
0!
0.
#2900000
1!
1.
00
b1010 1
#2905000
0!
0.
#2910000
1!
1.
00
b1001 1
#2915000
0!
0.
#2920000
1!
1.
00
b1000 1
#2925000
0!
0.
#2930000
1!
1.
00
b111 1
#2935000
0!
0.
#2940000
1!
1.
00
b110 1
#2945000
0!
0.
#2950000
1!
1.
00
b101 1
#2955000
0!
0.
#2960000
1!
1.
00
b100 1
#2965000
0!
0.
#2970000
1!
1.
00
b11 1
#2975000
0!
0.
#2980000
1!
1.
00
b10 1
#2985000
0!
0.
#2990000
1!
1.
00
b1 1
#2995000
0!
0.
#3000000
1!
1.
00
b0 1
12
#3005000
0!
0.
#3010000
1!
1$
b101 )
1.
10
b10011 1
02
b0 5
06
17
b110 9
b101 :
b0 ;
#3015000
0!
0.
#3020000
1!
0$
1.
00
b10010 1
#3025000
0!
0.
#3030000
1!
1.
00
b10001 1
#3035000
0!
0.
#3040000
1!
1.
00
b10000 1
#3045000
0!
0.
#3050000
1!
1.
00
b1111 1
#3055000
0!
0.
#3060000
1!
1.
00
b1110 1
#3065000
0!
0.
#3070000
1!
1.
00
b1101 1
#3075000
0!
0.
#3080000
1!
1.
00
b1100 1
#3085000
0!
0.
#3090000
1!
1.
00
b1011 1
#3095000
0!
0.
#3100000
1!
1.
00
b1010 1
#3105000
0!
0.
#3110000
1!
1.
00
b1001 1
#3115000
0!
0.
#3120000
1!
1.
00
b1000 1
#3125000
0!
0.
#3130000
1!
1.
00
b111 1
#3135000
0!
0.
#3140000
1!
1.
00
b110 1
#3145000
0!
0.
#3150000
1!
1.
00
b101 1
#3155000
0!
0.
#3160000
1!
1.
00
b100 1
#3165000
0!
0.
#3170000
1!
1.
00
b11 1
#3175000
0!
0.
#3180000
1!
1.
00
b10 1
#3185000
0!
0.
#3190000
1!
1.
00
b1 1
#3195000
0!
0.
#3200000
1!
1.
00
b0 1
12
#3205000
0!
0.
#3210000
1!
1$
b100 )
1.
10
b10011 1
02
b0 5
06
17
b101 9
b100 :
b0 ;
#3215000
0!
0.
#3220000
1!
0$
1.
00
b10010 1
#3225000
0!
0.
#3230000
1!
1.
00
b10001 1
#3235000
0!
0.
#3240000
1!
1.
00
b10000 1
#3245000
0!
0.
#3250000
1!
1.
00
b1111 1
#3255000
0!
0.
#3260000
1!
1.
00
b1110 1
#3265000
0!
0.
#3270000
1!
1.
00
b1101 1
#3275000
0!
0.
#3280000
1!
1.
00
b1100 1
#3285000
0!
0.
#3290000
1!
1.
00
b1011 1
#3295000
0!
0.
#3300000
1!
1.
00
b1010 1
#3305000
0!
0.
#3310000
1!
1.
00
b1001 1
#3315000
0!
0.
#3320000
1!
1.
00
b1000 1
#3325000
0!
0.
#3330000
1!
1.
00
b111 1
#3335000
0!
0.
#3340000
1!
1.
00
b110 1
#3345000
0!
0.
#3350000
1!
1.
00
b101 1
#3355000
0!
0.
#3360000
1!
1.
00
b100 1
#3365000
0!
0.
#3370000
1!
1.
00
b11 1
#3375000
0!
0.
#3380000
1!
1.
00
b10 1
#3385000
0!
0.
#3390000
1!
1.
00
b1 1
#3395000
0!
0.
#3400000
1!
1.
00
b0 1
12
#3405000
0!
0.
#3410000
1!
1$
b11 )
1.
10
b10011 1
02
b0 5
06
17
b100 9
b11 :
b0 ;
#3415000
0!
0.
#3420000
1!
0$
1.
00
b10010 1
#3425000
0!
0.
#3430000
1!
1.
00
b10001 1
#3435000
0!
0.
#3440000
1!
1.
00
b10000 1
#3445000
0!
0.
#3450000
1!
1.
00
b1111 1
#3455000
0!
0.
#3460000
1!
1.
00
b1110 1
#3465000
0!
0.
#3470000
1!
1.
00
b1101 1
#3475000
0!
0.
#3480000
1!
1.
00
b1100 1
#3485000
0!
0.
#3490000
1!
1.
00
b1011 1
#3495000
0!
0.
#3500000
1!
1.
00
b1010 1
#3505000
0!
0.
#3510000
1!
1.
00
b1001 1
#3515000
0!
0.
#3520000
1!
1.
00
b1000 1
#3525000
0!
0.
#3530000
1!
1.
00
b111 1
#3535000
0!
0.
#3540000
1!
1.
00
b110 1
#3545000
0!
0.
#3550000
1!
1.
00
b101 1
#3555000
0!
0.
#3560000
1!
1.
00
b100 1
#3565000
0!
0.
#3570000
1!
1.
00
b11 1
#3575000
0!
0.
#3580000
1!
1.
00
b10 1
#3585000
0!
0.
#3590000
1!
1.
00
b1 1
#3595000
0!
0.
#3600000
1!
1.
00
b0 1
12
#3605000
0!
0.
#3610000
1!
1$
b10 )
1.
10
b10011 1
02
b0 5
06
17
b11 9
b10 :
b0 ;
#3615000
0!
0.
#3620000
1!
0$
1.
00
b10010 1
#3625000
0!
0.
#3630000
1!
1.
00
b10001 1
#3635000
0!
0.
#3640000
1!
1.
00
b10000 1
#3645000
0!
0.
#3650000
1!
1.
00
b1111 1
#3655000
0!
0.
#3660000
1!
1.
00
b1110 1
