binary2bcd_double_dabble/hdl/binary2bcd_double_dabble.v
module binary2bcd_double_dabble (
  input wire [7:0]binary_in,
  input clk,
  input rst_n,
  output reg [19:0]unpacked_bcd,
  output reg [11:0]packed_bcd
);

wire [3:0]zero_4 = 4'b0000;
reg [19:0] scratch_pad;
reg [19:0] scratch_pad_temp;
localparam FOUR = 4;
localparam THREE = 3;
integer i, j;


always @(negedge rst_n) begin
  scratch_pad = {zero_4, zero_4, zero_4, binary_in};
  scratch_pad_temp = scratch_pad;
  scratch_pad = scratch_pad_temp << 1;
  for (i = 0; i < 7; i = i + 1) begin
    for (j = 0; j < 3; j = j + 1) begin
      case (j) 
        2'b00: begin
          if (scratch_pad[19:16] > FOUR) begin
            scratch_pad_temp[19:16] = scratch_pad[19:16];
            scratch_pad[19:16] = scratch_pad_temp[19:16] + THREE;
          end else begin
            scratch_pad_temp = scratch_pad;
          end
        end
        2'b01: begin
          if (scratch_pad[15:12] > FOUR) begin
            scratch_pad_temp[15:12] = scratch_pad[15:12];
            scratch_pad[15:12] = scratch_pad_temp[15:12] + THREE;
          end else begin
            scratch_pad_temp = scratch_pad;
          end
        end
        2'b10: begin
          if (scratch_pad[11:8] > FOUR) begin
            scratch_pad_temp[11:8] = scratch_pad[11:8];
            scratch_pad[11:8] = scratch_pad_temp[11:8] + THREE;
          end else begin
            scratch_pad_temp = scratch_pad;
          end
        end
        default: scratch_pad_temp = scratch_pad;
      endcase
    end
    scratch_pad_temp = scratch_pad;
    scratch_pad = scratch_pad_temp << 1;
  end
  packed_bcd = scratch_pad[19:8];
  unpacked_bcd = {scratch_pad[19:16], zero_4, scratch_pad[15:12], zero_4, scratch_pad[11:8]};
end


endmodule

binary2bcd_double_dabble/xsim/binary2bcd_double_dabble_tb.v
// set the timescale for the simulation
 `timescale 1ns/1ps 
module testbench;  // module of testbench

// localparam
localparam N = 256;
localparam CYCLE = 10;
// input signal use reg
reg [7:0] binary_in;
reg clk;
reg rst_n;

// output signal use wire
wire [19:0] unpacked_bcd;
wire [11:0] packed_bcd;

// interger 
integer j, error;
///// instantiate  module /////
// instantiate the module you finished in following format //
// module_name #(.parameter1(5),.parameter2(3)) unit_name (.port1(...), .port2(...), ...); //
binary2bcd_double_dabble binary2bcd_double_dabble(
.binary_in(binary_in),
.clk(clk),
.rst_n(rst_n),
.unpacked_bcd(unpacked_bcd),
.packed_bcd(packed_bcd)
);

//  dump the waveform of the simulation for fsdb//
/*initial begin
 $fsdbDumpfile("testbench.fsdb"); 
 $fsdbDumpvars;              
end*/

// dump the waveform of the simulation for vcd//
initial begin
  $dumpfile("testbench.vcd");
  $dumpvars("+mda");
end

reg [39:0] golden [0:N];
initial begin
  $readmemb("golden.dat",golden);
end

always #(CYCLE/2) clk = ~clk; 
always #(CYCLE) rst_n = ~rst_n;

// System block set only clock,reset signal and the timeout finish. 
initial begin
  clk = 1;
  rst_n = 1;
  // system reset
end

// output result checking block, control when to sample and verify the result.
integer fp_w;
reg [11:0] correct_data_packed;
reg [19:0] correct_data_unpacked;

initial begin
// error count
  error = 0;
// Use the same control technique to control when to sample output result.
// adder output for two cycle from input to output
  // you can also write the result to a text file
  fp_w = $fopen("answer.txt");
  for (j = 0; j < N; j = j + 1) begin
    @(negedge rst_n);
    //#(CYCLE);
    binary_in = golden[j][39:32];
    correct_data_packed = golden[j][31:20];
    correct_data_unpacked = golden[j][19:0];
    #(CYCLE);
    if(packed_bcd !== correct_data_packed || unpacked_bcd !== correct_data_unpacked) begin
        error = error + 1;
        $display("************* Pattern No.%d is wrong at %t ************", j,$time);
        $display("signal_in = %b, correct packed data is %b, correct unpacked data is %b,", binary_in, correct_data_packed, correct_data_unpacked);
        $display("but your result is %b and %b !!", packed_bcd, correct_data_unpacked);
      end
      $fdisplay(fp_w, "%b  %b___%b %b___%b", binary_in, correct_data_packed, packed_bcd, correct_data_unpacked, unpacked_bcd);
  end

  $fclose(fp_w);

  if(error == 0) begin
    $display("Congratulations!! The functionality of your binary2bcd is correct!!");
  end
  else begin
    $display("error !!");
  end 
  #(CYCLE) $finish; 

end

endmodule

binary2bcd_double_dabble/xsim/testbench.vcd
$date
   Tue Jan 14 02:09:02 2025
$end
$version
  2022.1
$end
$timescale
  1ps
$end
$scope module testbench $end
$var reg 8 ! binary_in [7:0] $end
$var reg 1 " clk $end
$var reg 1 # rst_n $end
$var wire 20 $ unpacked_bcd [19:0] $end
$var wire 12 % packed_bcd [11:0] $end
$var integer 32 & j [31:0] $end
$var integer 32 ' error [31:0] $end
$var integer 32 ( fp_w [31:0] $end
$var reg 12 ) correct_data_packed [11:0] $end
$var reg 20 * correct_data_unpacked [19:0] $end
$scope module binary2bcd_double_dabble $end
$var wire 8 + binary_in [7:0] $end
$var wire 1 , clk $end
$var wire 1 - rst_n $end
$var reg 20 . unpacked_bcd [19:0] $end
$var reg 12 / packed_bcd [11:0] $end
$var wire 4 0 zero_4 [3:0] $end
$var reg 20 1 scratch_pad [19:0] $end
$var reg 20 2 scratch_pad_temp [19:0] $end
$var integer 32 3 i [31:0] $end
$var integer 32 4 j [31:0] $end
$upscope $end
$upscope $end
$enddefinitions $end
#0
$dumpvars
bx !
1"
1#
bx $
bx %
b0 &
b0 '
b10 (
bx )
bx *
bx +
1,
1-
bx .
bx /
b0 0
bx 1
bx 2
bx 3
bx 4
$end
#5000
0"
0,
#10000
b0 !
1"
0#
b0 $
b0 %
b0 )
b0 *
b0 +
1,
0-
b0 .
b0 /
b0 1
b0 2
b111 3
b11 4
#15000
0"
0,
#20000
1"
1#
b1 &
1,
1-
#25000
0"
0,
#30000
b1 !
1"
0#
b1 $
b1 %
b1 )
b1 *
b1 +
1,
0-
b1 .
b1 /
b100000000 1
b10000000 2
b111 3
b11 4
#35000
0"
0,
#40000
1"
1#
b10 &
1,
1-
#45000
0"
0,
#50000
b10 !
1"
0#
b10 $
b10 %
b10 )
b10 *
b10 +
1,
0-
b10 .
b10 /
b1000000000 1
b100000000 2
b111 3
b11 4
#55000
0"
0,
#60000
1"
1#
b11 &
1,
1-
#65000
0"
0,
#70000
b11 !
1"
0#
b11 $
b11 %
b11 )
b11 *
b11 +
1,
0-
b11 .
b11 /
b1100000000 1
b110000000 2
b111 3
b11 4
#75000
0"
0,
#80000
1"
1#
b100 &
1,
1-
#85000
0"
0,
#90000
b100 !
1"
0#
b100 $
b100 %
b100 )
b100 *
b100 +
1,
0-
b100 .
b100 /
b10000000000 1
b1000000000 2
b111 3
b11 4
#95000
0"
0,
#100000
1"
1#
b101 &
1,
1-
#105000
0"
0,
#110000
b101 !
1"
0#
b101 $
b101 %
b101 )
b101 *
b101 +
1,
0-
b101 .
b101 /
b10100000000 1
b1010000000 2
b111 3
b11 4
#115000
0"
0,
#120000
1"
1#
b110 &
1,
1-
#125000
0"
0,
#130000
b110 !
1"
0#
b110 $
b110 %
b110 )
b110 *
b110 +
1,
0-
b110 .
b110 /
b11000000000 1
b1100000000 2
b111 3
b11 4
#135000
0"
0,
#140000
1"
1#
b111 &
1,
1-
#145000
0"
0,
#150000
b111 !
1"
0#
b111 $
b111 %
b111 )
b111 *
b111 +
1,
0-
b111 .
b111 /
b11100000000 1
b1110000000 2
b111 3
b11 4
#155000
0"
0,
#160000
1"
1#
b1000 &
1,
1-
#165000
0"
0,
#170000
b1000 !
1"
0#
b1000 $
b1000 %
b1000 )
b1000 *
b1000 +
1,
0-
b1000 .
b1000 /
b100000000000 1
b10000000000 2
b111 3
b11 4
#175000
0"
0,
#180000
1"
1#
b1001 &
1,
1-
#185000
0"
0,
#190000
b1001 !
1"
0#
b1001 $
b1001 %
b1001 )
b1001 *
b1001 +
1,
0-
b1001 .
b1001 /
b100100000000 1
b10010000000 2
b111 3
b11 4
#195000
0"
0,
#200000
1"
1#
b1010 &
1,
1-
#205000
0"
0,
#210000
b1010 !
1"
0#
b100000000 $
b10000 %
b10000 )
b100000000 *
b1010 +
1,
0-
b100000000 .
b10000 /
b1000000000000 1
b100000000000 2
b111 3
b11 4
#215000
0"
0,
#220000
1"
1#
b1011 &
1,
1-
#225000
0"
0,
#230000
b1011 !
1"
0#
b100000001 $
b10001 %
b10001 )
b100000001 *
b1011 +
1,
0-
b100000001 .
b10001 /
b1000100000000 1
b100010000000 2
b111 3
b11 4
#235000
0"
0,
#240000
1"
1#
b1100 &
1,
1-
#245000
0"
0,
#250000
b1100 !
1"
0#
b100000010 $
b10010 %
b10010 )
b100000010 *
b1100 +
1,
0-
b100000010 .
b10010 /
b1001000000000 1
b100100000000 2
b111 3
b11 4
#255000
0"
0,
#260000
1"
1#
b1101 &
1,
1-
#265000
0"
0,
#270000
b1101 !
1"
0#
b100000011 $
b10011 %
b10011 )
b100000011 *
b1101 +
1,
0-
b100000011 .
b10011 /
b1001100000000 1
b100110000000 2
b111 3
b11 4
#275000
0"
0,
#280000
1"
1#
b1110 &
1,
1-
#285000
0"
0,
#290000
b1110 !
1"
0#
b100000100 $
b10100 %
b10100 )
b100000100 *
b1110 +
1,
0-
b100000100 .
b10100 /
b1010000000000 1
b101000000000 2
b111 3
b11 4
#295000
0"
0,
#300000
1"
1#
b1111 &
1,
1-
#305000
0"
0,
#310000
b1111 !
1"
0#
b100000101 $
b10101 %
b10101 )
b100000101 *
b1111 +
1,
0-
b100000101 .
b10101 /
b1010100000000 1
b101010000000 2
b111 3
b11 4
#315000
0"
0,
#320000
1"
1#
b10000 &
1,
1-
#325000
0"
0,
#330000
b10000 !
1"
0#
b100000110 $
b10110 %
b10110 )
b100000110 *
b10000 +
1,
0-
b100000110 .
b10110 /
b1011000000000 1
b101100000000 2
b111 3
b11 4
#335000
0"
0,
#340000
1"
1#
b10001 &
1,
1-
#345000
0"
0,
#350000
b10001 !
1"
0#
b100000111 $
b10111 %
b10111 )
b100000111 *
b10001 +
1,
0-
b100000111 .
b10111 /
b1011100000000 1
b101110000000 2
b111 3
b11 4
#355000
0"
0,
#360000
1"
1#
b10010 &
1,
1-
#365000
0"
0,
#370000
b10010 !
1"
0#
b100001000 $
b11000 %
b11000 )
b100001000 *
b10010 +
1,
0-
b100001000 .
b11000 /
b1100000000000 1
b110000000000 2
b111 3
b11 4
#375000
0"
0,
#380000
1"
1#
b10011 &
1,
1-
#385000
0"
0,
#390000
b10011 !
1"
0#
b100001001 $
b11001 %
b11001 )
b100001001 *
b10011 +
1,
0-
b100001001 .
b11001 /
b1100100000000 1
b110010000000 2
b111 3
b11 4
#395000
0"
0,
#400000
1"
1#
b10100 &
1,
1-
#405000
0"
0,
#410000
b10100 !
1"
0#
b1000000000 $
b100000 %
b100000 )
b1000000000 *
b10100 +
1,
0-
b1000000000 .
b100000 /
b10000000000000 1
b1000000000000 2
b111 3
b11 4
#415000
0"
0,
#420000
1"
1#
b10101 &
1,
1-
#425000
0"
0,
#430000
b10101 !
1"
0#
b1000000001 $
b100001 %
b100001 )
b1000000001 *
b10101 +
1,
0-
b1000000001 .
b100001 /
b10000100000000 1
b1000010000000 2
b111 3
b11 4
#435000
0"
0,
#440000
1"
1#
b10110 &
1,
1-
#445000
0"
0,
#450000
b10110 !
1"
0#
b1000000010 $
b100010 %
b100010 )
b1000000010 *
b10110 +
1,
0-
b1000000010 .
b100010 /
b10001000000000 1
b1000100000000 2
b111 3
b11 4
#455000
0"
0,
#460000
1"
1#
b10111 &
1,
1-
#465000
0"
0,
#470000
b10111 !
1"
0#
b1000000011 $
b100011 %
b100011 )
b1000000011 *
b10111 +
1,
0-
b1000000011 .
b100011 /
b10001100000000 1
b1000110000000 2
b111 3
b11 4
#475000
0"
0,
#480000
1"
1#
b11000 &
1,
1-
#485000
0"
0,
#490000
b11000 !
1"
0#
b1000000100 $
b100100 %
b100100 )
b1000000100 *
b11000 +
1,
0-
b1000000100 .
b100100 /
b10010000000000 1
b1001000000000 2
b111 3
b11 4
#495000
0"
0,
#500000
1"
1#
b11001 &
1,
1-
#505000
0"
0,
#510000
b11001 !
1"
0#
b1000000101 $
b100101 %
b100101 )
b1000000101 *
b11001 +
1,
0-
b1000000101 .
b100101 /
b10010100000000 1
b1001010000000 2
b111 3
b11 4
#515000
0"
0,
#520000
1"
1#
b11010 &
1,
1-
#525000
0"
0,
#530000
b11010 !
1"
0#
b1000000110 $
b100110 %
b100110 )
b1000000110 *
b11010 +
1,
0-
b1000000110 .
b100110 /
b10011000000000 1
b1001100000000 2
b111 3
b11 4
#535000
0"
0,
#540000
1"
1#
b11011 &
1,
1-
#545000
0"
0,
#550000
b11011 !
1"
0#
b1000000111 $
b100111 %
b100111 )
b1000000111 *
b11011 +
1,
0-
b1000000111 .
b100111 /
b10011100000000 1
b1001110000000 2
b111 3
b11 4
#555000
0"
0,
#560000
1"
1#
b11100 &
1,
1-
#565000
0"
0,
#570000
b11100 !
1"
0#
b1000001000 $
b101000 %
b101000 )
b1000001000 *
b11100 +
1,
0-
b1000001000 .
b101000 /
b10100000000000 1
b1010000000000 2
b111 3
b11 4
#575000
0"
0,
#580000
1"
1#
b11101 &
1,
1-
#585000
0"
0,
#590000
b11101 !
1"
0#
b1000001001 $
b101001 %
b101001 )
b1000001001 *
b11101 +
1,
0-
b1000001001 .
b101001 /
b10100100000000 1
b1010010000000 2
b111 3
b11 4
#595000
0"
0,
#600000
1"
1#
b11110 &
1,
1-
#605000
0"
0,
#610000
b11110 !
1"
0#
b1100000000 $
b110000 %
b110000 )
b1100000000 *
b11110 +
1,
0-
b1100000000 .
b110000 /
b11000000000000 1
b1100000000000 2
b111 3
b11 4
#615000
0"
0,
#620000
1"
1#
b11111 &
1,
1-
#625000
0"
0,
#630000
b11111 !
1"
0#
b1100000001 $
b110001 %
b110001 )
b1100000001 *
b11111 +
1,
0-
b1100000001 .
b110001 /
b11000100000000 1
b1100010000000 2
b111 3
b11 4
#635000
0"
0,
#640000
1"
1#
b100000 &
1,
1-
#645000
0"
0,
#650000
b100000 !
1"
0#
b1100000010 $
b110010 %
b110010 )
b1100000010 *
b100000 +
1,
0-
b1100000010 .
b110010 /
b11001000000000 1
b1100100000000 2
b111 3
b11 4
#655000
0"
0,
#660000
1"
1#
b100001 &
1,
1-
#665000
0"
0,
#670000
b100001 !
1"
0#
b1100000011 $
b110011 %
b110011 )
b1100000011 *
b100001 +
1,
0-
b1100000011 .
b110011 /
b11001100000000 1
b1100110000000 2
b111 3
b11 4
#675000
0"
0,
#680000
1"
1#
b100010 &
1,
1-
#685000
0"
0,
#690000
b100010 !
1"
0#
b1100000100 $
b110100 %
b110100 )
b1100000100 *
b100010 +
1,
0-
b1100000100 .
b110100 /
b11010000000000 1
b1101000000000 2
b111 3
b11 4
#695000
0"
0,
#700000
1"
1#
b100011 &
1,
1-
#705000
0"
0,
#710000
b100011 !
1"
0#
b1100000101 $
b110101 %
b110101 )
b1100000101 *
b100011 +
1,
0-
b1100000101 .
b110101 /
b11010100000000 1
b1101010000000 2
b111 3
b11 4
#715000
0"
0,
#720000
1"
1#
b100100 &
1,
1-
#725000
0"
0,
#730000
b100100 !
1"
0#
b1100000110 $
b110110 %
b110110 )
b1100000110 *
b100100 +
1,
0-
b1100000110 .
b110110 /
b11011000000000 1
b1101100000000 2
b111 3
b11 4
#735000
0"
0,
#740000
1"
1#
b100101 &
1,
1-
#745000
0"
0,
#750000
b100101 !
1"
0#
b1100000111 $
b110111 %
b110111 )
b1100000111 *
b100101 +
1,
0-
b1100000111 .
b110111 /
b11011100000000 1
b1101110000000 2
b111 3
b11 4
#755000
0"
0,
#760000
1"
1#
b100110 &
1,
1-
#765000
0"
0,
#770000
b100110 !
1"
0#
b1100001000 $
b111000 %
b111000 )
b1100001000 *
b100110 +
1,
0-
b1100001000 .
b111000 /
b11100000000000 1
b1110000000000 2
b111 3
b11 4
#775000
0"
0,
#780000
1"
1#
b100111 &
1,
1-
#785000
0"
0,
#790000
b100111 !
1"
0#
b1100001001 $
b111001 %
b111001 )
b1100001001 *
b100111 +
1,
0-
b1100001001 .
b111001 /
b11100100000000 1
b1110010000000 2
b111 3
b11 4
#795000
0"
0,
#800000
1"
1#
b101000 &
1,
1-
#805000
0"
0,
#810000
b101000 !
1"
0#
b10000000000 $
b1000000 %
b1000000 )
b10000000000 *
b101000 +
1,
0-
b10000000000 .
b1000000 /
b100000000000000 1
b10000000000000 2
b111 3
b11 4
#815000
0"
0,
#820000
1"
1#
b101001 &
1,
1-
#825000
0"
0,
#830000
b101001 !
1"
0#
b10000000001 $
b1000001 %
b1000001 )
b10000000001 *
b101001 +
1,
0-
b10000000001 .
b1000001 /
b100000100000000 1
b10000010000000 2
b111 3
b11 4
#835000
0"
0,
#840000
1"
1#
b101010 &
1,
1-
#845000
0"
0,
#850000
b101010 !
1"
0#
b10000000010 $
b1000010 %
b1000010 )
b10000000010 *
b101010 +
1,
0-
b10000000010 .
b1000010 /
b100001000000000 1
b10000100000000 2
b111 3
b11 4
#855000
0"
0,
#860000
1"
1#
b101011 &
1,
1-
#865000
0"
0,
#870000
b101011 !
1"
0#
b10000000011 $
b1000011 %
b1000011 )
b10000000011 *
b101011 +
1,
0-
b10000000011 .
b1000011 /
b100001100000000 1
b10000110000000 2
b111 3
b11 4
#875000
0"
0,
#880000
1"
1#
b101100 &
1,
1-
#885000
0"
0,
#890000
b101100 !
1"
0#
b10000000100 $
b1000100 %
b1000100 )
b10000000100 *
b101100 +
1,
0-
b10000000100 .
b1000100 /
b100010000000000 1
b10001000000000 2
b111 3
b11 4
#895000
0"
0,
#900000
1"
1#
b101101 &
1,
1-
#905000
0"
0,
#910000
b101101 !
1"
0#
b10000000101 $
b1000101 %
b1000101 )
b10000000101 *
b101101 +
1,
0-
b10000000101 .
b1000101 /
b100010100000000 1
b10001010000000 2
b111 3
b11 4
#915000
0"
0,
#920000
1"
1#
b101110 &
1,
1-
#925000
0"
0,
#930000
b101110 !
1"
0#
b10000000110 $
b1000110 %
b1000110 )
b10000000110 *
b101110 +
1,
0-
b10000000110 .
b1000110 /
b100011000000000 1
b10001100000000 2
b111 3
b11 4
#935000
0"
0,
#940000
1"
1#
b101111 &
1,
1-
#945000
0"
0,
#950000
b101111 !
1"
0#
b10000000111 $
b1000111 %
b1000111 )
b10000000111 *
b101111 +
1,
0-
b10000000111 .
b1000111 /
b100011100000000 1
b10001110000000 2
b111 3
b11 4
#955000
0"
0,
#960000
1"
1#
b110000 &
1,
1-
#965000
0"
0,
#970000
b110000 !
1"
0#
b10000001000 $
b1001000 %
b1001000 )
b10000001000 *
b110000 +
1,
0-
b10000001000 .
b1001000 /
b100100000000000 1
b10010000000000 2
b111 3
b11 4
#975000
0"
0,
#980000
1"
1#
b110001 &
1,
1-
#985000
0"
0,
#990000
b110001 !
1"
0#
b10000001001 $
b1001001 %
b1001001 )
b10000001001 *
b110001 +
1,
0-
b10000001001 .
b1001001 /
b100100100000000 1
b10010010000000 2
b111 3
b11 4
#995000
0"
0,
#1000000
1"
1#
b110010 &
1,
1-
#1005000
0"
0,
#1010000
b110010 !
1"
0#
b10100000000 $
b1010000 %
b1010000 )
b10100000000 *
b110010 +
1,
0-
b10100000000 .
b1010000 /
b101000000000000 1
b10100000000000 2
b111 3
b11 4
#1015000
0"
0,
#1020000
1"
1#
b110011 &
1,
1-
#1025000
0"
0,
#1030000
b110011 !
1"
0#
b10100000001 $
b1010001 %
b1010001 )
b10100000001 *
b110011 +
1,
0-
b10100000001 .
b1010001 /
b101000100000000 1
b10100010000000 2
b111 3
b11 4
#1035000
0"
0,
#1040000
1"
1#
b110100 &
1,
1-
#1045000
0"
0,
#1050000
b110100 !
1"
0#
b10100000010 $
b1010010 %
b1010010 )
b10100000010 *
b110100 +
1,
0-
b10100000010 .
b1010010 /
b101001000000000 1
b10100100000000 2
b111 3
b11 4
#1055000
0"
0,
#1060000
1"
1#
b110101 &
1,
1-
#1065000
0"
0,
#1070000
b110101 !
1"
0#
b10100000011 $
b1010011 %
b1010011 )
b10100000011 *
b110101 +
1,
0-
b10100000011 .
b1010011 /
b101001100000000 1
b10100110000000 2
b111 3
b11 4
#1075000
0"
0,
#1080000
1"
1#
b110110 &
1,
1-
#1085000
0"
0,
#1090000
b110110 !
1"
0#
b10100000100 $
b1010100 %
b1010100 )
b10100000100 *
b110110 +
1,
0-
b10100000100 .
b1010100 /
b101010000000000 1
b10101000000000 2
b111 3
b11 4
#1095000
0"
0,
#1100000
1"
1#
b110111 &
1,
1-
#1105000
0"
0,
#1110000
b110111 !
1"
0#
b10100000101 $
b1010101 %
b1010101 )
b10100000101 *
b110111 +
1,
0-
b10100000101 .
b1010101 /
b101010100000000 1
b10101010000000 2
b111 3
b11 4
#1115000
0"
0,
#1120000
1"
1#
b111000 &
1,
1-
#1125000
0"
0,
#1130000
b111000 !
1"
0#
b10100000110 $
b1010110 %
b1010110 )
b10100000110 *
b111000 +
1,
0-
b10100000110 .
b1010110 /
b101011000000000 1
b10101100000000 2
b111 3
b11 4
#1135000
0"
0,
#1140000
1"
1#
b111001 &
1,
1-
#1145000
0"
0,
#1150000
b111001 !
1"
0#
b10100000111 $
b1010111 %
b1010111 )
b10100000111 *
b111001 +
1,
0-
b10100000111 .
b1010111 /
b101011100000000 1
b10101110000000 2
b111 3
b11 4
#1155000
0"
0,
#1160000
1"
1#
b111010 &
1,
1-
#1165000
0"
0,
#1170000
b111010 !
1"
0#
b10100001000 $
b1011000 %
b1011000 )
b10100001000 *
b111010 +
1,
0-
b10100001000 .
b1011000 /
b101100000000000 1
b10110000000000 2
b111 3
b11 4
#1175000
0"
0,
#1180000
1"
1#
b111011 &
1,
1-
#1185000
0"
0,
#1190000
b111011 !
1"
0#
b10100001001 $
b1011001 %
b1011001 )
b10100001001 *
b111011 +
1,
0-
b10100001001 .
b1011001 /
b101100100000000 1
b10110010000000 2
b111 3
b11 4
#1195000
0"
0,
#1200000
1"
1#
b111100 &
1,
1-
#1205000
0"
0,
#1210000
b111100 !
1"
0#
b11000000000 $
b1100000 %
b1100000 )
b11000000000 *
b111100 +
1,
0-
b11000000000 .
b1100000 /
b110000000000000 1
b11000000000000 2
b111 3
b11 4
#1215000
0"
0,
#1220000
1"
1#
b111101 &
1,
1-
#1225000
0"
0,
#1230000
b111101 !
1"
0#
b11000000001 $
b1100001 %
b1100001 )
b11000000001 *
b111101 +
1,
0-
b11000000001 .
b1100001 /
b110000100000000 1
b11000010000000 2
b111 3
b11 4
#1235000
0"
0,
#1240000
1"
1#
b111110 &
1,
1-
#1245000
0"
0,
#1250000
b111110 !
1"
0#
b11000000010 $
b1100010 %
b1100010 )
b11000000010 *
b111110 +
1,
0-
b11000000010 .
b1100010 /
b110001000000000 1
b11000100000000 2
b111 3
b11 4
#1255000
0"
0,
#1260000
1"
1#
b111111 &
1,
1-
#1265000
0"
0,
#1270000
b111111 !
1"
0#
b11000000011 $
b1100011 %
b1100011 )
b11000000011 *
b111111 +
1,
0-
b11000000011 .
b1100011 /
b110001100000000 1
b11000110000000 2
b111 3
b11 4
#1275000
0"
0,
#1280000
1"
1#
b1000000 &
1,
1-
#1285000
0"
0,
#1290000
b1000000 !
1"
0#
b11000000100 $
b1100100 %
b1100100 )
b11000000100 *
b1000000 +
1,
0-
b11000000100 .
b1100100 /
b110010000000000 1
b11001000000000 2
b111 3
b11 4
#1295000
0"
0,
#1300000
1"
1#
b1000001 &
1,
1-
#1305000
0"
0,
#1310000
b1000001 !
1"
0#
b11000000101 $
b1100101 %
b1100101 )
b11000000101 *
b1000001 +
1,
0-
b11000000101 .
b1100101 /
b110010100000000 1
b11001010000000 2
b111 3
b11 4
#1315000
0"
0,
#1320000
1"
1#
b1000010 &
1,
1-
#1325000
0"
0,
#1330000
b1000010 !
1"
0#
b11000000110 $
b1100110 %
b1100110 )
b11000000110 *
b1000010 +
1,
0-
b11000000110 .
b1100110 /
b110011000000000 1
b11001100000000 2
b111 3
b11 4
#1335000
0"
0,
#1340000
1"
1#
b1000011 &
1,
1-
#1345000
0"
0,
#1350000
b1000011 !
1"
0#
b11000000111 $
b1100111 %
b1100111 )
b11000000111 *
b1000011 +
1,
0-
b11000000111 .
b1100111 /
b110011100000000 1
b11001110000000 2
b111 3
b11 4
#1355000
0"
0,
#1360000
1"
1#
b1000100 &
1,
1-
#1365000
0"
0,
#1370000
b1000100 !
1"
0#
b11000001000 $
b1101000 %
b1101000 )
b11000001000 *
b1000100 +
1,
0-
b11000001000 .
b1101000 /
b110100000000000 1
b11010000000000 2
b111 3
b11 4
#1375000
0"
0,
#1380000
1"
1#
b1000101 &
1,
1-
#1385000
0"
0,
#1390000
b1000101 !
1"
0#
b11000001001 $
b1101001 %
b1101001 )
b11000001001 *
b1000101 +
1,
0-
b11000001001 .
b1101001 /
b110100100000000 1
b11010010000000 2
b111 3
b11 4
#1395000
0"
0,
#1400000
1"
1#
b1000110 &
1,
1-
#1405000
0"
0,
#1410000
b1000110 !
1"
0#
b11100000000 $
b1110000 %
b1110000 )
b11100000000 *
b1000110 +
1,
0-
b11100000000 .
b1110000 /
b111000000000000 1
b11100000000000 2
b111 3
b11 4
#1415000
0"
0,
#1420000
1"
1#
b1000111 &
1,
1-
#1425000
0"
0,
#1430000
b1000111 !
1"
0#
b11100000001 $
b1110001 %
b1110001 )
b11100000001 *
b1000111 +
1,
0-
b11100000001 .
b1110001 /
b111000100000000 1
b11100010000000 2
b111 3
b11 4
#1435000
0"
0,
#1440000
1"
1#
b1001000 &
1,
1-
#1445000
0"
0,
#1450000
b1001000 !
1"
0#
b11100000010 $
b1110010 %
b1110010 )
b11100000010 *
b1001000 +
1,
0-
b11100000010 .
b1110010 /
b111001000000000 1
b11100100000000 2
b111 3
b11 4
#1455000
0"
0,
#1460000
1"
1#
b1001001 &
1,
1-
#1465000
0"
0,
#1470000
b1001001 !
1"
0#
b11100000011 $
b1110011 %
b1110011 )
b11100000011 *
b1001001 +
1,
0-
b11100000011 .
b1110011 /
b111001100000000 1
b11100110000000 2
b111 3
b11 4
#1475000
0"
0,
#1480000
1"
1#
b1001010 &
1,
1-
#1485000
0"
0,
#1490000
b1001010 !
1"
0#
b11100000100 $
b1110100 %
b1110100 )
b11100000100 *
b1001010 +
1,
0-
b11100000100 .
b1110100 /
b111010000000000 1
b11101000000000 2
b111 3
b11 4
#1495000
0"
0,
#1500000
1"
1#
b1001011 &
1,
1-
#1505000
0"
0,
#1510000
b1001011 !
1"
0#
b11100000101 $
b1110101 %
b1110101 )
b11100000101 *
b1001011 +
1,
0-
b11100000101 .
b1110101 /
b111010100000000 1
b11101010000000 2
b111 3
b11 4
#1515000
0"
0,
#1520000
1"
1#
b1001100 &
1,
1-
#1525000
0"
0,
#1530000
b1001100 !
1"
0#
b11100000110 $
b1110110 %
b1110110 )
b11100000110 *
b1001100 +
1,
0-
b11100000110 .
b1110110 /
b111011000000000 1
b11101100000000 2
b111 3
b11 4
#1535000
0"
0,
#1540000
1"
1#
b1001101 &
1,
1-
#1545000
0"
0,
#1550000
b1001101 !
1"
0#
b11100000111 $
b1110111 %
b1110111 )
b11100000111 *
b1001101 +
1,
0-
b11100000111 .
b1110111 /
b111011100000000 1
b11101110000000 2
b111 3
b11 4
#1555000
0"
0,
#1560000
1"
1#
b1001110 &
1,
1-
#1565000
0"
0,
#1570000
b1001110 !
1"
0#
b11100001000 $
b1111000 %
b1111000 )
b11100001000 *
b1001110 +
1,
0-
b11100001000 .
b1111000 /
b111100000000000 1
b11110000000000 2
b111 3
b11 4
#1575000
0"
0,
#1580000
1"
1#
b1001111 &
1,
1-
#1585000
0"
0,
#1590000
b1001111 !
1"
0#
b11100001001 $
b1111001 %
b1111001 )
b11100001001 *
b1001111 +
1,
0-
b11100001001 .
b1111001 /
b111100100000000 1
b11110010000000 2
b111 3
b11 4
#1595000
0"
0,
#1600000
1"
1#
b1010000 &
1,
1-
#1605000
0"
0,
#1610000
b1010000 !
1"
0#
b100000000000 $
b10000000 %
b10000000 )
b100000000000 *
b1010000 +
1,
0-
b100000000000 .
b10000000 /
b1000000000000000 1
b100000000000000 2
b111 3
b11 4
#1615000
0"
0,
#1620000
1"
1#
b1010001 &
1,
1-
#1625000
0"
0,
#1630000
b1010001 !
1"
0#
b100000000001 $
b10000001 %
b10000001 )
b100000000001 *
b1010001 +
1,
0-
b100000000001 .
b10000001 /
b1000000100000000 1
b100000010000000 2
b111 3
b11 4
#1635000
0"
0,
#1640000
1"
1#
b1010010 &
1,
1-
#1645000
0"
0,
#1650000
b1010010 !
1"
0#
b100000000010 $
b10000010 %
b10000010 )
b100000000010 *
b1010010 +
1,
0-
b100000000010 .
b10000010 /
b1000001000000000 1
b100000100000000 2
b111 3
b11 4
#1655000
0"
0,
#1660000
1"
1#
b1010011 &
1,
1-
#1665000
0"
0,
#1670000
b1010011 !
1"
0#
b100000000011 $
b10000011 %
b10000011 )
b100000000011 *
b1010011 +
1,
0-
b100000000011 .
b10000011 /
b1000001100000000 1
b100000110000000 2
b111 3
b11 4
#1675000
0"
0,
#1680000
1"
1#
b1010100 &
1,
1-
#1685000
0"
0,
#1690000
b1010100 !
1"
0#
b100000000100 $
b10000100 %
b10000100 )
b100000000100 *
b1010100 +
1,
0-
b100000000100 .
b10000100 /
b1000010000000000 1
b100001000000000 2
b111 3
b11 4
#1695000
0"
0,
#1700000
1"
1#
b1010101 &
1,
1-
#1705000
0"
0,
#1710000
b1010101 !
1"
0#
b100000000101 $
b10000101 %
b10000101 )
b100000000101 *
b1010101 +
1,
0-
b100000000101 .
b10000101 /
b1000010100000000 1
b100001010000000 2
b111 3
b11 4
#1715000
0"
0,
#1720000
1"
1#
b1010110 &
1,
1-
#1725000
0"
0,
