binary2bcd_double_dabble/hdl/binary2bcd_double_dabble.v
module binary2bcd_double_dabble (
  input wire [7:0] binary_in,
  output reg [19:0] unpacked_bcd,
  output reg [11:0] packed_bcd
);

  // 定義常數
  localparam FOUR = 4;
  localparam THREE = 3;
  localparam ZERO = 4'b0000;

  // 暫存變數
  reg [19:0] scratch_pad;
  reg [19:0] scratch_pad_temp;
  integer i, j;

  // 組合邏輯
  always @(*) begin
    // 初始化暫存器
    scratch_pad = {12'b0, binary_in};
    scratch_pad_temp = 20'b0;

    // Double Dabble 演算法
    for (i = 0; i < 8; i = i + 1) begin
      // 每次迴圈，檢查每個 BCD 的 4-bit 區塊
      for (j = 0; j < 3; j = j + 1) begin
        case (j)
          2'b00: if (scratch_pad[19:16] > FOUR) scratch_pad[19:16] = scratch_pad[19:16] + THREE;
          2'b01: if (scratch_pad[15:12] > FOUR) scratch_pad[15:12] = scratch_pad[15:12] + THREE;
          2'b10: if (scratch_pad[11:8] > FOUR)  scratch_pad[11:8]  = scratch_pad[11:8]  + THREE;
        endcase
      end

      // 將數值左移一位
      scratch_pad = scratch_pad << 1;
    end

    // 生成輸出
    packed_bcd = scratch_pad[19:8];
    unpacked_bcd = {scratch_pad[19:16], ZERO, scratch_pad[15:12], ZERO, scratch_pad[11:8]};
  end

endmodule

binary2bcd_double_dabble/xsim/binary2bcd_double_dabble_tb.v
// set the timescale for the simulation
 `timescale 1ns/1ps 
module testbench;  // module of testbench

// localparam
localparam N = 256;
localparam CYCLE = 10;
// input signal use reg
reg [7:0] binary_in;

// output signal use wire
wire [19:0] unpacked_bcd;
wire [11:0] packed_bcd;

// interger 
integer j, error;
///// instantiate  module /////
// instantiate the module you finished in following format //
// module_name #(.parameter1(5),.parameter2(3)) unit_name (.port1(...), .port2(...), ...); //
binary2bcd_double_dabble binary2bcd_double_dabble(
.binary_in(binary_in),
.unpacked_bcd(unpacked_bcd),
.packed_bcd(packed_bcd)
);

//  dump the waveform of the simulation for fsdb//
/*initial begin
 $fsdbDumpfile("testbench.fsdb"); 
 $fsdbDumpvars;              
end*/

// dump the waveform of the simulation for vcd//
initial begin
  $dumpfile("testbench.vcd");
  $dumpvars("+mda");
end

reg [39:0] golden [0:N];
initial begin
  $readmemb("golden.dat",golden);
end


// output result checking block, control when to sample and verify the result.
integer fp_w;
reg [11:0] correct_data_packed;
reg [19:0] correct_data_unpacked;

initial begin
// error count
  error = 0;
// Use the same control technique to control when to sample output result.
// adder output for two cycle from input to output
  // you can also write the result to a text file
  fp_w = $fopen("answer.txt");
  for (j = 0; j < N; j = j + 1) begin
    //#(CYCLE);
    binary_in = golden[j][39:32];
    correct_data_packed = golden[j][31:20];
    correct_data_unpacked = golden[j][19:0];
    #(CYCLE);
    if(packed_bcd !== correct_data_packed || unpacked_bcd !== correct_data_unpacked) begin
        error = error + 1;
        $display("************* Pattern No.%d is wrong at %t ************", j,$time);
        $display("signal_in = %b, correct packed data is %b, correct unpacked data is %b,", binary_in, correct_data_packed, correct_data_unpacked);
        $display("but your result is %b and %b !!", packed_bcd, correct_data_unpacked);
      end
      $fdisplay(fp_w, "%b  %b___%b %b___%b", binary_in, correct_data_packed, packed_bcd, correct_data_unpacked, unpacked_bcd);
  end

  $fclose(fp_w);

  if(error == 0) begin
    $display("Congratulations!! The functionality of your binary2bcd is correct!!");
  end
  else begin
    $display("error !!");
  end 
  #(CYCLE) $finish; 

end

endmodule

binary2bcd_double_dabble/xsim/testbench.vcd
$date
   Wed Jan 15 02:39:11 2025
$end
$version
  2022.1
$end
$timescale
  1ps
$end
$scope module testbench $end
$var reg 8 ! binary_in [7:0] $end
$var wire 20 " unpacked_bcd [19:0] $end
$var wire 12 # packed_bcd [11:0] $end
$var integer 32 $ j [31:0] $end
$var integer 32 % error [31:0] $end
$var integer 32 & fp_w [31:0] $end
$var reg 12 ' correct_data_packed [11:0] $end
$var reg 20 ( correct_data_unpacked [19:0] $end
$scope module binary2bcd_double_dabble $end
$var wire 8 ) binary_in [7:0] $end
$var reg 20 * unpacked_bcd [19:0] $end
$var reg 12 + packed_bcd [11:0] $end
$var reg 20 , scratch_pad [19:0] $end
$var reg 20 - scratch_pad_temp [19:0] $end
$var integer 32 . i [31:0] $end
$var integer 32 / j [31:0] $end
$upscope $end
$upscope $end
$enddefinitions $end
#0
$dumpvars
b0 !
b0 "
b0 #
b0 $
b0 %
b10 &
b0 '
b0 (
b0 )
b0 *
b0 +
b0 ,
b0 -
b1000 .
b11 /
$end
#10000
b1 !
b1 "
b1 #
b1 $
b1 '
b1 (
b1 )
b1 *
b1 +
b100000000 ,
b0 -
b1000 .
b11 /
#20000
b10 !
b10 "
b10 #
b10 $
b10 '
b10 (
b10 )
b10 *
b10 +
b1000000000 ,
b0 -
b1000 .
b11 /
#30000
b11 !
b11 "
b11 #
b11 $
b11 '
b11 (
b11 )
b11 *
b11 +
b1100000000 ,
b0 -
b1000 .
b11 /
#40000
b100 !
b100 "
b100 #
b100 $
b100 '
b100 (
b100 )
b100 *
b100 +
b10000000000 ,
b0 -
b1000 .
b11 /
#50000
b101 !
b101 "
b101 #
b101 $
b101 '
b101 (
b101 )
b101 *
b101 +
b10100000000 ,
b0 -
b1000 .
b11 /
#60000
b110 !
b110 "
b110 #
b110 $
b110 '
b110 (
b110 )
b110 *
b110 +
b11000000000 ,
b0 -
b1000 .
b11 /
#70000
b111 !
b111 "
b111 #
b111 $
b111 '
b111 (
b111 )
b111 *
b111 +
b11100000000 ,
b0 -
b1000 .
b11 /
#80000
b1000 !
b1000 "
b1000 #
b1000 $
b1000 '
b1000 (
b1000 )
b1000 *
b1000 +
b100000000000 ,
b0 -
b1000 .
b11 /
#90000
b1001 !
b1001 "
b1001 #
b1001 $
b1001 '
b1001 (
b1001 )
b1001 *
b1001 +
b100100000000 ,
b0 -
b1000 .
b11 /
#100000
b1010 !
b100000000 "
b10000 #
b1010 $
b10000 '
b100000000 (
b1010 )
b100000000 *
b10000 +
b1000000000000 ,
b0 -
b1000 .
b11 /
#110000
b1011 !
b100000001 "
b10001 #
b1011 $
b10001 '
b100000001 (
b1011 )
b100000001 *
b10001 +
b1000100000000 ,
b0 -
b1000 .
b11 /
#120000
b1100 !
b100000010 "
b10010 #
b1100 $
b10010 '
b100000010 (
b1100 )
b100000010 *
b10010 +
b1001000000000 ,
b0 -
b1000 .
b11 /
#130000
b1101 !
b100000011 "
b10011 #
b1101 $
b10011 '
b100000011 (
b1101 )
b100000011 *
b10011 +
b1001100000000 ,
b0 -
b1000 .
b11 /
#140000
b1110 !
b100000100 "
b10100 #
b1110 $
b10100 '
b100000100 (
b1110 )
b100000100 *
b10100 +
b1010000000000 ,
b0 -
b1000 .
b11 /
#150000
b1111 !
b100000101 "
b10101 #
b1111 $
b10101 '
b100000101 (
b1111 )
b100000101 *
b10101 +
b1010100000000 ,
b0 -
b1000 .
b11 /
#160000
b10000 !
b100000110 "
b10110 #
b10000 $
b10110 '
b100000110 (
b10000 )
b100000110 *
b10110 +
b1011000000000 ,
b0 -
b1000 .
b11 /
#170000
b10001 !
b100000111 "
b10111 #
b10001 $
b10111 '
b100000111 (
b10001 )
b100000111 *
b10111 +
b1011100000000 ,
b0 -
b1000 .
b11 /
#180000
b10010 !
b100001000 "
b11000 #
b10010 $
b11000 '
b100001000 (
b10010 )
b100001000 *
b11000 +
b1100000000000 ,
b0 -
b1000 .
b11 /
#190000
b10011 !
b100001001 "
b11001 #
b10011 $
b11001 '
b100001001 (
b10011 )
b100001001 *
b11001 +
b1100100000000 ,
b0 -
b1000 .
b11 /
#200000
b10100 !
b1000000000 "
b100000 #
b10100 $
b100000 '
b1000000000 (
b10100 )
b1000000000 *
b100000 +
b10000000000000 ,
b0 -
b1000 .
b11 /
#210000
b10101 !
b1000000001 "
b100001 #
b10101 $
b100001 '
b1000000001 (
b10101 )
b1000000001 *
b100001 +
b10000100000000 ,
b0 -
b1000 .
b11 /
#220000
b10110 !
b1000000010 "
b100010 #
b10110 $
b100010 '
b1000000010 (
b10110 )
b1000000010 *
b100010 +
b10001000000000 ,
b0 -
b1000 .
b11 /
#230000
b10111 !
b1000000011 "
b100011 #
b10111 $
b100011 '
b1000000011 (
b10111 )
b1000000011 *
b100011 +
b10001100000000 ,
b0 -
b1000 .
b11 /
#240000
b11000 !
b1000000100 "
b100100 #
b11000 $
b100100 '
b1000000100 (
b11000 )
b1000000100 *
b100100 +
b10010000000000 ,
b0 -
b1000 .
b11 /
#250000
b11001 !
b1000000101 "
b100101 #
b11001 $
b100101 '
b1000000101 (
b11001 )
b1000000101 *
b100101 +
b10010100000000 ,
b0 -
b1000 .
b11 /
#260000
b11010 !
b1000000110 "
b100110 #
b11010 $
b100110 '
b1000000110 (
b11010 )
b1000000110 *
b100110 +
b10011000000000 ,
b0 -
b1000 .
b11 /
#270000
b11011 !
b1000000111 "
b100111 #
b11011 $
b100111 '
b1000000111 (
b11011 )
b1000000111 *
b100111 +
b10011100000000 ,
b0 -
b1000 .
b11 /
#280000
b11100 !
b1000001000 "
b101000 #
b11100 $
b101000 '
b1000001000 (
b11100 )
b1000001000 *
b101000 +
b10100000000000 ,
b0 -
b1000 .
b11 /
#290000
b11101 !
b1000001001 "
b101001 #
b11101 $
b101001 '
b1000001001 (
b11101 )
b1000001001 *
b101001 +
b10100100000000 ,
b0 -
b1000 .
b11 /
#300000
b11110 !
b1100000000 "
b110000 #
b11110 $
b110000 '
b1100000000 (
b11110 )
b1100000000 *
b110000 +
b11000000000000 ,
b0 -
b1000 .
b11 /
#310000
b11111 !
b1100000001 "
b110001 #
b11111 $
b110001 '
b1100000001 (
b11111 )
b1100000001 *
b110001 +
b11000100000000 ,
b0 -
b1000 .
b11 /
#320000
b100000 !
b1100000010 "
b110010 #
b100000 $
b110010 '
b1100000010 (
b100000 )
b1100000010 *
b110010 +
b11001000000000 ,
b0 -
b1000 .
b11 /
#330000
b100001 !
b1100000011 "
b110011 #
b100001 $
b110011 '
b1100000011 (
b100001 )
b1100000011 *
b110011 +
b11001100000000 ,
b0 -
b1000 .
b11 /
#340000
b100010 !
b1100000100 "
b110100 #
b100010 $
b110100 '
b1100000100 (
b100010 )
b1100000100 *
b110100 +
b11010000000000 ,
b0 -
b1000 .
b11 /
#350000
b100011 !
b1100000101 "
b110101 #
b100011 $
b110101 '
b1100000101 (
b100011 )
b1100000101 *
b110101 +
b11010100000000 ,
b0 -
b1000 .
b11 /
#360000
b100100 !
b1100000110 "
b110110 #
b100100 $
b110110 '
b1100000110 (
b100100 )
b1100000110 *
b110110 +
b11011000000000 ,
b0 -
b1000 .
b11 /
#370000
b100101 !
b1100000111 "
b110111 #
b100101 $
b110111 '
b1100000111 (
b100101 )
b1100000111 *
b110111 +
b11011100000000 ,
b0 -
b1000 .
b11 /
#380000
b100110 !
b1100001000 "
b111000 #
b100110 $
b111000 '
b1100001000 (
b100110 )
b1100001000 *
b111000 +
b11100000000000 ,
b0 -
b1000 .
b11 /
#390000
b100111 !
b1100001001 "
b111001 #
b100111 $
b111001 '
b1100001001 (
b100111 )
b1100001001 *
b111001 +
b11100100000000 ,
b0 -
b1000 .
b11 /
#400000
b101000 !
b10000000000 "
b1000000 #
b101000 $
b1000000 '
b10000000000 (
b101000 )
b10000000000 *
b1000000 +
b100000000000000 ,
b0 -
b1000 .
b11 /
#410000
b101001 !
b10000000001 "
b1000001 #
b101001 $
b1000001 '
b10000000001 (
b101001 )
b10000000001 *
b1000001 +
b100000100000000 ,
b0 -
b1000 .
b11 /
#420000
b101010 !
b10000000010 "
b1000010 #
b101010 $
b1000010 '
b10000000010 (
b101010 )
b10000000010 *
b1000010 +
b100001000000000 ,
b0 -
b1000 .
b11 /
#430000
b101011 !
b10000000011 "
b1000011 #
b101011 $
b1000011 '
b10000000011 (
b101011 )
b10000000011 *
b1000011 +
b100001100000000 ,
b0 -
b1000 .
b11 /
#440000
b101100 !
b10000000100 "
b1000100 #
b101100 $
b1000100 '
b10000000100 (
b101100 )
b10000000100 *
b1000100 +
b100010000000000 ,
b0 -
b1000 .
b11 /
#450000
b101101 !
b10000000101 "
b1000101 #
b101101 $
b1000101 '
b10000000101 (
b101101 )
b10000000101 *
b1000101 +
b100010100000000 ,
b0 -
b1000 .
b11 /
#460000
b101110 !
b10000000110 "
b1000110 #
b101110 $
b1000110 '
b10000000110 (
b101110 )
b10000000110 *
b1000110 +
b100011000000000 ,
b0 -
b1000 .
b11 /
#470000
b101111 !
b10000000111 "
b1000111 #
b101111 $
b1000111 '
b10000000111 (
b101111 )
b10000000111 *
b1000111 +
b100011100000000 ,
b0 -
b1000 .
b11 /
#480000
b110000 !
b10000001000 "
b1001000 #
b110000 $
b1001000 '
b10000001000 (
b110000 )
b10000001000 *
b1001000 +
b100100000000000 ,
b0 -
b1000 .
b11 /
#490000
b110001 !
b10000001001 "
b1001001 #
b110001 $
b1001001 '
b10000001001 (
b110001 )
b10000001001 *
b1001001 +
b100100100000000 ,
b0 -
b1000 .
b11 /
#500000
b110010 !
b10100000000 "
b1010000 #
b110010 $
b1010000 '
b10100000000 (
b110010 )
b10100000000 *
b1010000 +
b101000000000000 ,
b0 -
b1000 .
b11 /
#510000
b110011 !
b10100000001 "
b1010001 #
b110011 $
b1010001 '
b10100000001 (
b110011 )
b10100000001 *
b1010001 +
b101000100000000 ,
b0 -
b1000 .
b11 /
#520000
b110100 !
b10100000010 "
b1010010 #
b110100 $
b1010010 '
b10100000010 (
b110100 )
b10100000010 *
b1010010 +
b101001000000000 ,
b0 -
b1000 .
b11 /
#530000
b110101 !
b10100000011 "
b1010011 #
b110101 $
b1010011 '
b10100000011 (
b110101 )
b10100000011 *
b1010011 +
b101001100000000 ,
b0 -
b1000 .
b11 /
#540000
b110110 !
b10100000100 "
b1010100 #
b110110 $
b1010100 '
b10100000100 (
b110110 )
b10100000100 *
b1010100 +
b101010000000000 ,
b0 -
b1000 .
b11 /
#550000
b110111 !
b10100000101 "
b1010101 #
b110111 $
b1010101 '
b10100000101 (
b110111 )
b10100000101 *
b1010101 +
b101010100000000 ,
b0 -
b1000 .
b11 /
#560000
b111000 !
b10100000110 "
b1010110 #
b111000 $
b1010110 '
b10100000110 (
b111000 )
b10100000110 *
b1010110 +
b101011000000000 ,
b0 -
b1000 .
b11 /
#570000
b111001 !
b10100000111 "
b1010111 #
b111001 $
b1010111 '
b10100000111 (
b111001 )
b10100000111 *
b1010111 +
b101011100000000 ,
b0 -
b1000 .
b11 /
#580000
b111010 !
b10100001000 "
b1011000 #
b111010 $
b1011000 '
b10100001000 (
b111010 )
b10100001000 *
b1011000 +
b101100000000000 ,
b0 -
b1000 .
b11 /
#590000
b111011 !
b10100001001 "
b1011001 #
b111011 $
b1011001 '
b10100001001 (
b111011 )
b10100001001 *
b1011001 +
b101100100000000 ,
b0 -
b1000 .
b11 /
#600000
b111100 !
b11000000000 "
b1100000 #
b111100 $
b1100000 '
b11000000000 (
b111100 )
b11000000000 *
b1100000 +
b110000000000000 ,
b0 -
b1000 .
b11 /
#610000
b111101 !
b11000000001 "
b1100001 #
b111101 $
b1100001 '
b11000000001 (
b111101 )
b11000000001 *
b1100001 +
b110000100000000 ,
b0 -
b1000 .
b11 /
#620000
b111110 !
b11000000010 "
b1100010 #
b111110 $
b1100010 '
b11000000010 (
b111110 )
b11000000010 *
b1100010 +
b110001000000000 ,
b0 -
b1000 .
b11 /
#630000
b111111 !
b11000000011 "
b1100011 #
b111111 $
b1100011 '
b11000000011 (
b111111 )
b11000000011 *
b1100011 +
b110001100000000 ,
b0 -
b1000 .
b11 /
#640000
b1000000 !
b11000000100 "
b1100100 #
b1000000 $
b1100100 '
b11000000100 (
b1000000 )
b11000000100 *
b1100100 +
b110010000000000 ,
b0 -
b1000 .
b11 /
#650000
b1000001 !
b11000000101 "
b1100101 #
b1000001 $
b1100101 '
b11000000101 (
b1000001 )
b11000000101 *
b1100101 +
b110010100000000 ,
b0 -
b1000 .
b11 /
#660000
b1000010 !
b11000000110 "
b1100110 #
b1000010 $
b1100110 '
b11000000110 (
b1000010 )
b11000000110 *
b1100110 +
b110011000000000 ,
b0 -
b1000 .
b11 /
#670000
b1000011 !
b11000000111 "
b1100111 #
b1000011 $
b1100111 '
b11000000111 (
b1000011 )
b11000000111 *
b1100111 +
b110011100000000 ,
b0 -
b1000 .
b11 /
#680000
b1000100 !
b11000001000 "
b1101000 #
b1000100 $
b1101000 '
b11000001000 (
b1000100 )
b11000001000 *
b1101000 +
b110100000000000 ,
b0 -
b1000 .
b11 /
#690000
b1000101 !
b11000001001 "
b1101001 #
b1000101 $
b1101001 '
b11000001001 (
b1000101 )
b11000001001 *
b1101001 +
b110100100000000 ,
b0 -
b1000 .
b11 /
#700000
b1000110 !
b11100000000 "
b1110000 #
b1000110 $
b1110000 '
b11100000000 (
b1000110 )
b11100000000 *
b1110000 +
b111000000000000 ,
b0 -
b1000 .
b11 /
#710000
b1000111 !
b11100000001 "
b1110001 #
b1000111 $
b1110001 '
b11100000001 (
b1000111 )
b11100000001 *
b1110001 +
b111000100000000 ,
b0 -
b1000 .
b11 /
#720000
b1001000 !
b11100000010 "
b1110010 #
b1001000 $
b1110010 '
b11100000010 (
b1001000 )
b11100000010 *
b1110010 +
b111001000000000 ,
b0 -
b1000 .
b11 /
#730000
b1001001 !
b11100000011 "
b1110011 #
b1001001 $
b1110011 '
b11100000011 (
b1001001 )
b11100000011 *
b1110011 +
b111001100000000 ,
b0 -
b1000 .
b11 /
#740000
b1001010 !
b11100000100 "
b1110100 #
b1001010 $
b1110100 '
b11100000100 (
b1001010 )
b11100000100 *
b1110100 +
b111010000000000 ,
b0 -
b1000 .
b11 /
#750000
b1001011 !
b11100000101 "
b1110101 #
b1001011 $
b1110101 '
b11100000101 (
b1001011 )
b11100000101 *
b1110101 +
b111010100000000 ,
b0 -
b1000 .
b11 /
#760000
b1001100 !
b11100000110 "
b1110110 #
b1001100 $
b1110110 '
b11100000110 (
b1001100 )
b11100000110 *
b1110110 +
b111011000000000 ,
b0 -
b1000 .
b11 /
#770000
b1001101 !
b11100000111 "
b1110111 #
b1001101 $
b1110111 '
b11100000111 (
b1001101 )
b11100000111 *
b1110111 +
b111011100000000 ,
b0 -
b1000 .
b11 /
#780000
b1001110 !
b11100001000 "
b1111000 #
b1001110 $
b1111000 '
b11100001000 (
b1001110 )
b11100001000 *
b1111000 +
b111100000000000 ,
b0 -
b1000 .
b11 /
#790000
b1001111 !
b11100001001 "
b1111001 #
b1001111 $
b1111001 '
b11100001001 (
b1001111 )
b11100001001 *
b1111001 +
b111100100000000 ,
b0 -
b1000 .
b11 /
#800000
b1010000 !
b100000000000 "
b10000000 #
b1010000 $
b10000000 '
b100000000000 (
b1010000 )
b100000000000 *
b10000000 +
b1000000000000000 ,
b0 -
b1000 .
b11 /
#810000
b1010001 !
b100000000001 "
b10000001 #
b1010001 $
b10000001 '
b100000000001 (
b1010001 )
b100000000001 *
b10000001 +
b1000000100000000 ,
b0 -
b1000 .
b11 /
#820000
b1010010 !
b100000000010 "
b10000010 #
b1010010 $
b10000010 '
b100000000010 (
b1010010 )
b100000000010 *
b10000010 +
b1000001000000000 ,
b0 -
b1000 .
b11 /
#830000
b1010011 !
b100000000011 "
b10000011 #
b1010011 $
b10000011 '
b100000000011 (
b1010011 )
b100000000011 *
b10000011 +
b1000001100000000 ,
b0 -
b1000 .
b11 /
#840000
b1010100 !
b100000000100 "
b10000100 #
b1010100 $
b10000100 '
b100000000100 (
b1010100 )
b100000000100 *
b10000100 +
b1000010000000000 ,
b0 -
b1000 .
b11 /
#850000
b1010101 !
b100000000101 "
b10000101 #
b1010101 $
b10000101 '
b100000000101 (
b1010101 )
b100000000101 *
b10000101 +
b1000010100000000 ,
b0 -
b1000 .
b11 /
#860000
b1010110 !
b100000000110 "
b10000110 #
b1010110 $
b10000110 '
b100000000110 (
b1010110 )
b100000000110 *
b10000110 +
b1000011000000000 ,
b0 -
b1000 .
b11 /
#870000
b1010111 !
b100000000111 "
b10000111 #
b1010111 $
b10000111 '
b100000000111 (
b1010111 )
b100000000111 *
b10000111 +
b1000011100000000 ,
b0 -
b1000 .
b11 /
#880000
b1011000 !
b100000001000 "
b10001000 #
b1011000 $
b10001000 '
b100000001000 (
b1011000 )
b100000001000 *
b10001000 +
b1000100000000000 ,
b0 -
b1000 .
b11 /
#890000
b1011001 !
b100000001001 "
b10001001 #
b1011001 $
b10001001 '
b100000001001 (
b1011001 )
b100000001001 *
b10001001 +
b1000100100000000 ,
b0 -
b1000 .
b11 /
#900000
b1011010 !
b100100000000 "
b10010000 #
b1011010 $
b10010000 '
b100100000000 (
b1011010 )
b100100000000 *
b10010000 +
b1001000000000000 ,
b0 -
b1000 .
b11 /
#910000
b1011011 !
b100100000001 "
b10010001 #
b1011011 $
b10010001 '
b100100000001 (
b1011011 )
b100100000001 *
b10010001 +
b1001000100000000 ,
b0 -
b1000 .
b11 /
#920000
b1011100 !
b100100000010 "
b10010010 #
b1011100 $
b10010010 '
b100100000010 (
b1011100 )
b100100000010 *
b10010010 +
b1001001000000000 ,
b0 -
b1000 .
b11 /
#930000
b1011101 !
b100100000011 "
b10010011 #
b1011101 $
b10010011 '
b100100000011 (
b1011101 )
b100100000011 *
b10010011 +
b1001001100000000 ,
b0 -
b1000 .
b11 /
#940000
b1011110 !
b100100000100 "
b10010100 #
b1011110 $
b10010100 '
b100100000100 (
b1011110 )
b100100000100 *
b10010100 +
b1001010000000000 ,
b0 -
b1000 .
b11 /
#950000
b1011111 !
b100100000101 "
b10010101 #
b1011111 $
b10010101 '
b100100000101 (
b1011111 )
b100100000101 *
b10010101 +
b1001010100000000 ,
b0 -
b1000 .
b11 /
#960000
b1100000 !
b100100000110 "
b10010110 #
b1100000 $
b10010110 '
b100100000110 (
b1100000 )
b100100000110 *
b10010110 +
b1001011000000000 ,
b0 -
b1000 .
b11 /
#970000
b1100001 !
b100100000111 "
b10010111 #
b1100001 $
b10010111 '
b100100000111 (
b1100001 )
b100100000111 *
b10010111 +
b1001011100000000 ,
b0 -
b1000 .
b11 /
#980000
b1100010 !
b100100001000 "
b10011000 #
b1100010 $
b10011000 '
b100100001000 (
b1100010 )
b100100001000 *
b10011000 +
b1001100000000000 ,
b0 -
b1000 .
b11 /
#990000
b1100011 !
b100100001001 "
b10011001 #
b1100011 $
b10011001 '
b100100001001 (
b1100011 )
b100100001001 *
b10011001 +
b1001100100000000 ,
b0 -
b1000 .
b11 /
#1000000
b1100100 !
b10000000000000000 "
b100000000 #
b1100100 $
b100000000 '
b10000000000000000 (
b1100100 )
b10000000000000000 *
b100000000 +
b10000000000000000 ,
b0 -
b1000 .
b11 /
#1010000
b1100101 !
b10000000000000001 "
b100000001 #
b1100101 $
b100000001 '
b10000000000000001 (
b1100101 )
b10000000000000001 *
b100000001 +
b10000000100000000 ,
b0 -
b1000 .
b11 /
#1020000
b1100110 !
b10000000000000010 "
b100000010 #
b1100110 $
b100000010 '
b10000000000000010 (
b1100110 )
b10000000000000010 *
b100000010 +
b10000001000000000 ,
b0 -
b1000 .
b11 /
#1030000
b1100111 !
b10000000000000011 "
b100000011 #
b1100111 $
b100000011 '
b10000000000000011 (
b1100111 )
b10000000000000011 *
b100000011 +
b10000001100000000 ,
b0 -
b1000 .
b11 /
#1040000
b1101000 !
b10000000000000100 "
b100000100 #
b1101000 $
b100000100 '
b10000000000000100 (
b1101000 )
b10000000000000100 *
b100000100 +
b10000010000000000 ,
b0 -
b1000 .
b11 /
#1050000
b1101001 !
b10000000000000101 "
b100000101 #
b1101001 $
b100000101 '
b10000000000000101 (
b1101001 )
b10000000000000101 *
b100000101 +
b10000010100000000 ,
b0 -
b1000 .
b11 /
#1060000
b1101010 !
b10000000000000110 "
b100000110 #
b1101010 $
b100000110 '
b10000000000000110 (
b1101010 )
b10000000000000110 *
b100000110 +
b10000011000000000 ,
b0 -
b1000 .
b11 /
#1070000
b1101011 !
b10000000000000111 "
b100000111 #
b1101011 $
b100000111 '
b10000000000000111 (
b1101011 )
b10000000000000111 *
b100000111 +
b10000011100000000 ,
b0 -
b1000 .
b11 /
#1080000
b1101100 !
b10000000000001000 "
b100001000 #
b1101100 $
b100001000 '
b10000000000001000 (
b1101100 )
b10000000000001000 *
b100001000 +
b10000100000000000 ,
b0 -
b1000 .
b11 /
#1090000
b1101101 !
b10000000000001001 "
b100001001 #
b1101101 $
b100001001 '
b10000000000001001 (
b1101101 )
b10000000000001001 *
b100001001 +
b10000100100000000 ,
b0 -
b1000 .
b11 /
#1100000
b1101110 !
b10000000100000000 "
b100010000 #
b1101110 $
b100010000 '
b10000000100000000 (
b1101110 )
b10000000100000000 *
b100010000 +
b10001000000000000 ,
b0 -
b1000 .
b11 /
#1110000
b1101111 !
b10000000100000001 "
b100010001 #
b1101111 $
b100010001 '
b10000000100000001 (
b1101111 )
b10000000100000001 *
b100010001 +
b10001000100000000 ,
b0 -
b1000 .
b11 /
#1120000
b1110000 !
b10000000100000010 "
b100010010 #
b1110000 $
b100010010 '
b10000000100000010 (
b1110000 )
b10000000100000010 *
b100010010 +
b10001001000000000 ,
b0 -
b1000 .
b11 /
#1130000
b1110001 !
b10000000100000011 "
b100010011 #
b1110001 $
b100010011 '
b10000000100000011 (
b1110001 )
b10000000100000011 *
b100010011 +
b10001001100000000 ,
b0 -
b1000 .
b11 /
#1140000
b1110010 !
b10000000100000100 "
b100010100 #
b1110010 $
b100010100 '
b10000000100000100 (
b1110010 )
b10000000100000100 *
b100010100 +
b10001010000000000 ,
b0 -
b1000 .
b11 /
#1150000
b1110011 !
b10000000100000101 "
b100010101 #
b1110011 $
b100010101 '
b10000000100000101 (
b1110011 )
b10000000100000101 *
b100010101 +
b10001010100000000 ,
b0 -
b1000 .
b11 /
#1160000
b1110100 !
b10000000100000110 "
b100010110 #
b1110100 $
b100010110 '
b10000000100000110 (
b1110100 )
b10000000100000110 *
b100010110 +
b10001011000000000 ,
b0 -
b1000 .
b11 /
#1170000
b1110101 !
b10000000100000111 "
b100010111 #
b1110101 $
b100010111 '
b10000000100000111 (
b1110101 )
b10000000100000111 *
b100010111 +
b10001011100000000 ,
b0 -
b1000 .
b11 /
#1180000
b1110110 !
b10000000100001000 "
b100011000 #
b1110110 $
b100011000 '
b10000000100001000 (
b1110110 )
b10000000100001000 *
b100011000 +
b10001100000000000 ,
b0 -
b1000 .
b11 /
#1190000
b1110111 !
b10000000100001001 "
b100011001 #
b1110111 $
b100011001 '
b10000000100001001 (
b1110111 )
b10000000100001001 *
b100011001 +
b10001100100000000 ,
b0 -
b1000 .
b11 /
#1200000
b1111000 !
b10000001000000000 "
b100100000 #
b1111000 $
b100100000 '
b10000001000000000 (
b1111000 )
b10000001000000000 *
b100100000 +
b10010000000000000 ,
b0 -
b1000 .
b11 /
#1210000
b1111001 !
b10000001000000001 "
b100100001 #
b1111001 $
b100100001 '
b10000001000000001 (
b1111001 )
b10000001000000001 *
b100100001 +
b10010000100000000 ,
b0 -
b1000 .
b11 /
#1220000
b1111010 !
b10000001000000010 "
b100100010 #
b1111010 $
b100100010 '
b10000001000000010 (
b1111010 )
b10000001000000010 *
b100100010 +
b10010001000000000 ,
b0 -
b1000 .
b11 /
#1230000
b1111011 !
b10000001000000011 "
b100100011 #
b1111011 $
b100100011 '
b10000001000000011 (
b1111011 )
b10000001000000011 *
b100100011 +
b10010001100000000 ,
b0 -
b1000 .
b11 /
#1240000
b1111100 !
b10000001000000100 "
b100100100 #
b1111100 $
b100100100 '
b10000001000000100 (
b1111100 )
b10000001000000100 *
b100100100 +
b10010010000000000 ,
b0 -
b1000 .
b11 /
#1250000
b1111101 !
b10000001000000101 "
b100100101 #
b1111101 $
b100100101 '
b10000001000000101 (
b1111101 )
b10000001000000101 *
b100100101 +
b10010010100000000 ,
b0 -
b1000 .
b11 /
#1260000
b1111110 !
b10000001000000110 "
b100100110 #
b1111110 $
b100100110 '
b10000001000000110 (
b1111110 )
b10000001000000110 *
b100100110 +
b10010011000000000 ,
b0 -
b1000 .
b11 /
#1270000
b1111111 !
b10000001000000111 "
b100100111 #
b1111111 $
b100100111 '
b10000001000000111 (
b1111111 )
b10000001000000111 *
b100100111 +
b10010011100000000 ,
b0 -
b1000 .
b11 /
#1280000
b10000000 !
b10000001000001000 "
b100101000 #
b10000000 $
b100101000 '
b10000001000001000 (
b10000000 )
b10000001000001000 *
b100101000 +
b10010100000000000 ,
b0 -
b1000 .
b11 /
#1290000
b10000001 !
b10000001000001001 "
b100101001 #
b10000001 $
b100101001 '
b10000001000001001 (
b10000001 )
b10000001000001001 *
b100101001 +
b10010100100000000 ,
b0 -
b1000 .
b11 /
#1300000
b10000010 !
b10000001100000000 "
b100110000 #
b10000010 $
b100110000 '
b10000001100000000 (
b10000010 )
b10000001100000000 *
b100110000 +
b10011000000000000 ,
b0 -
b1000 .
b11 /
#1310000
b10000011 !
b10000001100000001 "
b100110001 #
b10000011 $
b100110001 '
b10000001100000001 (
b10000011 )
b10000001100000001 *
b100110001 +
b10011000100000000 ,
b0 -
b1000 .
b11 /
#1320000
b10000100 !
b10000001100000010 "
b100110010 #
b10000100 $
b100110010 '
b10000001100000010 (
b10000100 )
b10000001100000010 *
b100110010 +
b10011001000000000 ,
b0 -
b1000 .
b11 /
#1330000
b10000101 !
b10000001100000011 "
b100110011 #
b10000101 $
b100110011 '
b10000001100000011 (
b10000101 )
b10000001100000011 *
b100110011 +
b10011001100000000 ,
b0 -
b1000 .
b11 /
#1340000
b10000110 !
b10000001100000100 "
b100110100 #
b10000110 $
b100110100 '
b10000001100000100 (
b10000110 )
b10000001100000100 *
b100110100 +
b10011010000000000 ,
b0 -
b1000 .
b11 /
