uart_receiver/baud_rate/hdl/baud_rate_generator.v
module baud_rate_generator (
  input wire clk,
  input wire rst_n,
  output reg baud_rate_signal,
  output reg [13:0] counter
);

  parameter BAUD_RATE_NUMBER = 10416;
  //reg [13:0] counter;
  /*
  always @(posedge clk or negedge rst_n) begin
    if (!rst_n) begin
      counter <= BAUD_RATE_NUMBER - 1;
      baud_rate_signal <= 1'b0;
    end else begin
      if (counter == 1) begin
        counter <= counter - 1;
        baud_rate_signal <= 1;
      end else if (counter == 0) begin
        counter <= BAUD_RATE_NUMBER - 1;
        baud_rate_signal <= 0;
      end else begin  
        counter <= counter - 1;
        baud_rate_signal <= 0;
      end
    end
  end
  */
  always @(posedge clk or negedge rst_n) begin
    if (!rst_n) begin
      counter <= BAUD_RATE_NUMBER - 1;
      baud_rate_signal <= 1'b0;
    end else begin
      case (counter)
        1'b1: begin
          counter <= counter - 1;
          baud_rate_signal <= 0;
        end
        1'b0: begin
          counter <= BAUD_RATE_NUMBER - 1;
          baud_rate_signal <= 1;
        end
        default begin
          counter <= counter - 1;
          baud_rate_signal <= 0;
        end
      endcase 
    end
  end

endmodule

uart_receiver/baud_rate/xsim/baud_rate_generator_tb.v
// set the timescale for the simulation
 `timescale 1ns/1ps 
module testbench;  // module of testbench
//  parameter defined
parameter CYCLE = 10; // use CYCLE to describe the clock period
parameter LARGE_NUMBER  = 10500;// max cycle time=>timeout

// localparam
localparam N = 10417; //BAUD_RATE_NUMBER


// input signal use reg
reg clk;
reg rst_n;

// output signal use wire
wire baud_rate_out;
wire [13:0] counter;
// interger 
integer i, j, error;
///// instantiate  module /////
// instantiate the module you finished in following format //
// module_name #(.parameter1(5),.parameter2(3)) unit_name (.port1(...), .port2(...), ...); //
baud_rate_generator baud_rate_generator(
  .clk(clk),
  .rst_n(rst_n),
  .baud_rate_signal(baud_rate_out),
  .counter(counter)
);

//  dump the waveform of the simulation for fsdb//
/*initial begin
 $fsdbDumpfile("testbench.fsdb"); 
 $fsdbDumpvars;              
end*/

// dump the waveform of the simulation for vcd//
initial begin
  $dumpfile("testbench.vcd");
  $dumpvars("+mda");
end

// generate clk 
always #(CYCLE/2) clk = ~clk; 

// System block set only clock,reset signal and the timeout finish. 
initial begin
  clk = 1;
  rst_n = 1;
  // system reset
  #(CYCLE) rst_n = 0;
  #(CYCLE) rst_n = 1;

  #(CYCLE*LARGE_NUMBER) $finish;
end


// output result checking block, control when to sample and verify the result.
integer  fp_w;
initial begin
// error count
  error = 0;
// Use the same control technique to control when to sample output result.
  wait(rst_n==0);
// adder output for two cycle from input to output
  // you can also write the result to a text file
  fp_w = $fopen("answer.txt");
  for (j = 0; j < N; j = j + 1) begin
    @(posedge clk);
    if (j != 10416) begin
      if (baud_rate_out != 0) begin
        error = error + 1;
        $display("************* Pattern No.%d is wrong at %t ************", j,$time);
        $display("Output = 0, but your answer is %b ", baud_rate_out);  
      end
      $fdisplay(fp_w, "0_%b %d", baud_rate_out, counter);
    end else begin
      if (baud_rate_out != 1) begin
        error = error + 1;
        $display("************* Pattern No.%d is wrong at %t ************", j,$time);
        $display("Output = 1, but your answer is %b ", baud_rate_out);  
      end
      $fdisplay(fp_w, "1_%b %d", baud_rate_out, counter);
    end
  end
  $fclose(fp_w); 
  // check the error count
  if(error==0) begin
    $display("Congratulations!! The functionality of your adder is correct!!");
  end else begin
    $display("error !!");
  end 
  #(CYCLE) $finish;
end

endmodule

uart_receiver/baud_rate/xsim/testbench.vcd
$date
   Tue Jan  7 21:41:15 2025
$end
$version
  2022.1
$end
$timescale
  1ps
$end
$scope module testbench $end
$var reg 1 ! clk $end
$var reg 1 " rst_n $end
$var wire 1 # baud_rate_out $end
$var wire 14 $ counter [13:0] $end
$var integer 32 % i [31:0] $end
$var integer 32 & j [31:0] $end
$var integer 32 ' error [31:0] $end
$var integer 32 ( fp_w [31:0] $end
$scope module baud_rate_generator $end
$var wire 1 ) clk $end
$var wire 1 * rst_n $end
$var reg 1 + baud_rate_signal $end
$var reg 14 , counter [13:0] $end
$upscope $end
$upscope $end
$enddefinitions $end
#0
$dumpvars
1!
1"
0#
bx $
bx %
bx &
b0 '
bx (
1)
1*
0+
bx ,
$end
#5000
0!
0)
#10000
1!
0"
b10100010101111 $
b0 &
b10 (
1)
0*
0+
b10100010101111 ,
#15000
0!
0)
#20000
1!
1"
b10100010101110 $
b1 &
1)
1*
0+
b10100010101110 ,
#25000
0!
0)
#30000
1!
b10100010101101 $
b10 &
1)
0+
b10100010101101 ,
#35000
0!
0)
#40000
1!
b10100010101100 $
b11 &
1)
0+
b10100010101100 ,
#45000
0!
0)
#50000
1!
b10100010101011 $
b100 &
1)
0+
b10100010101011 ,
#55000
0!
0)
#60000
1!
b10100010101010 $
b101 &
1)
0+
b10100010101010 ,
#65000
0!
0)
#70000
1!
b10100010101001 $
b110 &
1)
0+
b10100010101001 ,
#75000
0!
0)
#80000
1!
b10100010101000 $
b111 &
1)
0+
b10100010101000 ,
#85000
0!
0)
#90000
1!
b10100010100111 $
b1000 &
1)
0+
b10100010100111 ,
#95000
0!
0)
#100000
1!
b10100010100110 $
b1001 &
1)
0+
b10100010100110 ,
#105000
0!
0)
#110000
1!
b10100010100101 $
b1010 &
1)
0+
b10100010100101 ,
#115000
0!
0)
#120000
1!
b10100010100100 $
b1011 &
1)
0+
b10100010100100 ,
#125000
0!
0)
#130000
1!
b10100010100011 $
b1100 &
1)
0+
b10100010100011 ,
#135000
0!
0)
#140000
1!
b10100010100010 $
b1101 &
1)
0+
b10100010100010 ,
#145000
0!
0)
#150000
1!
b10100010100001 $
b1110 &
1)
0+
b10100010100001 ,
#155000
0!
0)
#160000
1!
b10100010100000 $
b1111 &
1)
0+
b10100010100000 ,
#165000
0!
0)
#170000
1!
b10100010011111 $
b10000 &
1)
0+
b10100010011111 ,
#175000
0!
0)
#180000
1!
b10100010011110 $
b10001 &
1)
0+
b10100010011110 ,
#185000
0!
0)
#190000
1!
b10100010011101 $
b10010 &
1)
0+
b10100010011101 ,
#195000
0!
0)
#200000
1!
b10100010011100 $
b10011 &
1)
0+
b10100010011100 ,
#205000
0!
0)
#210000
1!
b10100010011011 $
b10100 &
1)
0+
b10100010011011 ,
#215000
0!
0)
#220000
1!
b10100010011010 $
b10101 &
1)
0+
b10100010011010 ,
#225000
0!
0)
#230000
1!
b10100010011001 $
b10110 &
1)
0+
b10100010011001 ,
#235000
0!
0)
#240000
1!
b10100010011000 $
b10111 &
1)
0+
b10100010011000 ,
#245000
0!
0)
#250000
1!
b10100010010111 $
b11000 &
1)
0+
b10100010010111 ,
#255000
0!
0)
#260000
1!
b10100010010110 $
b11001 &
1)
0+
b10100010010110 ,
#265000
0!
0)
#270000
1!
b10100010010101 $
b11010 &
1)
0+
b10100010010101 ,
#275000
0!
0)
#280000
1!
b10100010010100 $
b11011 &
1)
0+
b10100010010100 ,
#285000
0!
0)
#290000
1!
b10100010010011 $
b11100 &
1)
0+
b10100010010011 ,
#295000
0!
0)
#300000
1!
b10100010010010 $
b11101 &
1)
0+
b10100010010010 ,
#305000
0!
0)
#310000
1!
b10100010010001 $
b11110 &
1)
0+
b10100010010001 ,
#315000
0!
0)
#320000
1!
b10100010010000 $
b11111 &
1)
0+
b10100010010000 ,
#325000
0!
0)
#330000
1!
b10100010001111 $
b100000 &
1)
0+
b10100010001111 ,
#335000
0!
0)
#340000
1!
b10100010001110 $
b100001 &
1)
0+
b10100010001110 ,
#345000
0!
0)
#350000
1!
b10100010001101 $
b100010 &
1)
0+
b10100010001101 ,
#355000
0!
0)
#360000
1!
b10100010001100 $
b100011 &
1)
0+
b10100010001100 ,
#365000
0!
0)
#370000
1!
b10100010001011 $
b100100 &
1)
0+
b10100010001011 ,
#375000
0!
0)
#380000
1!
b10100010001010 $
b100101 &
1)
0+
b10100010001010 ,
#385000
0!
0)
#390000
1!
b10100010001001 $
b100110 &
1)
0+
b10100010001001 ,
#395000
0!
0)
#400000
1!
b10100010001000 $
b100111 &
1)
0+
b10100010001000 ,
#405000
0!
0)
#410000
1!
b10100010000111 $
b101000 &
1)
0+
b10100010000111 ,
#415000
0!
0)
#420000
1!
b10100010000110 $
b101001 &
1)
0+
b10100010000110 ,
#425000
0!
0)
#430000
1!
b10100010000101 $
b101010 &
1)
0+
b10100010000101 ,
#435000
0!
0)
#440000
1!
b10100010000100 $
b101011 &
1)
0+
b10100010000100 ,
#445000
0!
0)
#450000
1!
b10100010000011 $
b101100 &
1)
0+
b10100010000011 ,
#455000
0!
0)
#460000
1!
b10100010000010 $
b101101 &
1)
0+
b10100010000010 ,
#465000
0!
0)
#470000
1!
b10100010000001 $
b101110 &
1)
0+
b10100010000001 ,
#475000
0!
0)
#480000
1!
b10100010000000 $
b101111 &
1)
0+
b10100010000000 ,
#485000
0!
0)
#490000
1!
b10100001111111 $
b110000 &
1)
0+
b10100001111111 ,
#495000
0!
0)
#500000
1!
b10100001111110 $
b110001 &
1)
0+
b10100001111110 ,
#505000
0!
0)
#510000
1!
b10100001111101 $
b110010 &
1)
0+
b10100001111101 ,
#515000
0!
0)
#520000
1!
b10100001111100 $
b110011 &
1)
0+
b10100001111100 ,
#525000
0!
0)
#530000
1!
b10100001111011 $
b110100 &
1)
0+
b10100001111011 ,
#535000
0!
0)
#540000
1!
b10100001111010 $
b110101 &
1)
0+
b10100001111010 ,
#545000
0!
0)
#550000
1!
b10100001111001 $
b110110 &
1)
0+
b10100001111001 ,
#555000
0!
0)
#560000
1!
b10100001111000 $
b110111 &
1)
0+
b10100001111000 ,
#565000
0!
0)
#570000
1!
b10100001110111 $
b111000 &
1)
0+
b10100001110111 ,
#575000
0!
0)
#580000
1!
b10100001110110 $
b111001 &
1)
0+
b10100001110110 ,
#585000
0!
0)
#590000
1!
b10100001110101 $
b111010 &
1)
0+
b10100001110101 ,
#595000
0!
0)
#600000
1!
b10100001110100 $
b111011 &
1)
0+
b10100001110100 ,
#605000
0!
0)
#610000
1!
b10100001110011 $
b111100 &
1)
0+
b10100001110011 ,
#615000
0!
0)
#620000
1!
b10100001110010 $
b111101 &
1)
0+
b10100001110010 ,
#625000
0!
0)
#630000
1!
b10100001110001 $
b111110 &
1)
0+
b10100001110001 ,
#635000
0!
0)
#640000
1!
b10100001110000 $
b111111 &
1)
0+
b10100001110000 ,
#645000
0!
0)
#650000
1!
b10100001101111 $
b1000000 &
1)
0+
b10100001101111 ,
#655000
0!
0)
#660000
1!
b10100001101110 $
b1000001 &
1)
0+
b10100001101110 ,
#665000
0!
0)
#670000
1!
b10100001101101 $
b1000010 &
1)
0+
b10100001101101 ,
#675000
0!
0)
#680000
1!
b10100001101100 $
b1000011 &
1)
0+
b10100001101100 ,
#685000
0!
0)
#690000
1!
b10100001101011 $
b1000100 &
1)
0+
b10100001101011 ,
#695000
0!
0)
#700000
1!
b10100001101010 $
b1000101 &
1)
0+
b10100001101010 ,
#705000
0!
0)
#710000
1!
b10100001101001 $
b1000110 &
1)
0+
b10100001101001 ,
#715000
0!
0)
#720000
1!
b10100001101000 $
b1000111 &
1)
0+
b10100001101000 ,
#725000
0!
0)
#730000
1!
b10100001100111 $
b1001000 &
1)
0+
b10100001100111 ,
#735000
0!
0)
#740000
1!
b10100001100110 $
b1001001 &
1)
0+
b10100001100110 ,
#745000
0!
0)
#750000
1!
b10100001100101 $
b1001010 &
1)
0+
b10100001100101 ,
#755000
0!
0)
#760000
1!
b10100001100100 $
b1001011 &
1)
0+
b10100001100100 ,
#765000
0!
0)
#770000
1!
b10100001100011 $
b1001100 &
1)
0+
b10100001100011 ,
#775000
0!
0)
#780000
1!
b10100001100010 $
b1001101 &
1)
0+
b10100001100010 ,
#785000
0!
0)
#790000
1!
b10100001100001 $
b1001110 &
1)
0+
b10100001100001 ,
#795000
0!
0)
#800000
1!
b10100001100000 $
b1001111 &
1)
0+
b10100001100000 ,
#805000
0!
0)
#810000
1!
b10100001011111 $
b1010000 &
1)
0+
b10100001011111 ,
#815000
0!
0)
#820000
1!
b10100001011110 $
b1010001 &
1)
0+
b10100001011110 ,
#825000
0!
0)
#830000
1!
b10100001011101 $
b1010010 &
1)
0+
b10100001011101 ,
#835000
0!
0)
#840000
1!
b10100001011100 $
b1010011 &
1)
0+
b10100001011100 ,
#845000
0!
0)
#850000
1!
b10100001011011 $
b1010100 &
1)
0+
b10100001011011 ,
#855000
0!
0)
#860000
1!
b10100001011010 $
b1010101 &
1)
0+
b10100001011010 ,
#865000
0!
0)
#870000
1!
b10100001011001 $
b1010110 &
1)
0+
b10100001011001 ,
#875000
0!
0)
#880000
1!
b10100001011000 $
b1010111 &
1)
0+
b10100001011000 ,
#885000
0!
0)
#890000
1!
b10100001010111 $
b1011000 &
1)
0+
b10100001010111 ,
#895000
0!
0)
#900000
1!
b10100001010110 $
b1011001 &
1)
0+
b10100001010110 ,
#905000
0!
0)
#910000
1!
b10100001010101 $
b1011010 &
1)
0+
b10100001010101 ,
#915000
0!
0)
#920000
1!
b10100001010100 $
b1011011 &
1)
0+
b10100001010100 ,
#925000
0!
0)
#930000
1!
b10100001010011 $
b1011100 &
1)
0+
b10100001010011 ,
#935000
0!
0)
#940000
1!
b10100001010010 $
b1011101 &
1)
0+
b10100001010010 ,
#945000
0!
0)
#950000
1!
b10100001010001 $
b1011110 &
1)
0+
b10100001010001 ,
#955000
0!
0)
#960000
1!
b10100001010000 $
b1011111 &
1)
0+
b10100001010000 ,
#965000
0!
0)
#970000
1!
b10100001001111 $
b1100000 &
1)
0+
b10100001001111 ,
#975000
0!
0)
#980000
1!
b10100001001110 $
b1100001 &
1)
0+
b10100001001110 ,
#985000
0!
0)
#990000
1!
b10100001001101 $
b1100010 &
1)
0+
b10100001001101 ,
#995000
0!
0)
#1000000
1!
b10100001001100 $
b1100011 &
1)
0+
b10100001001100 ,
#1005000
0!
0)
#1010000
1!
b10100001001011 $
b1100100 &
1)
0+
b10100001001011 ,
#1015000
0!
0)
#1020000
1!
b10100001001010 $
b1100101 &
1)
0+
b10100001001010 ,
#1025000
0!
0)
#1030000
1!
b10100001001001 $
b1100110 &
1)
0+
b10100001001001 ,
#1035000
0!
0)
#1040000
1!
b10100001001000 $
b1100111 &
1)
0+
b10100001001000 ,
#1045000
0!
0)
#1050000
1!
b10100001000111 $
b1101000 &
1)
0+
b10100001000111 ,
#1055000
0!
0)
#1060000
1!
b10100001000110 $
b1101001 &
1)
0+
b10100001000110 ,
#1065000
0!
0)
#1070000
1!
b10100001000101 $
b1101010 &
1)
0+
b10100001000101 ,
#1075000
0!
0)
#1080000
1!
b10100001000100 $
b1101011 &
1)
0+
b10100001000100 ,
#1085000
0!
0)
#1090000
1!
b10100001000011 $
b1101100 &
1)
0+
b10100001000011 ,
#1095000
0!
0)
#1100000
1!
b10100001000010 $
b1101101 &
1)
0+
b10100001000010 ,
#1105000
0!
0)
#1110000
1!
b10100001000001 $
b1101110 &
1)
0+
b10100001000001 ,
#1115000
0!
0)
#1120000
1!
b10100001000000 $
b1101111 &
1)
0+
b10100001000000 ,
#1125000
0!
0)
#1130000
1!
b10100000111111 $
b1110000 &
1)
0+
b10100000111111 ,
#1135000
0!
0)
#1140000
1!
b10100000111110 $
b1110001 &
1)
0+
b10100000111110 ,
#1145000
0!
0)
#1150000
1!
b10100000111101 $
b1110010 &
1)
0+
b10100000111101 ,
#1155000
0!
0)
#1160000
1!
b10100000111100 $
b1110011 &
1)
0+
b10100000111100 ,
#1165000
0!
0)
#1170000
1!
b10100000111011 $
b1110100 &
1)
0+
b10100000111011 ,
#1175000
0!
0)
#1180000
1!
b10100000111010 $
b1110101 &
1)
0+
b10100000111010 ,
#1185000
0!
0)
#1190000
1!
b10100000111001 $
b1110110 &
1)
0+
b10100000111001 ,
#1195000
0!
0)
#1200000
1!
b10100000111000 $
b1110111 &
1)
0+
b10100000111000 ,
#1205000
0!
0)
#1210000
1!
b10100000110111 $
b1111000 &
1)
0+
b10100000110111 ,
#1215000
0!
0)
#1220000
1!
b10100000110110 $
b1111001 &
1)
0+
b10100000110110 ,
#1225000
0!
0)
#1230000
1!
b10100000110101 $
b1111010 &
1)
0+
b10100000110101 ,
#1235000
0!
0)
#1240000
1!
b10100000110100 $
b1111011 &
1)
0+
b10100000110100 ,
#1245000
0!
0)
#1250000
1!
b10100000110011 $
b1111100 &
1)
0+
b10100000110011 ,
#1255000
0!
0)
#1260000
1!
b10100000110010 $
b1111101 &
1)
0+
b10100000110010 ,
#1265000
0!
0)
#1270000
1!
b10100000110001 $
b1111110 &
1)
0+
b10100000110001 ,
#1275000
0!
0)
#1280000
1!
b10100000110000 $
b1111111 &
1)
0+
b10100000110000 ,
#1285000
0!
0)
#1290000
1!
b10100000101111 $
b10000000 &
1)
0+
b10100000101111 ,
#1295000
0!
0)
#1300000
1!
b10100000101110 $
b10000001 &
1)
0+
b10100000101110 ,
#1305000
0!
0)
#1310000
1!
b10100000101101 $
b10000010 &
1)
0+
b10100000101101 ,
#1315000
0!
0)
#1320000
1!
b10100000101100 $
b10000011 &
1)
0+
b10100000101100 ,
#1325000
0!
0)
#1330000
1!
b10100000101011 $
b10000100 &
1)
0+
b10100000101011 ,
#1335000
0!
0)
#1340000
1!
b10100000101010 $
b10000101 &
1)
0+
b10100000101010 ,
#1345000
0!
0)
#1350000
1!
b10100000101001 $
b10000110 &
1)
0+
b10100000101001 ,
#1355000
0!
0)
#1360000
1!
b10100000101000 $
b10000111 &
1)
0+
b10100000101000 ,
#1365000
0!
0)
#1370000
1!
b10100000100111 $
b10001000 &
1)
0+
b10100000100111 ,
#1375000
0!
0)
#1380000
1!
b10100000100110 $
b10001001 &
1)
0+
b10100000100110 ,
#1385000
0!
0)
#1390000
1!
b10100000100101 $
b10001010 &
1)
0+
b10100000100101 ,
#1395000
0!
0)
#1400000
1!
b10100000100100 $
b10001011 &
1)
0+
b10100000100100 ,
#1405000
0!
0)
#1410000
1!
b10100000100011 $
b10001100 &
1)
0+
b10100000100011 ,
#1415000
0!
0)
#1420000
1!
b10100000100010 $
b10001101 &
1)
0+
b10100000100010 ,
#1425000
0!
0)
#1430000
1!
b10100000100001 $
b10001110 &
1)
0+
b10100000100001 ,
#1435000
0!
0)
#1440000
1!
b10100000100000 $
b10001111 &
1)
0+
b10100000100000 ,
#1445000
0!
0)
#1450000
1!
b10100000011111 $
b10010000 &
1)
0+
b10100000011111 ,
#1455000
0!
0)
#1460000
1!
b10100000011110 $
b10010001 &
1)
0+
b10100000011110 ,
#1465000
0!
0)
#1470000
1!
b10100000011101 $
b10010010 &
1)
0+
b10100000011101 ,
#1475000
0!
0)
#1480000
1!
b10100000011100 $
b10010011 &
1)
0+
b10100000011100 ,
#1485000
0!
0)
#1490000
1!
b10100000011011 $
b10010100 &
1)
0+
b10100000011011 ,
#1495000
0!
0)
#1500000
1!
b10100000011010 $
b10010101 &
1)
0+
b10100000011010 ,
#1505000
0!
0)
#1510000
1!
b10100000011001 $
b10010110 &
1)
0+
b10100000011001 ,
#1515000
0!
0)
#1520000
1!
b10100000011000 $
b10010111 &
1)
0+
b10100000011000 ,
#1525000
0!
0)
#1530000
1!
b10100000010111 $
b10011000 &
1)
0+
b10100000010111 ,
#1535000
0!
0)
#1540000
1!
b10100000010110 $
b10011001 &
1)
0+
b10100000010110 ,
#1545000
0!
0)
#1550000
1!
b10100000010101 $
b10011010 &
1)
0+
b10100000010101 ,
#1555000
0!
0)
#1560000
1!
b10100000010100 $
b10011011 &
1)
0+
b10100000010100 ,
#1565000
0!
0)
#1570000
1!
b10100000010011 $
b10011100 &
1)
0+
b10100000010011 ,
#1575000
0!
0)
#1580000
1!
b10100000010010 $
b10011101 &
1)
0+
b10100000010010 ,
#1585000
0!
0)
#1590000
1!
b10100000010001 $
b10011110 &
1)
0+
b10100000010001 ,
#1595000
0!
0)
#1600000
1!
b10100000010000 $
b10011111 &
1)
0+
b10100000010000 ,
#1605000
0!
0)
#1610000
1!
b10100000001111 $
b10100000 &
1)
0+
b10100000001111 ,
#1615000
0!
0)
#1620000
1!
b10100000001110 $
b10100001 &
1)
0+
b10100000001110 ,
#1625000
0!
0)
#1630000
1!
b10100000001101 $
b10100010 &
1)
0+
b10100000001101 ,
#1635000
0!
0)
#1640000
1!
b10100000001100 $
b10100011 &
1)
0+
b10100000001100 ,
#1645000
0!
0)
#1650000
1!
b10100000001011 $
b10100100 &
1)
0+
b10100000001011 ,
#1655000
0!
0)
#1660000
1!
b10100000001010 $
b10100101 &
1)
0+
b10100000001010 ,
#1665000
0!
0)
#1670000
1!
b10100000001001 $
b10100110 &
1)
0+
b10100000001001 ,
#1675000
0!
0)
#1680000
1!
b10100000001000 $
b10100111 &
1)
0+
b10100000001000 ,
#1685000
0!
0)
#1690000
1!
b10100000000111 $
b10101000 &
1)
0+
b10100000000111 ,
#1695000
0!
0)
#1700000
1!
b10100000000110 $
b10101001 &
1)
0+
b10100000000110 ,
#1705000
0!
0)
#1710000
1!
b10100000000101 $
b10101010 &
1)
0+
b10100000000101 ,
#1715000
0!
0)
#1720000
1!
b10100000000100 $
b10101011 &
1)
0+
b10100000000100 ,
#1725000
0!
0)
#1730000
1!
b10100000000011 $
b10101100 &
1)
0+
b10100000000011 ,
#1735000
0!
0)
#1740000
1!
b10100000000010 $
b10101101 &
1)
0+
b10100000000010 ,
#1745000
0!
0)
#1750000
1!
b10100000000001 $
b10101110 &
1)
0+
b10100000000001 ,
#1755000
0!
0)
#1760000
1!
b10100000000000 $
b10101111 &
1)
0+
b10100000000000 ,
#1765000
0!
0)
#1770000
1!
b10011111111111 $
b10110000 &
1)
0+
b10011111111111 ,
#1775000
0!
0)
#1780000
1!
b10011111111110 $
b10110001 &
1)
0+
b10011111111110 ,
#1785000
0!
0)
#1790000
1!
b10011111111101 $
b10110010 &
1)
0+
b10011111111101 ,
#1795000
0!
0)
#1800000
1!
b10011111111100 $
b10110011 &
1)
0+
b10011111111100 ,
#1805000
0!
0)
#1810000
1!
b10011111111011 $
b10110100 &
1)
0+
b10011111111011 ,
#1815000
0!
0)
#1820000
1!
b10011111111010 $
b10110101 &
1)
0+
b10011111111010 ,
#1825000
0!
0)
#1830000
1!
b10011111111001 $
b10110110 &
1)
0+
b10011111111001 ,
#1835000
0!
0)
#1840000
1!
b10011111111000 $
b10110111 &
1)
0+
b10011111111000 ,
#1845000
0!
0)
#1850000
1!
b10011111110111 $
b10111000 &
1)
0+
b10011111110111 ,
#1855000
0!
0)
#1860000
1!
b10011111110110 $
b10111001 &
1)
0+
b10011111110110 ,
#1865000
0!
0)
#1870000
1!
b10011111110101 $
b10111010 &
1)
0+
b10011111110101 ,
#1875000
0!
0)
#1880000
1!
b10011111110100 $
b10111011 &
1)
0+
b10011111110100 ,
#1885000
0!
0)
#1890000
1!
b10011111110011 $
b10111100 &
1)
0+
b10011111110011 ,
#1895000
0!
0)
#1900000
1!
b10011111110010 $
b10111101 &
1)
0+
b10011111110010 ,
#1905000
0!
0)
#1910000
1!
b10011111110001 $
b10111110 &
1)
0+
b10011111110001 ,
#1915000
0!
0)
#1920000
1!
b10011111110000 $
b10111111 &
1)
0+
b10011111110000 ,
#1925000
0!
0)
#1930000
1!
b10011111101111 $
b11000000 &
1)
0+
b10011111101111 ,
#1935000
0!
0)
#1940000
1!
b10011111101110 $
b11000001 &
1)
0+
b10011111101110 ,
#1945000
0!
0)
#1950000
1!
b10011111101101 $
b11000010 &
1)
0+
b10011111101101 ,
#1955000
0!
0)
#1960000
1!
b10011111101100 $
b11000011 &
1)
0+
b10011111101100 ,
#1965000
0!
0)
#1970000
1!
b10011111101011 $
b11000100 &
1)
0+
b10011111101011 ,
#1975000
0!
0)
#1980000
1!
b10011111101010 $
b11000101 &
1)
0+
b10011111101010 ,
#1985000
0!
0)
#1990000
1!
b10011111101001 $
b11000110 &
1)
0+
b10011111101001 ,
#1995000
0!
0)
#2000000
1!
b10011111101000 $
b11000111 &
1)
0+
b10011111101000 ,
#2005000
0!
0)
#2010000
1!
b10011111100111 $
b11001000 &
1)
0+
b10011111100111 ,
#2015000
0!
0)
#2020000
1!
b10011111100110 $
b11001001 &
1)
0+
b10011111100110 ,
#2025000
0!
0)
#2030000
1!
b10011111100101 $
b11001010 &
1)
0+
b10011111100101 ,
#2035000
0!
0)
#2040000
1!
b10011111100100 $
b11001011 &
1)
0+
b10011111100100 ,
#2045000
0!
0)
#2050000
1!
b10011111100011 $
b11001100 &
1)
0+
b10011111100011 ,
#2055000
0!
0)
#2060000
1!
b10011111100010 $
b11001101 &
1)
0+
b10011111100010 ,
#2065000
0!
0)
#2070000
1!
b10011111100001 $
b11001110 &
1)
0+
b10011111100001 ,
#2075000
0!
0)
#2080000
1!
b10011111100000 $
b11001111 &
1)
0+
b10011111100000 ,
#2085000
0!
0)
#2090000
1!
b10011111011111 $
b11010000 &
1)
0+
b10011111011111 ,
#2095000
0!
0)
#2100000
1!
b10011111011110 $
b11010001 &
1)
0+
b10011111011110 ,
#2105000
0!
0)
#2110000
1!
b10011111011101 $
b11010010 &
1)
0+
b10011111011101 ,
#2115000
0!
0)
#2120000
1!
b10011111011100 $
b11010011 &
1)
0+
b10011111011100 ,
#2125000
0!
0)
#2130000
1!
b10011111011011 $
b11010100 &
1)
0+
b10011111011011 ,
#2135000
0!
0)
#2140000
1!
b10011111011010 $
b11010101 &
1)
0+
b10011111011010 ,
#2145000
0!
0)
#2150000
1!
b10011111011001 $
b11010110 &
1)
0+
b10011111011001 ,
#2155000
0!
0)
#2160000
1!
b10011111011000 $
b11010111 &
1)
0+
b10011111011000 ,
#2165000
0!
0)
#2170000
1!
b10011111010111 $
b11011000 &
1)
0+
b10011111010111 ,
#2175000
0!
0)
#2180000
1!
b10011111010110 $
b11011001 &
1)
0+
b10011111010110 ,
#2185000
0!
0)
#2190000
1!
b10011111010101 $
b11011010 &
1)
0+
b10011111010101 ,
#2195000
0!
0)
#2200000
1!
b10011111010100 $
b11011011 &
1)
0+
b10011111010100 ,
#2205000
0!
0)
#2210000
1!
b10011111010011 $
b11011100 &
1)
0+
b10011111010011 ,
#2215000
0!
0)
#2220000
1!
b10011111010010 $
b11011101 &
1)
0+
b10011111010010 ,
#2225000
0!
0)
#2230000
1!
b10011111010001 $
b11011110 &
1)
0+
b10011111010001 ,
#2235000
0!
0)
#2240000
1!
b10011111010000 $
b11011111 &
1)
0+
b10011111010000 ,
#2245000
0!
0)
#2250000
1!
b10011111001111 $
b11100000 &
1)
0+
b10011111001111 ,
#2255000
0!
0)
#2260000
1!
b10011111001110 $
b11100001 &
1)
0+
b10011111001110 ,
#2265000
0!
0)
#2270000
1!
b10011111001101 $
b11100010 &
1)
0+
b10011111001101 ,
#2275000
0!
0)
#2280000
1!
b10011111001100 $
b11100011 &
1)
0+
b10011111001100 ,
#2285000
0!
0)
#2290000
1!
b10011111001011 $
b11100100 &
1)
0+
b10011111001011 ,
#2295000
0!
0)
#2300000
1!
b10011111001010 $
b11100101 &
1)
0+
b10011111001010 ,
#2305000
0!
0)
#2310000
1!
b10011111001001 $
b11100110 &
1)
0+
b10011111001001 ,
#2315000
0!
0)
#2320000
1!
b10011111001000 $
b11100111 &
1)
0+
b10011111001000 ,
#2325000
0!
0)
#2330000
1!
b10011111000111 $
b11101000 &
1)
0+
b10011111000111 ,
#2335000
0!
0)
#2340000
1!
b10011111000110 $
b11101001 &
1)
0+
b10011111000110 ,
#2345000
0!
0)
#2350000
1!
b10011111000101 $
b11101010 &
1)
0+
b10011111000101 ,
#2355000
0!
0)
#2360000
1!
b10011111000100 $
b11101011 &
1)
0+
b10011111000100 ,
#2365000
0!
0)
#2370000
1!
b10011111000011 $
b11101100 &
1)
0+
b10011111000011 ,
#2375000
0!
0)
#2380000
1!
b10011111000010 $
b11101101 &
1)
0+
b10011111000010 ,
#2385000
0!
0)
#2390000
1!
b10011111000001 $
b11101110 &
1)
0+
b10011111000001 ,
#2395000
0!
0)
#2400000
1!
b10011111000000 $
b11101111 &
1)
0+
b10011111000000 ,
#2405000
0!
0)
#2410000
1!
b10011110111111 $
b11110000 &
1)
0+
b10011110111111 ,
#2415000
0!
0)
#2420000
1!
b10011110111110 $
b11110001 &
1)
0+
b10011110111110 ,
#2425000
0!
0)
#2430000
1!
b10011110111101 $
b11110010 &
1)
0+
b10011110111101 ,
#2435000
0!
0)
#2440000
1!
b10011110111100 $
b11110011 &
1)
0+
b10011110111100 ,
#2445000
0!
0)
#2450000
1!
b10011110111011 $
b11110100 &
1)
0+
b10011110111011 ,
#2455000
0!
0)
#2460000
1!
b10011110111010 $
b11110101 &
1)
0+
b10011110111010 ,
#2465000
0!
0)
#2470000
1!
b10011110111001 $
b11110110 &
1)
0+
b10011110111001 ,
#2475000
0!
0)
#2480000
1!
b10011110111000 $
b11110111 &
1)
0+
b10011110111000 ,
#2485000
0!
0)
#2490000
1!
b10011110110111 $
b11111000 &
1)
0+
b10011110110111 ,
#2495000
0!
0)
#2500000
1!
b10011110110110 $
b11111001 &
1)
0+
b10011110110110 ,
#2505000
0!
0)
#2510000
1!
b10011110110101 $
b11111010 &
1)
0+
b10011110110101 ,
#2515000
0!
0)
#2520000
1!
b10011110110100 $
b11111011 &
1)
0+
b10011110110100 ,
#2525000
0!
0)
#2530000
1!
b10011110110011 $
b11111100 &
1)
0+
b10011110110011 ,
#2535000
0!
0)
#2540000
1!
b10011110110010 $
b11111101 &
1)
0+
b10011110110010 ,
#2545000
0!
0)
#2550000
1!
b10011110110001 $
b11111110 &
1)
0+
b10011110110001 ,
#2555000
0!
0)
#2560000
1!
b10011110110000 $
b11111111 &
1)
0+
b10011110110000 ,
#2565000
0!
0)
#2570000
1!
b10011110101111 $
b100000000 &
1)
0+
b10011110101111 ,
#2575000
0!
0)
