uart_RandT/hdl/uart_transmitter.v
module uart_transmitter(
  input wire [7:0]data,
  input wire baud_rate_signal,
  input wire start,
  input wire rst_n,
  input wire clk,
  output reg uart_tx
);
  reg [10:1] packed_data;
  reg state;
  reg [3:0]bit_counter;
  localparam IDLE = 1'b0;
  localparam TRANSMIT = 1'b1;
  //localparam TRANSMIT_NUMBER = 10;
  localparam ZER0 = 0;
  localparam ONE = 1;
  localparam TEN = 10;

  always @(posedge clk or negedge rst_n) begin
    if (!rst_n) begin
      uart_tx <= ZER0;
      state <= IDLE;
      bit_counter <= TEN;
    end else begin
      packed_data <= {1'b0, data, 1'b1};
      case (state) 
        IDLE: begin
          if (start == ONE) begin
            state <= TRANSMIT;
            uart_tx <= ONE;
            bit_counter <= TEN;
          end else begin
            state <= IDLE;
            uart_tx <= ONE;
            bit_counter <= TEN;
          end
        end
        TRANSMIT: begin
          if (baud_rate_signal == ONE) begin
            if (bit_counter == ZER0) begin
              state <= IDLE;
              uart_tx <= ONE;
              bit_counter <= TEN;
            end else begin
              state <= TRANSMIT;
              uart_tx <= packed_data[bit_counter];
              bit_counter <= bit_counter - 1;
            end
          end else begin
            /*
            if (bit_counter == ZER0) begin
              uart_tx <= ONE;
            end else begin
              uart_tx <= packed_data[bit_counter - 1];
            end
            */
            state <= TRANSMIT;
          end
        end
        default: state <= IDLE;
      endcase
    end 
  end
endmodule

uart_RandT/hdl/baud_rate_generator.v
module baud_rate_generator (
  input wire clk,
  input wire rst_n,
  output reg baud_rate_signal
);

  parameter BAUD_RATE_NUMBER = 20;
  reg [13:0] counter;
  /*
  always @(posedge clk or negedge rst_n) begin
    if (!rst_n) begin
      counter <= BAUD_RATE_NUMBER - 1;
      baud_rate_signal <= 1'b0;
    end else begin
      if (counter == 1) begin
        counter <= counter - 1;
        baud_rate_signal <= 1;
      end else if (counter == 0) begin
        counter <= BAUD_RATE_NUMBER - 1;
        baud_rate_signal <= 0;
      end else begin  
        counter <= counter - 1;
        baud_rate_signal <= 0;
      end
    end
  end
  */
  always @(posedge clk or negedge rst_n) begin
    if (!rst_n) begin
      counter <= BAUD_RATE_NUMBER - 1;
      baud_rate_signal <= 1'b0;
    end else begin
      case (counter)
        14'b00000000000001: begin
          counter <= counter - 1;
          baud_rate_signal <= 0;
        end
        14'b00000000000000: begin
          counter <= BAUD_RATE_NUMBER - 1;
          baud_rate_signal <= 1;
        end
        default: begin
          counter <= counter - 1;
          baud_rate_signal <= 0;
        end
      endcase 
    end
  end

endmodule

uart_transmitter/xsim/uart_transmitter_tb.v
// set the timescale for the simulation
 `timescale 1ns/1ps 
module testbench;  // module of testbench
//  parameter defined
parameter CYCLE = 10; // use CYCLE to describe the clock period
parameter BAUD_RATE_NUMBER = 20;

// localparam
localparam N = 256; 


// input signal use reg
reg clk;
reg rst_n;
reg start;
reg [7:0] data;

// output signal use wire
wire baud_rate_signal;
wire uart_tx;


// interger 
integer j, error;
///// instantiate  module /////
// instantiate the module you finished in following format //
// module_name #(.parameter1(5),.parameter2(3)) unit_name (.port1(...), .port2(...), ...); //
baud_rate_generator baud_rate_generator(
  .clk(clk),
  .rst_n(rst_n),
  .baud_rate_signal(baud_rate_signal)
);

uart_transmitter uart_transmitter(
  .data(data),
  .baud_rate_signal(baud_rate_signal),
  .start(start),
  .rst_n(rst_n),
  .clk(clk),
  .uart_tx(uart_tx)
);
//  dump the waveform of the simulation for fsdb//
/*initial begin
 $fsdbDumpfile("testbench.fsdb"); 
 $fsdbDumpvars;              
end*/

// dump the waveform of the simulation for vcd//
initial begin
  $dumpfile("testbench.vcd");
  $dumpvars("+mda");
end

// there you can read data from the file,and store in the register.
reg [17:0] golden [0:N];
initial begin
  $readmemb("golden.dat",golden);
end


// generate clk 
always #(CYCLE/2) clk = ~clk; 

// System block set only clock,reset signal and the timeout finish. 
initial begin
  clk = 1;
  rst_n = 1;
  start = 0;
  // system reset
  #(CYCLE) rst_n = 0;
  #(CYCLE) rst_n = 1;
  #(CYCLE*2) start = 1;
end

integer k;
task send_uarttx (output reg [9:0] pattern_out);
  begin
    for (k = 9; k >= 0; k = k - 1) begin
      @(posedge baud_rate_signal);
      #(CYCLE*2);
      pattern_out[k] = uart_tx; 
    end
  end
endtask

// output result checking block, control when to sample and verify the result.
integer fp_w;
reg [9:0] correct_data;
reg [9:0] result;

initial begin
// error count
  error = 0;
// Use the same control technique to control when to sample output result.
  wait(rst_n==0);
  wait(rst_n==1);
// adder output for two cycle from input to output
  // you can also write the result to a text file
  fp_w = $fopen("answer.txt");
  for (j = 0; j < N; j = j + 1) begin
    @(posedge clk);
    data = golden[j][17:10];
    correct_data = golden[j][9:0];
    send_uarttx(result);
    if(result !== correct_data) begin
        error = error + 1;
        $display("************* Pattern No.%d is wrong at %t ************", j,$time);
        $display("signal_in = %b, correct data is %b,", data, correct_data);
        $display("but your result is %b !!", result);
      end
      $fdisplay(fp_w, "%b  %b_%b", data, correct_data, result);
    #(CYCLE*20);
  end

  $fclose(fp_w);

  if(error == 0) begin
    $display("Congratulations!! The functionality of your receiver is correct!!");
  end
  else begin
    $display("error !!");
  end 
  #(CYCLE) $finish; 

end

endmodule

uart_transmitter/xsim/testbench.vcd
$date
   Mon Jan 13 07:01:37 2025
$end
$version
  2022.1
$end
$timescale
  1ps
$end
$scope module testbench $end
$var reg 1 ! clk $end
$var reg 1 " rst_n $end
$var reg 1 # start $end
$var reg 8 $ data [7:0] $end
$var wire 1 % baud_rate_signal $end
$var wire 1 & uart_tx $end
$var integer 32 ' j [31:0] $end
$var integer 32 ( error [31:0] $end
$var integer 32 ) k [31:0] $end
$var integer 32 * fp_w [31:0] $end
$var reg 10 + correct_data [9:0] $end
$var reg 10 , result [9:0] $end
$scope module baud_rate_generator $end
$var wire 1 - clk $end
$var wire 1 . rst_n $end
$var reg 1 / baud_rate_signal $end
$var reg 14 0 counter [13:0] $end
$upscope $end
$scope module uart_transmitter $end
$var wire 8 1 data [7:0] $end
$var wire 1 % baud_rate_signal $end
$var wire 1 2 start $end
$var wire 1 3 rst_n $end
$var wire 1 4 clk $end
$var reg 1 5 uart_tx $end
$var reg 10 6 packed_data [9:0] $end
$var reg 1 7 state $end
$var reg 4 8 bit_counter [3:0] $end
$upscope $end
$scope task send_uarttx $end
$var reg 10 9 pattern_out [9:0] $end
$upscope $end
$upscope $end
$enddefinitions $end
#0
$dumpvars
1!
1"
0#
bx $
0%
x&
bx '
b0 (
bx )
bx *
bx +
bx ,
1-
1.
0/
bx 0
bx 1
02
13
14
x5
b0xxxxxxxx1 6
x7
bx 8
bx 9
$end
#5000
0!
0-
04
#10000
1!
0"
0&
1-
0.
0/
b10011 0
03
14
05
07
b1010 8
#15000
0!
0-
04
#20000
1!
1"
1&
b0 '
b10 *
1-
1.
0/
b10010 0
13
14
15
b0xxxxxxxx1 6
07
b1010 8
#25000
0!
0-
04
#30000
1!
b0 $
b1001 )
b1 +
1-
0/
b10001 0
b0 1
14
15
b1 6
07
b1010 8
#35000
0!
0-
04
#40000
1!
1#
1-
0/
b10000 0
12
14
15
b1 6
17
b1010 8
#45000
0!
0-
04
#50000
1!
1-
0/
b1111 0
14
b1 6
17
#55000
0!
0-
04
#60000
1!
1-
0/
b1110 0
14
b1 6
17
#65000
0!
0-
04
#70000
1!
1-
0/
b1101 0
14
b1 6
17
#75000
0!
0-
04
#80000
1!
1-
0/
b1100 0
14
b1 6
17
#85000
0!
0-
04
#90000
1!
1-
0/
b1011 0
14
b1 6
17
#95000
0!
0-
04
#100000
1!
1-
0/
b1010 0
14
b1 6
17
#105000
0!
0-
04
#110000
1!
1-
0/
b1001 0
14
b1 6
17
#115000
0!
0-
04
#120000
1!
1-
0/
b1000 0
14
b1 6
17
#125000
0!
0-
04
#130000
1!
1-
0/
b111 0
14
b1 6
17
#135000
0!
0-
04
#140000
1!
1-
0/
b110 0
14
b1 6
17
#145000
0!
0-
04
#150000
1!
1-
0/
b101 0
14
b1 6
17
#155000
0!
0-
04
#160000
1!
1-
0/
b100 0
14
b1 6
17
#165000
0!
0-
04
#170000
1!
1-
0/
b11 0
14
b1 6
17
#175000
0!
0-
04
#180000
1!
1-
0/
b10 0
14
b1 6
17
#185000
0!
0-
04
#190000
1!
1-
0/
b1 0
14
b1 6
17
#195000
0!
0-
04
#200000
1!
1-
0/
b0 0
14
b1 6
17
#205000
0!
0-
04
#210000
1!
1%
1-
1/
b10011 0
14
b1 6
17
#215000
0!
0-
04
#220000
1!
0%
0&
1-
0/
b10010 0
14
05
b1 6
17
b1001 8
#225000
0!
0-
04
#230000
1!
b1000 )
1-
0/
b10001 0
14
b1 6
17
b0xxxxxxxxx 9
#235000
0!
0-
04
#240000
1!
1-
0/
b10000 0
14
b1 6
17
#245000
0!
0-
04
#250000
1!
1-
0/
b1111 0
14
b1 6
17
#255000
0!
0-
04
#260000
1!
1-
0/
b1110 0
14
b1 6
17
#265000
0!
0-
04
#270000
1!
1-
0/
b1101 0
14
b1 6
17
#275000
0!
0-
04
#280000
1!
1-
0/
b1100 0
14
b1 6
17
#285000
0!
0-
04
#290000
1!
1-
0/
b1011 0
14
b1 6
17
#295000
0!
0-
04
#300000
1!
1-
0/
b1010 0
14
b1 6
17
#305000
0!
0-
04
#310000
1!
1-
0/
b1001 0
14
b1 6
17
#315000
0!
0-
04
#320000
1!
1-
0/
b1000 0
14
b1 6
17
#325000
0!
0-
04
#330000
1!
1-
0/
b111 0
14
b1 6
17
#335000
0!
0-
04
#340000
1!
1-
0/
b110 0
14
b1 6
17
#345000
0!
0-
04
#350000
1!
1-
0/
b101 0
14
b1 6
17
#355000
0!
0-
04
#360000
1!
1-
0/
b100 0
14
b1 6
17
#365000
0!
0-
04
#370000
1!
1-
0/
b11 0
14
b1 6
17
#375000
0!
0-
04
#380000
1!
1-
0/
b10 0
14
b1 6
17
#385000
0!
0-
04
#390000
1!
1-
0/
b1 0
14
b1 6
17
#395000
0!
0-
04
#400000
1!
1-
0/
b0 0
14
b1 6
17
#405000
0!
0-
04
#410000
1!
1%
1-
1/
b10011 0
14
b1 6
17
#415000
0!
0-
04
#420000
1!
0%
1-
0/
b10010 0
14
05
b1 6
17
b1000 8
#425000
0!
0-
04
#430000
1!
b111 )
1-
0/
b10001 0
14
b1 6
17
b0xxxxxxxx 9
#435000
0!
0-
04
#440000
1!
1-
0/
b10000 0
14
b1 6
17
#445000
0!
0-
04
#450000
1!
1-
0/
b1111 0
14
b1 6
17
#455000
0!
0-
04
#460000
1!
1-
0/
b1110 0
14
b1 6
17
#465000
0!
0-
04
#470000
1!
1-
0/
b1101 0
14
b1 6
17
#475000
0!
0-
04
#480000
1!
1-
0/
b1100 0
14
b1 6
17
#485000
0!
0-
04
#490000
1!
1-
0/
b1011 0
14
b1 6
17
#495000
0!
0-
04
#500000
1!
1-
0/
b1010 0
14
b1 6
17
#505000
0!
0-
04
#510000
1!
1-
0/
b1001 0
14
b1 6
17
#515000
0!
0-
04
#520000
1!
1-
0/
b1000 0
14
b1 6
17
#525000
0!
0-
04
#530000
1!
1-
0/
b111 0
14
b1 6
17
#535000
0!
0-
04
#540000
1!
1-
0/
b110 0
14
b1 6
17
#545000
0!
0-
04
#550000
1!
1-
0/
b101 0
14
b1 6
17
#555000
0!
0-
04
#560000
1!
1-
0/
b100 0
14
b1 6
17
#565000
0!
0-
04
#570000
1!
1-
0/
b11 0
14
b1 6
17
#575000
0!
0-
04
#580000
1!
1-
0/
b10 0
14
b1 6
17
#585000
0!
0-
04
#590000
1!
1-
0/
b1 0
14
b1 6
17
#595000
0!
0-
04
#600000
1!
1-
0/
b0 0
14
b1 6
17
#605000
0!
0-
04
#610000
1!
1%
1-
1/
b10011 0
14
b1 6
17
#615000
0!
0-
04
#620000
1!
0%
1-
0/
b10010 0
14
05
b1 6
17
b111 8
#625000
0!
0-
04
#630000
1!
b110 )
1-
0/
b10001 0
14
b1 6
17
b0xxxxxxx 9
#635000
0!
0-
04
#640000
1!
1-
0/
b10000 0
14
b1 6
17
#645000
0!
0-
04
#650000
1!
1-
0/
b1111 0
14
b1 6
17
#655000
0!
0-
04
#660000
1!
1-
0/
b1110 0
14
b1 6
17
#665000
0!
0-
04
#670000
1!
1-
0/
b1101 0
14
b1 6
17
#675000
0!
0-
04
#680000
1!
1-
0/
b1100 0
14
b1 6
17
#685000
0!
0-
04
#690000
1!
1-
0/
b1011 0
14
b1 6
17
#695000
0!
0-
04
#700000
1!
1-
0/
b1010 0
14
b1 6
17
#705000
0!
0-
04
#710000
1!
1-
0/
b1001 0
14
b1 6
17
#715000
0!
0-
04
#720000
1!
1-
0/
b1000 0
14
b1 6
17
#725000
0!
0-
04
#730000
1!
1-
0/
b111 0
14
b1 6
17
#735000
0!
0-
04
#740000
1!
1-
0/
b110 0
14
b1 6
17
#745000
0!
0-
04
#750000
1!
1-
0/
b101 0
14
b1 6
17
#755000
0!
0-
04
#760000
1!
1-
0/
b100 0
14
b1 6
17
#765000
0!
0-
04
#770000
1!
1-
0/
b11 0
14
b1 6
17
#775000
0!
0-
04
#780000
1!
1-
0/
b10 0
14
b1 6
17
#785000
0!
0-
04
#790000
1!
1-
0/
b1 0
14
b1 6
17
#795000
0!
0-
04
#800000
1!
1-
0/
b0 0
14
b1 6
17
#805000
0!
0-
04
#810000
1!
1%
1-
1/
b10011 0
14
b1 6
17
#815000
0!
0-
04
#820000
1!
0%
1-
0/
b10010 0
14
05
b1 6
17
b110 8
#825000
0!
0-
04
#830000
1!
b101 )
1-
0/
b10001 0
14
b1 6
17
b0xxxxxx 9
#835000
0!
0-
04
#840000
1!
1-
0/
b10000 0
14
b1 6
17
#845000
0!
0-
04
#850000
1!
1-
0/
b1111 0
14
b1 6
17
#855000
0!
0-
04
#860000
1!
1-
0/
b1110 0
14
b1 6
17
#865000
0!
0-
04
#870000
1!
1-
0/
b1101 0
14
b1 6
17
#875000
0!
0-
04
#880000
1!
1-
0/
b1100 0
14
b1 6
17
#885000
0!
0-
04
#890000
1!
1-
0/
b1011 0
14
b1 6
17
#895000
0!
0-
04
#900000
1!
1-
0/
b1010 0
14
b1 6
17
#905000
0!
0-
04
#910000
1!
1-
0/
b1001 0
14
b1 6
17
#915000
0!
0-
04
#920000
1!
1-
0/
b1000 0
14
b1 6
17
#925000
0!
0-
04
#930000
1!
1-
0/
b111 0
14
b1 6
17
#935000
0!
0-
04
#940000
1!
1-
0/
b110 0
14
b1 6
17
#945000
0!
0-
04
#950000
1!
1-
0/
b101 0
14
b1 6
17
#955000
0!
0-
04
#960000
1!
1-
0/
b100 0
14
b1 6
17
#965000
0!
0-
04
#970000
1!
1-
0/
b11 0
14
b1 6
17
#975000
0!
0-
04
#980000
1!
1-
0/
b10 0
14
b1 6
17
#985000
0!
0-
04
#990000
1!
1-
0/
b1 0
14
b1 6
17
#995000
0!
0-
04
#1000000
1!
1-
0/
b0 0
14
b1 6
17
#1005000
0!
0-
04
#1010000
1!
1%
1-
1/
b10011 0
14
b1 6
17
#1015000
0!
0-
04
#1020000
1!
0%
1-
0/
b10010 0
14
05
b1 6
17
b101 8
#1025000
0!
0-
04
#1030000
1!
b100 )
1-
0/
b10001 0
14
b1 6
17
b0xxxxx 9
#1035000
0!
0-
04
#1040000
1!
1-
0/
b10000 0
14
b1 6
17
#1045000
0!
0-
04
#1050000
1!
1-
0/
b1111 0
14
b1 6
17
#1055000
0!
0-
04
#1060000
1!
1-
0/
b1110 0
14
b1 6
17
#1065000
0!
0-
04
#1070000
1!
1-
0/
b1101 0
14
b1 6
17
#1075000
0!
0-
04
#1080000
1!
1-
0/
b1100 0
14
b1 6
17
#1085000
0!
0-
04
#1090000
1!
1-
0/
b1011 0
14
b1 6
17
#1095000
0!
0-
04
#1100000
1!
1-
0/
b1010 0
14
b1 6
17
#1105000
0!
0-
04
#1110000
1!
1-
0/
b1001 0
14
b1 6
17
#1115000
0!
0-
04
#1120000
1!
1-
0/
b1000 0
14
b1 6
17
#1125000
0!
0-
04
#1130000
1!
1-
0/
b111 0
14
b1 6
17
#1135000
0!
0-
04
#1140000
1!
1-
0/
b110 0
14
b1 6
17
#1145000
0!
0-
04
#1150000
1!
1-
0/
b101 0
14
b1 6
17
#1155000
0!
0-
04
#1160000
1!
1-
0/
b100 0
14
b1 6
17
#1165000
0!
0-
04
#1170000
1!
1-
0/
b11 0
14
b1 6
17
#1175000
0!
0-
04
#1180000
1!
1-
0/
b10 0
14
b1 6
17
#1185000
0!
0-
04
#1190000
1!
1-
0/
b1 0
14
b1 6
17
#1195000
0!
0-
04
#1200000
1!
1-
0/
b0 0
14
b1 6
17
#1205000
0!
0-
04
#1210000
1!
1%
1-
1/
b10011 0
14
b1 6
17
#1215000
0!
0-
04
#1220000
1!
0%
1-
0/
b10010 0
14
05
b1 6
17
b100 8
#1225000
0!
0-
04
#1230000
1!
b11 )
1-
0/
b10001 0
14
b1 6
17
b0xxxx 9
#1235000
0!
0-
04
#1240000
1!
1-
0/
b10000 0
14
b1 6
17
#1245000
0!
0-
04
#1250000
1!
1-
0/
b1111 0
14
b1 6
17
#1255000
0!
0-
04
#1260000
1!
1-
0/
b1110 0
14
b1 6
17
#1265000
0!
0-
04
#1270000
1!
1-
0/
b1101 0
14
b1 6
17
#1275000
0!
0-
04
#1280000
1!
1-
0/
b1100 0
14
b1 6
17
#1285000
0!
0-
04
#1290000
1!
1-
0/
b1011 0
14
b1 6
17
#1295000
0!
0-
04
#1300000
1!
1-
0/
b1010 0
14
b1 6
17
#1305000
0!
0-
04
#1310000
1!
1-
0/
b1001 0
14
b1 6
17
#1315000
0!
0-
04
#1320000
1!
1-
0/
b1000 0
14
b1 6
17
#1325000
0!
0-
04
#1330000
1!
1-
0/
b111 0
14
b1 6
17
#1335000
0!
0-
04
#1340000
1!
1-
0/
b110 0
14
b1 6
17
#1345000
0!
0-
04
#1350000
1!
1-
0/
b101 0
14
b1 6
17
#1355000
0!
0-
04
#1360000
1!
1-
0/
b100 0
14
b1 6
17
#1365000
0!
0-
04
#1370000
1!
1-
0/
b11 0
14
b1 6
17
#1375000
0!
0-
04
#1380000
1!
1-
0/
b10 0
14
b1 6
17
#1385000
0!
0-
04
#1390000
1!
1-
0/
b1 0
14
b1 6
17
#1395000
0!
0-
04
#1400000
1!
1-
0/
b0 0
14
b1 6
17
#1405000
0!
0-
04
#1410000
1!
1%
1-
1/
b10011 0
14
b1 6
17
#1415000
0!
0-
04
#1420000
1!
0%
1-
0/
b10010 0
14
05
b1 6
17
b11 8
#1425000
0!
0-
04
#1430000
1!
b10 )
1-
0/
b10001 0
14
b1 6
17
b0xxx 9
#1435000
0!
0-
04
#1440000
1!
1-
0/
b10000 0
14
b1 6
17
#1445000
0!
0-
04
#1450000
1!
1-
0/
b1111 0
14
b1 6
17
#1455000
0!
0-
04
#1460000
1!
1-
0/
b1110 0
14
b1 6
17
#1465000
0!
0-
04
#1470000
1!
1-
0/
b1101 0
14
b1 6
17
#1475000
0!
0-
04
#1480000
1!
1-
0/
b1100 0
14
b1 6
17
#1485000
0!
0-
04
#1490000
1!
1-
0/
b1011 0
14
b1 6
17
#1495000
0!
0-
04
#1500000
1!
1-
0/
b1010 0
14
b1 6
17
#1505000
0!
0-
04
#1510000
1!
1-
0/
b1001 0
14
b1 6
17
#1515000
0!
0-
04
#1520000
1!
1-
0/
b1000 0
14
b1 6
17
#1525000
0!
0-
04
#1530000
1!
1-
0/
b111 0
14
b1 6
17
#1535000
0!
0-
04
#1540000
1!
1-
0/
b110 0
14
b1 6
17
#1545000
0!
0-
04
#1550000
1!
1-
0/
b101 0
14
b1 6
17
#1555000
0!
0-
04
#1560000
1!
1-
0/
b100 0
14
b1 6
17
#1565000
0!
0-
04
#1570000
1!
1-
0/
b11 0
14
b1 6
17
#1575000
0!
0-
04
#1580000
1!
1-
0/
b10 0
14
b1 6
17
#1585000
0!
0-
04
#1590000
1!
1-
0/
b1 0
14
b1 6
17
#1595000
0!
0-
04
#1600000
1!
1-
0/
b0 0
14
b1 6
17
#1605000
0!
0-
04
#1610000
1!
1%
1-
1/
b10011 0
14
b1 6
17
#1615000
0!
0-
04
#1620000
1!
0%
1-
0/
b10010 0
14
05
b1 6
17
b10 8
#1625000
0!
0-
04
#1630000
1!
b1 )
1-
0/
b10001 0
14
b1 6
17
b0xx 9
#1635000
0!
0-
04
#1640000
1!
1-
0/
b10000 0
14
b1 6
17
#1645000
0!
0-
04
#1650000
1!
1-
0/
b1111 0
14
b1 6
17
#1655000
0!
0-
04
#1660000
1!
1-
0/
b1110 0
14
b1 6
17
#1665000
0!
0-
04
#1670000
1!
1-
0/
b1101 0
14
b1 6
17
#1675000
0!
0-
04
#1680000
1!
1-
0/
b1100 0
14
b1 6
17
#1685000
0!
0-
04
#1690000
1!
1-
0/
b1011 0
14
b1 6
17
#1695000
0!
0-
04
#1700000
1!
1-
0/
b1010 0
14
b1 6
17
#1705000
0!
0-
04
#1710000
1!
1-
0/
b1001 0
14
b1 6
17
#1715000
0!
0-
04
#1720000
1!
1-
0/
b1000 0
14
b1 6
17
#1725000
0!
0-
04
#1730000
1!
1-
0/
b111 0
14
b1 6
17
#1735000
0!
0-
04
#1740000
1!
1-
0/
b110 0
14
b1 6
17
#1745000
0!
0-
04
#1750000
1!
1-
0/
b101 0
14
b1 6
17
#1755000
0!
0-
04
#1760000
1!
1-
0/
b100 0
14
b1 6
17
#1765000
0!
0-
04
#1770000
1!
1-
0/
b11 0
14
b1 6
17
#1775000
0!
0-
04
#1780000
1!
1-
0/
b10 0
14
b1 6
17
#1785000
0!
0-
04
#1790000
1!
1-
0/
b1 0
14
b1 6
17
#1795000
0!
0-
04
#1800000
1!
1-
0/
b0 0
14
b1 6
17
#1805000
0!
0-
04
#1810000
1!
1%
1-
1/
b10011 0
14
b1 6
17
#1815000
0!
0-
04
#1820000
1!
0%
1-
0/
b10010 0
14
05
b1 6
17
b1 8
#1825000
0!
0-
04
#1830000
1!
b0 )
1-
0/
b10001 0
14
b1 6
17
b0x 9
#1835000
0!
0-
04
#1840000
1!
1-
0/
b10000 0
14
b1 6
17
#1845000
0!
0-
04
#1850000
1!
1-
0/
b1111 0
14
b1 6
17
#1855000
0!
0-
04
#1860000
1!
1-
0/
b1110 0
14
b1 6
17
#1865000
0!
0-
04
#1870000
1!
1-
0/
b1101 0
14
b1 6
17
#1875000
0!
0-
04
#1880000
1!
1-
0/
b1100 0
14
b1 6
17
#1885000
0!
0-
04
#1890000
1!
1-
0/
b1011 0
14
b1 6
17
#1895000
0!
0-
04
#1900000
1!
1-
0/
b1010 0
14
b1 6
17
#1905000
0!
0-
04
#1910000
1!
1-
0/
b1001 0
14
b1 6
17
#1915000
0!
0-
04
#1920000
1!
1-
0/
b1000 0
14
b1 6
17
#1925000
0!
0-
04
#1930000
1!
1-
0/
b111 0
14
b1 6
17
#1935000
0!
0-
04
#1940000
1!
1-
0/
b110 0
14
b1 6
17
#1945000
0!
0-
04
#1950000
1!
1-
0/
b101 0
14
b1 6
17
#1955000
0!
0-
04
#1960000
1!
1-
0/
b100 0
14
b1 6
17
#1965000
0!
0-
04
#1970000
1!
1-
0/
b11 0
14
b1 6
17
#1975000
0!
0-
04
#1980000
1!
1-
0/
b10 0
14
b1 6
17
#1985000
0!
0-
04
#1990000
1!
1-
0/
b1 0
14
b1 6
17
#1995000
0!
0-
04
#2000000
1!
1-
0/
b0 0
14
b1 6
17
#2005000
0!
0-
04
#2010000
1!
1%
1-
1/
b10011 0
14
b1 6
17
#2015000
0!
0-
04
#2020000
1!
0%
1&
1-
0/
b10010 0
14
15
b1 6
17
b0 8
#2025000
0!
0-
04
#2030000
1!
b11111111111111111111111111111111 )
b1 ,
1-
0/
b10001 0
14
b1 6
17
b1 9
#2035000
0!
0-
04
#2040000
1!
1-
0/
b10000 0
14
b1 6
17
#2045000
0!
0-
04
#2050000
1!
1-
0/
b1111 0
14
b1 6
17
#2055000
0!
0-
04
#2060000
1!
1-
0/
b1110 0
14
b1 6
17
#2065000
0!
0-
04
#2070000
1!
1-
0/
b1101 0
14
b1 6
17
#2075000
0!
0-
04
#2080000
1!
1-
0/
b1100 0
14
b1 6
17
#2085000
0!
0-
04
#2090000
1!
1-
0/
b1011 0
14
b1 6
17
#2095000
0!
0-
04
#2100000
1!
1-
0/
b1010 0
14
b1 6
17
#2105000
0!
0-
04
#2110000
1!
1-
0/
b1001 0
14
b1 6
17
#2115000
0!
0-
04
#2120000
1!
1-
0/
b1000 0
14
b1 6
17
#2125000
0!
0-
04
#2130000
1!
1-
0/
b111 0
14
b1 6
17
#2135000
0!
0-
04
#2140000
1!
1-
0/
b110 0
14
b1 6
17
#2145000
0!
0-
04
#2150000
1!
1-
0/
b101 0
14
b1 6
17
#2155000
0!
0-
04
#2160000
1!
1-
0/
b100 0
14
b1 6
17
#2165000
0!
0-
04
#2170000
1!
1-
0/
b11 0
14
b1 6
17
#2175000
0!
0-
04
#2180000
1!
1-
0/
b10 0
14
b1 6
17
#2185000
0!
0-
04
#2190000
1!
1-
0/
b1 0
14
b1 6
17
#2195000
0!
0-
04
#2200000
1!
1-
0/
b0 0
14
b1 6
17
#2205000
0!
0-
04
#2210000
1!
1%
1-
1/
b10011 0
14
b1 6
17
#2215000
0!
0-
04
#2220000
1!
0%
1-
0/
b10010 0
14
15
b1 6
07
b1010 8
#2225000
0!
0-
04
#2230000
1!
b1 $
b1 '
b1001 )
b11 +
1-
0/
b10001 0
b1 1
14
15
b11 6
17
b1010 8
#2235000
0!
0-
04
#2240000
1!
1-
0/
b10000 0
14
b11 6
17
#2245000
0!
0-
04
#2250000
1!
1-
0/
b1111 0
14
b11 6
17
#2255000
0!
0-
04
#2260000
1!
1-
0/
b1110 0
14
b11 6
17
#2265000
0!
0-
04
#2270000
1!
1-
0/
b1101 0
14
b11 6
17
#2275000
0!
0-
04
#2280000
1!
1-
0/
b1100 0
14
b11 6
17
#2285000
0!
0-
04
#2290000
1!
1-
0/
b1011 0
14
b11 6
17
#2295000
0!
0-
04
#2300000
1!
1-
0/
b1010 0
14
b11 6
17
#2305000
0!
0-
04
#2310000
1!
1-
0/
b1001 0
14
b11 6
17
#2315000
0!
0-
04
#2320000
1!
1-
0/
b1000 0
14
b11 6
17
#2325000
0!
0-
04
#2330000
1!
1-
0/
b111 0
14
b11 6
17
#2335000
0!
0-
04
#2340000
1!
1-
0/
b110 0
14
b11 6
17
#2345000
0!
0-
04
#2350000
1!
1-
0/
b101 0
14
b11 6
17
#2355000
0!
0-
04
#2360000
1!
1-
0/
b100 0
14
b11 6
17
#2365000
0!
0-
04
#2370000
1!
1-
0/
b11 0
14
b11 6
17
#2375000
0!
0-
04
#2380000
1!
1-
0/
b10 0
14
b11 6
17
#2385000
0!
0-
04
#2390000
1!
1-
0/
b1 0
14
b11 6
17
#2395000
0!
0-
04
#2400000
1!
1-
0/
b0 0
14
b11 6
17
#2405000
0!
0-
04
#2410000
1!
1%
1-
1/
b10011 0
14
b11 6
17
#2415000
0!
0-
04
#2420000
1!
0%
0&
1-
0/
b10010 0
14
05
b11 6
17
b1001 8
#2425000
0!
0-
04
#2430000
1!
b1000 )
1-
0/
b10001 0
14
b11 6
17
b1 9
#2435000
0!
0-
04
#2440000
1!
1-
0/
b10000 0
14
b11 6
17
#2445000
0!
0-
04
#2450000
1!
1-
0/
b1111 0
14
b11 6
17
#2455000
0!
0-
04
#2460000
1!
1-
0/
b1110 0
14
b11 6
17
#2465000
0!
0-
04
#2470000
1!
1-
0/
b1101 0
14
b11 6
17
#2475000
0!
0-
04
#2480000
1!
1-
0/
b1100 0
14
b11 6
17
#2485000
0!
0-
04
#2490000
1!
1-
0/
b1011 0
14
b11 6
17
#2495000
0!
0-
04
#2500000
1!
1-
0/
b1010 0
14
b11 6
17
#2505000
0!
0-
04
#2510000
1!
1-
0/
b1001 0
14
b11 6
17
#2515000
0!
0-
04
#2520000
1!
1-
0/
b1000 0
14
b11 6
17
#2525000
0!
0-
04
#2530000
1!
1-
0/
b111 0
14
b11 6
17
#2535000
0!
0-
04
#2540000
1!
1-
0/
b110 0
14
b11 6
17
#2545000
0!
0-
04
#2550000
1!
1-
0/
b101 0
14
b11 6
17
#2555000
0!
0-
04
#2560000
1!
1-
0/
b100 0
14
b11 6
17
#2565000
0!
0-
04
#2570000
1!
1-
0/
b11 0
14
b11 6
17
#2575000
0!
0-
04
#2580000
1!
1-
0/
b10 0
14
b11 6
17
#2585000
0!
0-
04
#2590000
1!
1-
0/
b1 0
14
b11 6
17
#2595000
0!
0-
04
#2600000
1!
1-
0/
b0 0
14
b11 6
17
#2605000
0!
0-
04
#2610000
1!
1%
1-
1/
b10011 0
14
b11 6
17
#2615000
0!
0-
04
#2620000
1!
0%
1-
0/
b10010 0
14
05
b11 6
17
b1000 8
#2625000
0!
0-
04
#2630000
1!
b111 )
1-
0/
b10001 0
14
b11 6
17
b1 9
#2635000
0!
0-
04
#2640000
1!
1-
0/
b10000 0
14
b11 6
17
#2645000
0!
0-
04
#2650000
1!
1-
0/
b1111 0
14
b11 6
17
#2655000
0!
0-
04
#2660000
1!
1-
0/
b1110 0
14
b11 6
17
#2665000
0!
0-
04
#2670000
1!
1-
0/
b1101 0
14
b11 6
17
#2675000
0!
0-
04
#2680000
1!
1-
0/
b1100 0
14
b11 6
17
#2685000
0!
0-
04
#2690000
1!
1-
0/
b1011 0
14
b11 6
17
#2695000
0!
0-
04
#2700000
1!
1-
0/
b1010 0
14
b11 6
17
#2705000
0!
0-
04
#2710000
1!
1-
0/
b1001 0
14
b11 6
17
#2715000
0!
0-
04
#2720000
1!
1-
0/
b1000 0
14
b11 6
17
#2725000
0!
0-
04
#2730000
1!
1-
0/
b111 0
14
b11 6
17
#2735000
0!
0-
04
