uart_RandT/hdl/uart_transmitter.v
module uart_transmitter (
  input wire [7:0] data,            // 輸入的 8-bit 資料
  input wire baud_rate_signal,      // 波特率訊號
  input wire start,                 // 傳輸開始訊號
  input wire rst_n,                 // 復位訊號（低有效）
  input wire clk,                   // 時鐘訊號
  output reg uart_tx                // UART 資料輸出
);

  reg [10:0] packed_data;           // 打包的 10-bit 資料（起始位、數據位、停止位）
  reg state, next_state;            // 狀態與下一狀態
  reg [3:0] bit_counter, next_bit_counter; // 位元計數器和下一值
  reg next_uart_tx;                 // 下一時鐘週期的輸出狀態
  localparam IDLE = 1'b0;
  localparam TRANSMIT = 1'b1;

  // 狀態切換與資料更新邏輯（時序邏輯）
  always @(posedge clk or negedge rst_n) begin
    if (!rst_n) begin
      state <= IDLE;
      bit_counter <= 4'd10;
      uart_tx <= 1'b1;              // 默認為高電平
      packed_data <= 11'b0;         // 默認為空
    end else begin
      state <= next_state;
      bit_counter <= next_bit_counter;
      uart_tx <= next_uart_tx;
      if (start && state == IDLE) begin
        packed_data <= {1'b0, data, 1'b1}; // 起始位（0）+ 資料 + 停止位（1）
      end
    end
  end

  // 組合邏輯：計算下一狀態與輸出
  always @(*) begin
    // 預設值
    next_state = state;
    next_bit_counter = bit_counter;
    next_uart_tx = uart_tx;

    case (state)
      IDLE: begin
        next_uart_tx = 1'b1;        // 默認為高電平
        if (start) begin
          next_state = TRANSMIT;
          next_bit_counter = 4'd10;
        end
      end

      TRANSMIT: begin
        if (baud_rate_signal) begin
          if (bit_counter == 0) begin
            next_state = IDLE;      // 傳輸完成，回到空閒狀態
            next_uart_tx = 1'b1;    // 停止位為高電平
          end else begin
            next_bit_counter = bit_counter - 1;
            next_uart_tx = packed_data[bit_counter - 1]; // 輸出當前位元
          end
        end
      end

      default: begin
        next_state = IDLE;
      end
    endcase
  end

endmodule

uart_receiver/baud_rate/hdl/baud_rate_generator.v
module baud_rate_generator (
  input wire clk,
  input wire rst_n,
  output reg baud_rate_signal,
  output reg [13:0] counter
);

  parameter BAUD_RATE_NUMBER = 10416;
  reg baud_rate_next; // 組合邏輯輸出暫存

  // 時序邏輯：只負責時鐘驅動的數值更新
  always @(posedge clk or negedge rst_n) begin
    if (!rst_n) begin
      counter <= BAUD_RATE_NUMBER - 1;
      baud_rate_signal <= 1'b0;
    end else begin
      counter <= (counter == 0) ? BAUD_RATE_NUMBER - 1 : counter - 1;
      baud_rate_signal <= baud_rate_next; // 從組合邏輯取得下一狀態
    end
  end

  // 組合邏輯：計算 baud_rate_signal 的下一狀態
  always @(*) begin
    if (counter == 1) begin
      baud_rate_next = 1'b0;
    end else if (counter == 0) begin
      baud_rate_next = 1'b1;
    end else begin
      baud_rate_next = 1'b0;
    end
  end

endmodule

uart_transmitter/xsim/uart_transmitter_tb.v
// Set the timescale for the simulation
`timescale 1ns/1ps

module testbench;  // Testbench module definition

// Parameter definitions
parameter CYCLE = 10; // Clock period in nanoseconds
parameter BAUD_RATE_NUMBER = 20; // Baud rate scaling factor

// Local parameter definition
localparam N = 256; // Number of test patterns

// Input signals (declared as `reg`)
reg clk;             // Clock signal
reg rst_n;           // Reset signal (active low)
reg start;           // Signal to start transmission
reg [7:0] data;      // 8-bit input data

// Output signals (declared as `wire`)
wire baud_rate_signal; // Baud rate signal
wire uart_tx;          // UART transmitted output signal

// Integer variables
integer j, error; // Loop counter `j` and error counter

// Instantiate modules to be tested
// Instantiate the baud rate generator module
baud_rate_generator baud_rate_generator(
  .clk(clk),
  .rst_n(rst_n),
  .baud_rate_signal(baud_rate_signal)
);

// Instantiate the UART transmitter module
uart_transmitter uart_transmitter(
  .data(data),
  .baud_rate_signal(baud_rate_signal),
  .start(start),
  .rst_n(rst_n),
  .clk(clk),
  .uart_tx(uart_tx)
);

// Dump the waveform of the simulation in VCD format
initial begin
  $dumpfile("testbench.vcd");      // Specify the output VCD file
  $dumpvars("+mda");               // Dump all module variables
end

// Load test patterns from a file into a register array
reg [17:0] golden [0:N]; // Array to store golden patterns
initial begin
  $readmemb("golden.dat", golden); // Read binary patterns from "golden.dat"
end

// Generate the clock signal
always #(CYCLE/2) clk = ~clk; // Toggle clock every half cycle

// System initialization block
initial begin
  clk = 1;        // Initialize clock to 1
  rst_n = 1;      // Initialize reset to active high
  start = 0;      // Set start signal to inactive
  #(CYCLE/2) rst_n = 0;  // Assert reset (active low)
  #(CYCLE) rst_n = 1;    // Deassert reset
  #(CYCLE*2) start = 1;  // Activate start signal after 2 clock cycles
end

// Task to capture UART output bit-by-bit
integer k; // Loop counter for task
task send_uarttx (output reg [9:0] pattern_out);
  begin
    for (k = 9; k >= 0; k = k - 1) begin
      @(posedge baud_rate_signal); // Wait for baud rate signal edge
      #(CYCLE*2);                  // Add delay to synchronize
      pattern_out[k] = uart_tx;    // Capture UART output bit-by-bit
    end
  end
endtask

// Block to verify results and log output
integer fp_w;           // File pointer for writing results
reg [9:0] correct_data; // Expected correct data
reg [9:0] result;       // Captured result from UART output

initial begin
  error = 0; // Initialize error counter

  // Wait for reset to complete
  wait(rst_n == 0);
  wait(rst_n == 1);

  // Open a file to log the output results
  fp_w = $fopen("answer.txt");

  // Loop through all test patterns
  for (j = 0; j < N; j = j + 1) begin
    @(posedge clk); // Wait for the clock edge
    data = golden[j][17:10];      // Extract input data from golden pattern
    correct_data = golden[j][9:0]; // Extract expected output data

    send_uarttx(result);          // Capture the UART output

    // Check if the captured result matches the expected data
    if (result !== correct_data) begin
      error = error + 1; // Increment error counter if mismatch
      $display("************* Pattern No.%d is wrong at %t ************", j, $time);
      $display("signal_in = %b, correct data is %b,", data, correct_data);
      $display("but your result is %b !!", result);
    end

    // Write results to the output file
    $fdisplay(fp_w, "%b  %b_%b", data, correct_data, result);

    #(CYCLE*20); // Wait for baud rate signal to propagate
  end

  $fclose(fp_w); // Close the output file

  // Display final results
  if (error == 0) begin
    $display("Congratulations!! The functionality of your transmitter is correct!!");
  end else begin
    $display("Error detected!!");
  end

  #(CYCLE) $finish; // End the simulation
end

endmodule

uart_transmitter/xsim/testbench.vcd
$date
   Wed Jan 15 02:28:46 2025
$end
$version
  2022.1
$end
$timescale
  1ps
$end
$scope module testbench $end
$var reg 1 ! clk $end
$var reg 1 " rst_n $end
$var reg 1 # start $end
$var reg 8 $ data [7:0] $end
$var wire 1 % baud_rate_signal $end
$var wire 1 & uart_tx $end
$var integer 32 ' j [31:0] $end
$var integer 32 ( error [31:0] $end
$var integer 32 ) k [31:0] $end
$var integer 32 * fp_w [31:0] $end
$var reg 10 + correct_data [9:0] $end
$var reg 10 , result [9:0] $end
$scope module baud_rate_generator $end
$var wire 1 - clk $end
$var wire 1 . rst_n $end
$var reg 1 / baud_rate_signal $end
$var reg 14 0 counter [13:0] $end
$var reg 1 1 baud_rate_next $end
$upscope $end
$scope module uart_transmitter $end
$var wire 8 2 data [7:0] $end
$var wire 1 % baud_rate_signal $end
$var wire 1 3 start $end
$var wire 1 4 rst_n $end
$var wire 1 5 clk $end
$var reg 1 6 uart_tx $end
$var reg 11 7 packed_data [10:0] $end
$var reg 1 8 state $end
$var reg 1 9 next_state $end
$var reg 4 : bit_counter [3:0] $end
$var reg 4 ; next_bit_counter [3:0] $end
$var reg 1 < next_uart_tx $end
$upscope $end
$scope task send_uarttx $end
$var reg 10 = pattern_out [9:0] $end
$upscope $end
$upscope $end
$enddefinitions $end
#0
$dumpvars
1!
1"
0#
bx $
x%
x&
bx '
b0 (
bx )
bx *
bx +
bx ,
1-
1.
x/
bx 0
x1
bx 2
03
14
15
x6
bx 7
08
09
bx :
bx ;
1<
bx =
$end
#5000
0!
0-
05
#10000
1!
0"
0%
1&
1-
0.
0/
b10011 0
01
04
15
16
b0 7
08
b1010 :
b1010 ;
#15000
0!
0-
05
#20000
1!
1"
b0 '
b10 *
1-
1.
0/
b10010 0
14
15
16
08
b1010 :
#25000
0!
0-
05
#30000
1!
b0 $
b1001 )
b1 +
1-
0/
b10001 0
b0 2
15
16
08
b1010 :
#35000
0!
0-
05
#40000
1!
1#
1-
0/
b10000 0
13
15
16
b1 7
18
19
b1010 :
b1010 ;
#45000
0!
0-
05
#50000
1!
1-
0/
b1111 0
15
16
18
b1010 :
#55000
0!
0-
05
#60000
1!
1-
0/
b1110 0
15
16
18
b1010 :
#65000
0!
0-
05
#70000
1!
1-
0/
b1101 0
15
16
18
b1010 :
#75000
0!
0-
05
#80000
1!
1-
0/
b1100 0
15
16
18
b1010 :
#85000
0!
0-
05
#90000
1!
1-
0/
b1011 0
15
16
18
b1010 :
#95000
0!
0-
05
#100000
1!
1-
0/
b1010 0
15
16
18
b1010 :
#105000
0!
0-
05
#110000
1!
1-
0/
b1001 0
15
16
18
b1010 :
#115000
0!
0-
05
#120000
1!
1-
0/
b1000 0
15
16
18
b1010 :
#125000
0!
0-
05
#130000
1!
1-
0/
b111 0
15
16
18
b1010 :
#135000
0!
0-
05
#140000
1!
1-
0/
b110 0
15
16
18
b1010 :
#145000
0!
0-
05
#150000
1!
1-
0/
b101 0
15
16
18
b1010 :
#155000
0!
0-
05
#160000
1!
1-
0/
b100 0
15
16
18
b1010 :
#165000
0!
0-
05
#170000
1!
1-
0/
b11 0
15
16
18
b1010 :
#175000
0!
0-
05
#180000
1!
1-
0/
b10 0
15
16
18
b1010 :
#185000
0!
0-
05
#190000
1!
1-
0/
b1 0
15
16
18
b1010 :
#195000
0!
0-
05
#200000
1!
1-
0/
b0 0
11
15
16
18
b1010 :
#205000
0!
0-
05
#210000
1!
1%
1-
1/
b10011 0
01
15
16
18
b1010 :
b1001 ;
0<
#215000
0!
0-
05
#220000
1!
0%
0&
1-
0/
b10010 0
15
06
18
b1001 :
b1001 ;
#225000
0!
0-
05
#230000
1!
b1000 )
1-
0/
b10001 0
15
06
18
b1001 :
b0xxxxxxxxx =
#235000
0!
0-
05
#240000
1!
1-
0/
b10000 0
15
06
18
b1001 :
#245000
0!
0-
05
#250000
1!
1-
0/
b1111 0
15
06
18
b1001 :
#255000
0!
0-
05
#260000
1!
1-
0/
b1110 0
15
06
18
b1001 :
#265000
0!
0-
05
#270000
1!
1-
0/
b1101 0
15
06
18
b1001 :
#275000
0!
0-
05
#280000
1!
1-
0/
b1100 0
15
06
18
b1001 :
#285000
0!
0-
05
#290000
1!
1-
0/
b1011 0
15
06
18
b1001 :
#295000
0!
0-
05
#300000
1!
1-
0/
b1010 0
15
06
18
b1001 :
#305000
0!
0-
05
#310000
1!
1-
0/
b1001 0
15
06
18
b1001 :
#315000
0!
0-
05
#320000
1!
1-
0/
b1000 0
15
06
18
b1001 :
#325000
0!
0-
05
#330000
1!
1-
0/
b111 0
15
06
18
b1001 :
#335000
0!
0-
05
#340000
1!
1-
0/
b110 0
15
06
18
b1001 :
#345000
0!
0-
05
#350000
1!
1-
0/
b101 0
15
06
18
b1001 :
#355000
0!
0-
05
#360000
1!
1-
0/
b100 0
15
06
18
b1001 :
#365000
0!
0-
05
#370000
1!
1-
0/
b11 0
15
06
18
b1001 :
#375000
0!
0-
05
#380000
1!
1-
0/
b10 0
15
06
18
b1001 :
#385000
0!
0-
05
#390000
1!
1-
0/
b1 0
15
06
18
b1001 :
#395000
0!
0-
05
#400000
1!
1-
0/
b0 0
11
15
06
18
b1001 :
#405000
0!
0-
05
#410000
1!
1%
1-
1/
b10011 0
01
15
06
18
b1001 :
b1000 ;
#415000
0!
0-
05
#420000
1!
0%
1-
0/
b10010 0
15
06
18
b1000 :
b1000 ;
#425000
0!
0-
05
#430000
1!
b111 )
1-
0/
b10001 0
15
06
18
b1000 :
b0xxxxxxxx =
#435000
0!
0-
05
#440000
1!
1-
0/
b10000 0
15
06
18
b1000 :
#445000
0!
0-
05
#450000
1!
1-
0/
b1111 0
15
06
18
b1000 :
#455000
0!
0-
05
#460000
1!
1-
0/
b1110 0
15
06
18
b1000 :
#465000
0!
0-
05
#470000
1!
1-
0/
b1101 0
15
06
18
b1000 :
#475000
0!
0-
05
#480000
1!
1-
0/
b1100 0
15
06
18
b1000 :
#485000
0!
0-
05
#490000
1!
1-
0/
b1011 0
15
06
18
b1000 :
#495000
0!
0-
05
#500000
1!
1-
0/
b1010 0
15
06
18
b1000 :
#505000
0!
0-
05
#510000
1!
1-
0/
b1001 0
15
06
18
b1000 :
#515000
0!
0-
05
#520000
1!
1-
0/
b1000 0
15
06
18
b1000 :
#525000
0!
0-
05
#530000
1!
1-
0/
b111 0
15
06
18
b1000 :
#535000
0!
0-
05
#540000
1!
1-
0/
b110 0
15
06
18
b1000 :
#545000
0!
0-
05
#550000
1!
1-
0/
b101 0
15
06
18
b1000 :
#555000
0!
0-
05
#560000
1!
1-
0/
b100 0
15
06
18
b1000 :
#565000
0!
0-
05
#570000
1!
1-
0/
b11 0
15
06
18
b1000 :
#575000
0!
0-
05
#580000
1!
1-
0/
b10 0
15
06
18
b1000 :
#585000
0!
0-
05
#590000
1!
1-
0/
b1 0
15
06
18
b1000 :
#595000
0!
0-
05
#600000
1!
1-
0/
b0 0
11
15
06
18
b1000 :
#605000
0!
0-
05
#610000
1!
1%
1-
1/
b10011 0
01
15
06
18
b1000 :
b111 ;
#615000
0!
0-
05
#620000
1!
0%
1-
0/
b10010 0
15
06
18
b111 :
b111 ;
#625000
0!
0-
05
#630000
1!
b110 )
1-
0/
b10001 0
15
06
18
b111 :
b0xxxxxxx =
#635000
0!
0-
05
#640000
1!
1-
0/
b10000 0
15
06
18
b111 :
#645000
0!
0-
05
#650000
1!
1-
0/
b1111 0
15
06
18
b111 :
#655000
0!
0-
05
#660000
1!
1-
0/
b1110 0
15
06
18
b111 :
#665000
0!
0-
05
#670000
1!
1-
0/
b1101 0
15
06
18
b111 :
#675000
0!
0-
05
#680000
1!
1-
0/
b1100 0
15
06
18
b111 :
#685000
0!
0-
05
#690000
1!
1-
0/
b1011 0
15
06
18
b111 :
#695000
0!
0-
05
#700000
1!
1-
0/
b1010 0
15
06
18
b111 :
#705000
0!
0-
05
#710000
1!
1-
0/
b1001 0
15
06
18
b111 :
#715000
0!
0-
05
#720000
1!
1-
0/
b1000 0
15
06
18
b111 :
#725000
0!
0-
05
#730000
1!
1-
0/
b111 0
15
06
18
b111 :
#735000
0!
0-
05
#740000
1!
1-
0/
b110 0
15
06
18
b111 :
#745000
0!
0-
05
#750000
1!
1-
0/
b101 0
15
06
18
b111 :
#755000
0!
0-
05
#760000
1!
1-
0/
b100 0
15
06
18
b111 :
#765000
0!
0-
05
#770000
1!
1-
0/
b11 0
15
06
18
b111 :
#775000
0!
0-
05
#780000
1!
1-
0/
b10 0
15
06
18
b111 :
#785000
0!
0-
05
#790000
1!
1-
0/
b1 0
15
06
18
b111 :
#795000
0!
0-
05
#800000
1!
1-
0/
b0 0
11
15
06
18
b111 :
#805000
0!
0-
05
#810000
1!
1%
1-
1/
b10011 0
01
15
06
18
b111 :
b110 ;
#815000
0!
0-
05
#820000
1!
0%
1-
0/
b10010 0
15
06
18
b110 :
b110 ;
#825000
0!
0-
05
#830000
1!
b101 )
1-
0/
b10001 0
15
06
18
b110 :
b0xxxxxx =
#835000
0!
0-
05
#840000
1!
1-
0/
b10000 0
15
06
18
b110 :
#845000
0!
0-
05
#850000
1!
1-
0/
b1111 0
15
06
18
b110 :
#855000
0!
0-
05
#860000
1!
1-
0/
b1110 0
15
06
18
b110 :
#865000
0!
0-
05
#870000
1!
1-
0/
b1101 0
15
06
18
b110 :
#875000
0!
0-
05
#880000
1!
1-
0/
b1100 0
15
06
18
b110 :
#885000
0!
0-
05
#890000
1!
1-
0/
b1011 0
15
06
18
b110 :
#895000
0!
0-
05
#900000
1!
1-
0/
b1010 0
15
06
18
b110 :
#905000
0!
0-
05
#910000
1!
1-
0/
b1001 0
15
06
18
b110 :
#915000
0!
0-
05
#920000
1!
1-
0/
b1000 0
15
06
18
b110 :
#925000
0!
0-
05
#930000
1!
1-
0/
b111 0
15
06
18
b110 :
#935000
0!
0-
05
#940000
1!
1-
0/
b110 0
15
06
18
b110 :
#945000
0!
0-
05
#950000
1!
1-
0/
b101 0
15
06
18
b110 :
#955000
0!
0-
05
#960000
1!
1-
0/
b100 0
15
06
18
b110 :
#965000
0!
0-
05
#970000
1!
1-
0/
b11 0
15
06
18
b110 :
#975000
0!
0-
05
#980000
1!
1-
0/
b10 0
15
06
18
b110 :
#985000
0!
0-
05
#990000
1!
1-
0/
b1 0
15
06
18
b110 :
#995000
0!
0-
05
#1000000
1!
1-
0/
b0 0
11
15
06
18
b110 :
#1005000
0!
0-
05
#1010000
1!
1%
1-
1/
b10011 0
01
15
06
18
b110 :
b101 ;
#1015000
0!
0-
05
#1020000
1!
0%
1-
0/
b10010 0
15
06
18
b101 :
b101 ;
#1025000
0!
0-
05
#1030000
1!
b100 )
1-
0/
b10001 0
15
06
18
b101 :
b0xxxxx =
#1035000
0!
0-
05
#1040000
1!
1-
0/
b10000 0
15
06
18
b101 :
#1045000
0!
0-
05
#1050000
1!
1-
0/
b1111 0
15
06
18
b101 :
#1055000
0!
0-
05
#1060000
1!
1-
0/
b1110 0
15
06
18
b101 :
#1065000
0!
0-
05
#1070000
1!
1-
0/
b1101 0
15
06
18
b101 :
#1075000
0!
0-
05
#1080000
1!
1-
0/
b1100 0
15
06
18
b101 :
#1085000
0!
0-
05
#1090000
1!
1-
0/
b1011 0
15
06
18
b101 :
#1095000
0!
0-
05
#1100000
1!
1-
0/
b1010 0
15
06
18
b101 :
#1105000
0!
0-
05
#1110000
1!
1-
0/
b1001 0
15
06
18
b101 :
#1115000
0!
0-
05
#1120000
1!
1-
0/
b1000 0
15
06
18
b101 :
#1125000
0!
0-
05
#1130000
1!
1-
0/
b111 0
15
06
18
b101 :
#1135000
0!
0-
05
#1140000
1!
1-
0/
b110 0
15
06
18
b101 :
#1145000
0!
0-
05
#1150000
1!
1-
0/
b101 0
15
06
18
b101 :
#1155000
0!
0-
05
#1160000
1!
1-
0/
b100 0
15
06
18
b101 :
#1165000
0!
0-
05
#1170000
1!
1-
0/
b11 0
15
06
18
b101 :
#1175000
0!
0-
05
#1180000
1!
1-
0/
b10 0
15
06
18
b101 :
#1185000
0!
0-
05
#1190000
1!
1-
0/
b1 0
15
06
18
b101 :
#1195000
0!
0-
05
#1200000
1!
1-
0/
b0 0
11
15
06
18
b101 :
#1205000
0!
0-
05
#1210000
1!
1%
1-
1/
b10011 0
01
15
06
18
b101 :
b100 ;
#1215000
0!
0-
05
#1220000
1!
0%
1-
0/
b10010 0
15
06
18
b100 :
b100 ;
#1225000
0!
0-
05
#1230000
1!
b11 )
1-
0/
b10001 0
15
06
18
b100 :
b0xxxx =
#1235000
0!
0-
05
#1240000
1!
1-
0/
b10000 0
15
06
18
b100 :
#1245000
0!
0-
05
#1250000
1!
1-
0/
b1111 0
15
06
18
b100 :
#1255000
0!
0-
05
#1260000
1!
1-
0/
b1110 0
15
06
18
b100 :
#1265000
0!
0-
05
#1270000
1!
1-
0/
b1101 0
15
06
18
b100 :
#1275000
0!
0-
05
#1280000
1!
1-
0/
b1100 0
15
06
18
b100 :
#1285000
0!
0-
05
#1290000
1!
1-
0/
b1011 0
15
06
18
b100 :
#1295000
0!
0-
05
#1300000
1!
1-
0/
b1010 0
15
06
18
b100 :
#1305000
0!
0-
05
#1310000
1!
1-
0/
b1001 0
15
06
18
b100 :
#1315000
0!
0-
05
#1320000
1!
1-
0/
b1000 0
15
06
18
b100 :
#1325000
0!
0-
05
#1330000
1!
1-
0/
b111 0
15
06
18
b100 :
#1335000
0!
0-
05
#1340000
1!
1-
0/
b110 0
15
06
18
b100 :
#1345000
0!
0-
05
#1350000
1!
1-
0/
b101 0
15
06
18
b100 :
#1355000
0!
0-
05
#1360000
1!
1-
0/
b100 0
15
06
18
b100 :
#1365000
0!
0-
05
#1370000
1!
1-
0/
b11 0
15
06
18
b100 :
#1375000
0!
0-
05
#1380000
1!
1-
0/
b10 0
15
06
18
b100 :
#1385000
0!
0-
05
#1390000
1!
1-
0/
b1 0
15
06
18
b100 :
#1395000
0!
0-
05
#1400000
1!
1-
0/
b0 0
11
15
06
18
b100 :
#1405000
0!
0-
05
#1410000
1!
1%
1-
1/
b10011 0
01
15
06
18
b100 :
b11 ;
#1415000
0!
0-
05
#1420000
1!
0%
1-
0/
b10010 0
15
06
18
b11 :
b11 ;
#1425000
0!
0-
05
#1430000
1!
b10 )
1-
0/
b10001 0
15
06
18
b11 :
b0xxx =
#1435000
0!
0-
05
#1440000
1!
1-
0/
b10000 0
15
06
18
b11 :
#1445000
0!
0-
05
#1450000
1!
1-
0/
b1111 0
15
06
18
b11 :
#1455000
0!
0-
05
#1460000
1!
1-
0/
b1110 0
15
06
18
b11 :
#1465000
0!
0-
05
#1470000
1!
1-
0/
b1101 0
15
06
18
b11 :
#1475000
0!
0-
05
#1480000
1!
1-
0/
b1100 0
15
06
18
b11 :
#1485000
0!
0-
05
#1490000
1!
1-
0/
b1011 0
15
06
18
b11 :
#1495000
0!
0-
05
#1500000
1!
1-
0/
b1010 0
15
06
18
b11 :
#1505000
0!
0-
05
#1510000
1!
1-
0/
b1001 0
15
06
18
b11 :
#1515000
0!
0-
05
#1520000
1!
1-
0/
b1000 0
15
06
18
b11 :
#1525000
0!
0-
05
#1530000
1!
1-
0/
b111 0
15
06
18
b11 :
#1535000
0!
0-
05
#1540000
1!
1-
0/
b110 0
15
06
18
b11 :
#1545000
0!
0-
05
#1550000
1!
1-
0/
b101 0
15
06
18
b11 :
#1555000
0!
0-
05
#1560000
1!
1-
0/
b100 0
15
06
18
b11 :
#1565000
0!
0-
05
#1570000
1!
1-
0/
b11 0
15
06
18
b11 :
#1575000
0!
0-
05
#1580000
1!
1-
0/
b10 0
15
06
18
b11 :
#1585000
0!
0-
05
#1590000
1!
1-
0/
b1 0
15
06
18
b11 :
#1595000
0!
0-
05
#1600000
1!
1-
0/
b0 0
11
15
06
18
b11 :
#1605000
0!
0-
05
#1610000
1!
1%
1-
1/
b10011 0
01
15
06
18
b11 :
b10 ;
#1615000
0!
0-
05
#1620000
1!
0%
1-
0/
b10010 0
15
06
18
b10 :
b10 ;
#1625000
0!
0-
05
#1630000
1!
b1 )
1-
0/
b10001 0
15
06
18
b10 :
b0xx =
#1635000
0!
0-
05
#1640000
1!
1-
0/
b10000 0
15
06
18
b10 :
#1645000
0!
0-
05
#1650000
1!
1-
0/
b1111 0
15
06
18
b10 :
#1655000
0!
0-
05
#1660000
1!
1-
0/
b1110 0
15
06
18
b10 :
#1665000
0!
0-
05
#1670000
1!
1-
0/
b1101 0
15
06
18
b10 :
#1675000
0!
0-
05
#1680000
1!
1-
0/
b1100 0
15
06
18
b10 :
#1685000
0!
0-
05
#1690000
1!
1-
0/
b1011 0
15
06
18
b10 :
#1695000
0!
0-
05
#1700000
1!
1-
0/
b1010 0
15
06
18
b10 :
#1705000
0!
0-
05
#1710000
1!
1-
0/
b1001 0
15
06
18
b10 :
#1715000
0!
0-
05
#1720000
1!
1-
0/
b1000 0
15
06
18
b10 :
#1725000
0!
0-
05
#1730000
1!
1-
0/
b111 0
15
06
18
b10 :
#1735000
0!
0-
05
#1740000
1!
1-
0/
b110 0
15
06
18
b10 :
#1745000
0!
0-
05
#1750000
1!
1-
0/
b101 0
15
06
18
b10 :
#1755000
0!
0-
05
#1760000
1!
1-
0/
b100 0
15
06
18
b10 :
#1765000
0!
0-
05
#1770000
1!
1-
0/
b11 0
15
06
18
b10 :
#1775000
0!
0-
05
#1780000
1!
1-
0/
b10 0
15
06
18
b10 :
#1785000
0!
0-
05
#1790000
1!
1-
0/
b1 0
15
06
18
b10 :
#1795000
0!
0-
05
#1800000
1!
1-
0/
b0 0
11
15
06
18
b10 :
#1805000
0!
0-
05
#1810000
1!
1%
1-
1/
b10011 0
01
15
06
18
b10 :
b1 ;
#1815000
0!
0-
05
#1820000
1!
0%
1-
0/
b10010 0
15
06
18
b1 :
b1 ;
0<
#1825000
0!
0-
05
#1830000
1!
b0 )
1-
0/
b10001 0
15
06
18
b1 :
b0x =
#1835000
0!
0-
05
#1840000
1!
1-
0/
b10000 0
15
06
18
b1 :
#1845000
0!
0-
05
#1850000
1!
1-
0/
b1111 0
15
06
18
b1 :
#1855000
0!
0-
05
#1860000
1!
1-
0/
b1110 0
15
06
18
b1 :
#1865000
0!
0-
05
#1870000
1!
1-
0/
b1101 0
15
06
18
b1 :
#1875000
0!
0-
05
#1880000
1!
1-
0/
b1100 0
15
06
18
b1 :
#1885000
0!
0-
05
#1890000
1!
1-
0/
b1011 0
15
06
18
b1 :
#1895000
0!
0-
05
#1900000
1!
1-
0/
b1010 0
15
06
18
b1 :
#1905000
0!
0-
05
#1910000
1!
1-
0/
b1001 0
15
06
18
b1 :
#1915000
0!
0-
05
#1920000
1!
1-
0/
b1000 0
15
06
18
b1 :
#1925000
0!
0-
05
#1930000
1!
1-
0/
b111 0
15
06
18
b1 :
#1935000
0!
0-
05
#1940000
1!
1-
0/
b110 0
15
06
18
b1 :
#1945000
0!
0-
05
#1950000
1!
1-
0/
b101 0
15
06
18
b1 :
#1955000
0!
0-
05
#1960000
1!
1-
0/
b100 0
15
06
18
b1 :
#1965000
0!
0-
05
#1970000
1!
1-
0/
b11 0
15
06
18
b1 :
#1975000
0!
0-
05
#1980000
1!
1-
0/
b10 0
15
06
18
b1 :
#1985000
0!
0-
05
#1990000
1!
1-
0/
b1 0
15
06
18
b1 :
#1995000
0!
0-
05
#2000000
1!
1-
0/
b0 0
11
15
06
18
b1 :
#2005000
0!
0-
05
#2010000
1!
1%
1-
1/
b10011 0
01
15
06
18
b1 :
b0 ;
1<
#2015000
0!
0-
05
#2020000
1!
0%
1&
1-
0/
b10010 0
15
16
18
19
b0 :
b0 ;
#2025000
0!
0-
05
#2030000
1!
b11111111111111111111111111111111 )
b1 ,
1-
0/
b10001 0
15
16
18
b0 :
b1 =
#2035000
0!
0-
05
#2040000
1!
1-
0/
b10000 0
15
16
18
b0 :
#2045000
0!
0-
05
#2050000
1!
1-
0/
b1111 0
15
16
18
b0 :
#2055000
0!
0-
05
#2060000
1!
1-
0/
b1110 0
15
16
18
b0 :
#2065000
0!
0-
05
#2070000
1!
1-
0/
b1101 0
15
16
18
b0 :
#2075000
0!
0-
05
#2080000
1!
1-
0/
b1100 0
15
16
18
b0 :
#2085000
0!
0-
05
#2090000
1!
1-
0/
b1011 0
15
16
18
b0 :
#2095000
0!
0-
05
#2100000
1!
1-
0/
b1010 0
15
16
18
b0 :
#2105000
0!
0-
05
#2110000
1!
1-
0/
b1001 0
15
16
18
b0 :
#2115000
0!
0-
05
#2120000
1!
1-
0/
b1000 0
15
16
18
b0 :
#2125000
0!
0-
05
#2130000
1!
1-
0/
b111 0
15
16
18
b0 :
#2135000
0!
0-
05
#2140000
1!
1-
0/
b110 0
15
16
18
b0 :
#2145000
0!
0-
05
#2150000
1!
1-
0/
b101 0
15
16
18
b0 :
#2155000
0!
0-
05
#2160000
1!
1-
0/
b100 0
15
16
18
b0 :
#2165000
0!
0-
05
#2170000
1!
1-
0/
b11 0
15
16
18
b0 :
#2175000
0!
0-
05
#2180000
1!
1-
0/
b10 0
15
16
18
b0 :
#2185000
0!
0-
05
#2190000
1!
1-
0/
b1 0
15
16
18
b0 :
#2195000
0!
0-
05
#2200000
1!
1-
0/
b0 0
11
15
16
18
b0 :
#2205000
0!
0-
05
#2210000
1!
1%
1-
1/
b10011 0
01
15
16
18
09
b0 :
b0 ;
#2215000
0!
0-
05
#2220000
1!
0%
1-
0/
b10010 0
15
16
08
19
b0 :
b1010 ;
#2225000
0!
0-
05
#2230000
1!
b1 $
b1 '
b1001 )
b11 +
1-
0/
b10001 0
b1 2
15
16
b11 7
18
b1010 :
b1010 ;
#2235000
0!
0-
05
#2240000
1!
1-
0/
b10000 0
15
16
18
b1010 :
#2245000
0!
0-
05
#2250000
1!
1-
0/
b1111 0
15
16
18
b1010 :
#2255000
0!
0-
05
#2260000
1!
1-
0/
b1110 0
15
16
18
b1010 :
#2265000
0!
0-
05
#2270000
1!
1-
0/
b1101 0
15
16
18
b1010 :
#2275000
0!
0-
05
#2280000
1!
1-
0/
b1100 0
15
16
18
b1010 :
#2285000
0!
0-
05
#2290000
1!
1-
0/
b1011 0
15
16
18
b1010 :
#2295000
0!
0-
05
#2300000
1!
1-
0/
b1010 0
15
16
18
b1010 :
#2305000
0!
0-
05
#2310000
1!
1-
0/
b1001 0
15
16
18
b1010 :
#2315000
0!
0-
05
#2320000
1!
1-
0/
b1000 0
15
16
18
b1010 :
#2325000
0!
0-
05
#2330000
1!
1-
0/
b111 0
15
16
18
b1010 :
#2335000
0!
0-
05
#2340000
1!
1-
0/
b110 0
15
16
18
b1010 :
#2345000
0!
0-
05
#2350000
1!
1-
0/
b101 0
15
16
18
b1010 :
#2355000
0!
0-
05
#2360000
1!
1-
0/
b100 0
15
16
18
b1010 :
#2365000
0!
0-
05
#2370000
1!
1-
0/
b11 0
15
16
18
b1010 :
#2375000
0!
0-
05
#2380000
1!
1-
0/
b10 0
15
16
18
b1010 :
#2385000
0!
0-
05
#2390000
1!
1-
0/
b1 0
15
16
18
b1010 :
#2395000
0!
0-
05
#2400000
1!
1-
0/
b0 0
11
15
16
18
b1010 :
#2405000
0!
0-
05
#2410000
1!
1%
1-
1/
b10011 0
01
15
16
18
b1010 :
b1001 ;
0<
#2415000
0!
0-
05
#2420000
1!
0%
0&
1-
0/
b10010 0
15
06
18
b1001 :
b1001 ;
#2425000
0!
0-
05
#2430000
1!
b1000 )
1-
0/
b10001 0
15
06
18
b1001 :
b1 =
#2435000
0!
0-
05
#2440000
1!
1-
0/
b10000 0
15
06
18
b1001 :
#2445000
0!
0-
05
#2450000
1!
1-
0/
b1111 0
15
06
18
b1001 :
